Workbook

Sheet Glosario
A1: 1. Gastos directos | B1: Son aquellos que están directamente relacionados con la fabricación del producto o prestación del servicio.
A2: 2. Gastos indirectos | B2: Son aquellos que no están directamente relacionados con la producción, pero son necesarios para el funcionamiento del negocio.
A3: 3. Gastos fijos | B3: Son los gastos que no cambian con el nivel de producción o actividad del negocio. Se mantienen constantes en el corto plazo.
A4: 4. Gastos variables | B4: Son los gastos que fluctúan directamente con el nivel de producción o ventas.
A5: 5. Gastos administrativos | B5: Son los gastos relacionados con la gestión y operación del negocio, que no están vinculados directamente a la producción.
A6: 6. Gastos financieros | B6: Son los costos relacionados con la obtención y uso de recursos financieros.
A7: 7. Gastos de ventas | B7: Son aquellos que se generan al comercializar y distribuir el producto.

Sheet Balances
A1: Balances de requerimientos
C3: Activos que se gestionan en el largo plazo (activos fijos) que reptresentan parte de la inversión que se realiza en un primer momento para poder operar durante un periodo de mediano (5 años) o largo plazo (10 años). | V3: Activos que se gestionan en el corto plazo (activo circulante) que varían en función del volumen de producción y que pueden fluctuar durante periodos cortos de tiempo, por ejemplo en negocios que se caracterizan por ser estacionales)
C5: BALANCE DE MAQUINARIA Y EQUIPO | L5: BALANCE DE OBRA FÍSICA | V5: BALANCE DE PERSONAL | Z5: BALANCE DE INSUMOS
B6: Clasificación | C6: ITEM | D6: Cantidad | E6: Costo unitario | F6: Costo total | G6: Vida útil | H6: Valor de liquidación | I6: Ingreso total | K6: Clasificación | L6: ITEM | M6: Unidad de medida | N6: Cantidad (dimensión) | O6: Costo unitario | P6: Costo total | Q6: Vida útil | R6: Valor residual | S6: Ingreso total | U6: Clasificación | V6: Puesto | W6: Sueldo mensual | Y6: Clasificación | Z6: MATERIAL | AA6: Unidad de medida | AB6: Cantidad | AC6: Costo unitario | AD6: Total
C7: Sierra de mesa o sierra circular industrial | D7: 1 | E7: 30000 | F7: =D7*E7 -> 30000 | G7: 10 | H7: =0.1*E7 -> 3000 | I7: =H7*D7 -> 3000 | L7: Local o bodega | M7: m2 (200) | N7: 1 | O7: 2400000 | P7: =N7*O7 -> 2400000 | Q7: 10 | S7: =R7*N7 -> 0 | V7: Carpintero | W7: 8000 | Z7: Madera | AA7: Metro | AB7: 1 | AC7: 150 | AD7: =AB7*AC7 -> 150
C8: Sierra ingleteadora | D8: 1 | E8: 12000 | F8: =D8*E8 -> 12000 | G8: 10 | H8: =0.1*E8 -> 1200 | I8: =H8*D8 -> 1200 | L8: Baños | M8: m2 (4) | N8: 2 | O8: 45000 | P8: =N8*O8 -> 90000 | Q8: 10 | S8: =R8*N8 -> 0 | V8: Operador de maquinaria | W8: 9000 | Z8: MDF (Fibra densidad media) | AA8: Metro | AB8: 1 | AC8: 400 | AD8: =AB8*AC8 -> 400
C9: Router o fresadora de madera | D9: 1 | E9: 18000 | F9: =D9*E9 -> 18000 | G9: 10 | H9: =0.1*E9 -> 1800 | I9: =H9*D9 -> 1800 | L9: Cocina | M9: m2 (20) | N9: 1 | O9: 80000 | P9: =N9*O9 -> 80000 | Q9: 10 | S9: =R9*N9 -> 0 | V9: Técnico de mantenimiento | W9: 10000 | Z9: Pegamento | AA9: Litro | AB9: 1 | AC9: 140 | AD9: =AB9*AC9 -> 140
C10: Lijadora de banda y disco | D10: 1 | E10: 7000 | F10: =D10*E10 -> 7000 | G10: 10 | H10: =0.1*E10 -> 700 | I10: =H10*D10 -> 700 | L10: Almacén | M10: m2 (100) | N10: 1 | O10: 1200000 | P10: =N10*O10 -> 1200000 | Q10: 10 | S10: =R10*N10 -> 0 | V10: Técnico en acabados | W10: 8400 | Z10: Clavos | AA10: Kg | AB10: 1 | AC10: 90 | AD10: =AB10*AC10 -> 90
C11: Compresor de aire con pistola de clavado | D11: 1 | E11: 8500 | F11: =D11*E11 -> 8500 | G11: 10 | H11: =0.1*E11 -> 850 | I11: =H11*D11 -> 850 | L11: Terreno | M11: m2 (400) | N11: 1 | O11: 2000000 | P11: =N11*O11 -> 2000000 | Q11: 10 | S11: =R11*N11 -> 0 | V11: Inspector de calidad | W11: 8000 | Z11: Grapas | AA11: Kg | AB11: 1 | AC11: 100 | AD11: =AB11*AC11 -> 100
C12: Prensas de ensamblaje | D12: 1 | E12: 6500 | F12: =D12*E12 -> 6500 | G12: 10 | H12: =0.1*E12 -> 650 | I12: =H12*D12 -> 650 | P12: =SUM(P7:P11) -> 5770000 | S12: =SUM(S7:S11) -> 0 | V12: Supervisor de producción | W12: 10000 | Z12: Lija | AA12: Paquete (10) | AB12: 1 | AC12: 200 | AD12: =AB12*AC12 -> 200
C13: Cabina de pintura o barnizado | D13: 1 | E13: 28000 | F13: =D13*E13 -> 28000 | G13: 10 | H13: =0.1*E13 -> 2800 | I13: =H13*D13 -> 2800 | V13: Asistente administrativo | W13: 8500 | Z13: Pintura o barniz | AA13: Litro | AB13: 1 | AC13: 240 | AD13: =AB13*AC13 -> 240
C14: Equipo de pulido y cepillado | D14: 1 | E14: 13500 | F14: =D14*E14 -> 13500 | G14: 10 | H14: =0.1*E14 -> 1350 | I14: =H14*D14 -> 1350 | V14: Encargado de ventas y distribución | W14: 10000 | Z14: Rollo de latex | AA14: Pieza | AB14: 1 | AC14: 80 | AD14: =AB14*AC14 -> 80
C15: Calibrador y escuadras de precisión | D15: 1 | E15: 4500 | F15: =D15*E15 -> 4500 | G15: 10 | H15: =0.1*E15 -> 450 | I15: =H15*D15 -> 450 | V15: Personal de limpieza | W15: 6000 | Z15: Prime o sellador de madera | AA15: Litro | AB15: 1 | AC15: 130 | AD15: =AB15*AC15 -> 130
C16: Mesas de trabajo | D16: 1 | E16: 4800 | F16: =D16*E16 -> 4800 | G16: 10 | H16: =0.1*E16 -> 480 | I16: =H16*D16 -> 480 | V16: Diseñador gráfico | W16: 12000 | Z16: Cartón para embalaje | AA16: Pieza | AB16: 1 | AC16: 12 | AD16: =AB16*AC16 -> 12
C17: Estantes y racks | D17: 1 | E17: 3800 | F17: =D17*E17 -> 3800 | G17: 10 | H17: =0.1*E17 -> 380 | I17: =H17*D17 -> 380 | V17: Administrador | W17: 16000 | Z17: Soporte para colgar marco | AA17: Paquete (100) | AB17: 1 | AC17: 70 | AD17: =AB17*AC17 -> 70
C18: Sistema de aspiración de polvo | D18: 1 | E18: 29000 | F18: =D18*E18 -> 29000 | G18: 10 | H18: =0.1*E18 -> 2900 | I18: =H18*D18 -> 2900 | V18: Contador | W18: 12000 | Z18: Tornillos para soporte | AA18: Caja (100) | AB18: 1 | AC18: 110 | AD18: =AB18*AC18 -> 110
C19: Computadora con software de diseño | D19: 1 | E19: 35000 | F19: =D19*E19 -> 35000 | G19: 5 | H19: =0.1*E19 -> 3500 | I19: =H19*D19 -> 3500 | Z19: Luz (promedio mensual) | AA19: Recibo | AB19: 1 | AC19: 6400 | AD19: =AB19*AC19 -> 6400
C20: Impresora o plotter de gran formato | D20: 1 | E20: 18000 | F20: =D20*E20 -> 18000 | G20: 5 | H20: =0.1*E20 -> 1800 | I20: =H20*D20 -> 1800 | Z20: Combustible | AA20: Litro | AB20: 1 | AC20: 25 | AD20: =AB20*AC20 -> 25
C21: Escritorio | D21: 1 | E21: 3500 | F21: =D21*E21 -> 3500 | G21: 10 | H21: =0.1*E21 -> 350 | I21: =H21*D21 -> 350 | Z21: Internet/telefonía (cuota mensual) | AA21: Recibo | AB21: 1 | AC21: 600 | AD21: =AB21*AC21 -> 600
C22: Silla de oficina | D22: 1 | E22: 2100 | F22: =D22*E22 -> 2100 | G22: 10 | H22: =0.1*E22 -> 210 | I22: =H22*D22 -> 210 | Z22: Papelería (material predeterminado) | AA22: Paquete | AB22: 1 | AC22: 2500 | AD22: =AB22*AC22 -> 2500
C23: Vehículo compacto | D23: 1 | E23: 360000 | F23: =D23*E23 -> 360000 | G23: 10 | H23: =0.1*E23 -> 36000 | I23: =H23*D23 -> 36000 | Z23: Material de limpieza (material predeterminado) | AA23: Paquete | AB23: 1 | AC23: 1200 | AD23: =AB23*AC23 -> 1200
C24: Vehículo de carga | D24: 2 | E24: 450000 | F24: =D24*E24 -> 900000 | G24: 10 | H24: =0.1*E24 -> 45000 | I24: =H24*D24 -> 90000
C25: Pantalla 55 pulgadas | D25: 1 | E25: 12000 | F25: =D25*E25 -> 12000 | G25: 10 | H25: =0.1*E25 -> 1200 | I25: =H25*D25 -> 1200
C26: Soporte para pantalla | D26: 1 | E26: 600 | F26: =D26*E26 -> 600 | G26: 10 | H26: =0.1*E26 -> 60 | I26: =H26*D26 -> 60
F27: =SUM(F7:F26) -> 1496800 | I27: =SUM(I7:I26) -> 149680
A79: Equipo
A104: Esenciales si se usan adhesivos o solventes.
A109: Para fijar decoraciones o etiquetas mediante calor.
A114: Para herramientas neumáticas o equipos automáticos.
A119: Lámparas LED de alta intensidad para las áreas de costura y corte.
A124: Selladoras de plástico.
A125: Máquinas para empaquetado al vacío si es necesario.
A130: Para mover insumos pesados como rollos grandes de tela.
A134: Si deseas optimizar el uso de estos activos, también puedes considerar sistemas de control digital o software de gestión de manufactura (ERP) para coordinar las operaciones del negocio. ¿Te gustaría desarrollar un flujo de trabajo o esquema de procesos con estos activos?
A136: 4o
A138: Dijiste:
A140: dame el precio estimado de cada uno de esos activos en pesos mexicanos
... A341: .

Sheet CT
A1: Capital de trabajo
A3: Tasa de crecimiento anual de producción | P3: 0.03 | AD3: 0.05 | AR3: 0.05 | BF3: 0.05 | BT3: 0.05 | CH3: 0.05 | CV3: 0.05 | DJ3: 0.05 | DX3: 0.05
A4: Tasa de inflación | P4: 0.07 | AD4: 0.06 | AR4: 0.06 | BF4: 0.06 | BT4: 0.06 | CH4: 0.06 | CV4: 0.06 | DJ4: 0.06 | DX4: 0.06
A5: PROGRAMA DE INGRESOS | B5: AÑO 1 | P5: AÑO 2 | AD5: Año 3 | AR5: AÑO 4 | BF5: AÑO 5 | BT5: AÑO 6 | CH5: AÑO 7 | CV5: AÑO 8 | DJ5: AÑO 9 | DX5: AÑO 10
A6: DESCRIPCIÓN | B6: M1 | C6: M2 | D6: M3 | E6: M4 | F6: M5 | G6: M6 | H6: M7 | I6: M8 | J6: M9 | K6: M10 | L6: M11 | M6: M12 | N6: TOTAL | O6: W | P6: M1 | Q6: M2 | R6: M3 | S6: M4 | T6: M5 | U6: M6 | V6: M7 | W6: M8 | X6: M9 | Y6: M10 | Z6: M11 | AA6: M12 | AB6: TOTAL | AC6: W | AD6: M1 | AE6: M2 | AF6: M3 | AG6: M4 | AH6: M5 | AI6: M6 | AJ6: M7 | AK6: M8 | AL6: M9 | AM6: M10 | AN6: M11 | AO6: M12 | AP6: TOTAL | AQ6: W | AR6: M1 | AS6: M2 | AT6: M3 | AU6: M4 | AV6: M5 | AW6: M6 | AX6: M7 | AY6: M8 | AZ6: M9 | BA6: M10 | BB6: M11 | BC6: M12 | BD6: TOTAL | BE6: W | BF6: M1 | BG6: M2 | BH6: M3 | BI6: M4 | BJ6: M5 | BK6: M6 | BL6: M7 | BM6: M8 | BN6: M9 | BO6: M10 | BP6: M11 | BQ6: M12 | BR6: TOTAL | BS6: W | BT6: M1 | BU6: M2 | BV6: M3 | BW6: M4 | BX6: M5 | BY6: M6 | BZ6: M7 | CA6: M8 | CB6: M9 | CC6: M10 | CD6: M11 | CE6: M12 | CF6: TOTAL | CG6: W | CH6: M1 | CI6: M2 | CJ6: M3 | CK6: M4 | CL6: M5 | CM6: M6 | CN6: M7 | CO6: M8 | CP6: M9 | CQ6: M10 | CR6: M11 | CS6: M12 | CT6: TOTAL | CU6: W | CV6: M1 | CW6: M2 | CX6: M3 | CY6: M4 | CZ6: M5 | DA6: M6 | DB6: M7 | DC6: M8 | DD6: M9 | DE6: M10 | DF6: M11 | DG6: M12 | DH6: TOTAL | DI6: W | DJ6: M1 | DK6: M2 | DL6: M3 | DM6: M4 | DN6: M5 | DO6: M6 | DP6: M7 | DQ6: M8 | DR6: M9 | DS6: M10 | DT6: M11 | DU6: M12 | DV6: TOTAL | DW6: W | DX6: M1 | DY6: M2 | DZ6: M3 | EA6: M4 | EB6: M5 | EC6: M6 | ED6: M7 | EE6: M8 | EF6: M9 | EG6: M10 | EH6: M11 | EI6: M12 | EJ6: TOTAL
A7: Unidades de producción (Q) | B7: 1480 | C7: =B7*(1+C3) -> 1480 | D7: =C7*(1+D3) -> 1480 | E7: =D7*(1+E3) -> 1480 | F7: =E7*(1+F3) -> 1480 | G7: =F7*(1+G3) -> 1480 | H7: =G7*(1+H3) -> 1480 | I7: =H7*(1+I3) -> 1480 | J7: =I7*(1+J3) -> 1480 | ... M7: =L7*(1+M3) -> 1480 | N7: =SUM(B7:M7) -> 17760 | O7: 1 | P7: =$O$7*B7*(1+$P$3) -> 1524.4 | Q7: =$O$7*C7*(1+$P$3) -> 1524.4 | R7: =$O$7*D7*(1+$P$3) -> 1524.4 | S7: =$O$7*E7*(1+$P$3) -> 1524.4 | T7: =$O$7*F7*(1+$P$3) -> 1524.4 | U7: =$O$7*G7*(1+$P$3) -> 1524.4 | V7: =$O$7*H7*(1+$P$3) -> 1524.4 | W7: =$O$7*I7*(1+$P$3) -> 1524.4 | ... AA7: =$O$7*M7*(1+$P$3) -> 1524.4 | AB7: =SUM(P7:AA7) -> 18292.8 | AC7: 1 | AD7: =$AC7*P7*(1+$AD$3) -> 1600.62 | AE7: =$AC7*Q7*(1+$AD$3) -> 1600.62 | AF7: =$AC7*R7*(1+$AD$3) -> 1600.62 | AG7: =$AC7*S7*(1+$AD$3) -> 1600.62 | AH7: =$AC7*T7*(1+$AD$3) -> 1600.62 | AI7: =$AC7*U7*(1+$AD$3) -> 1600.62 | AJ7: =$AC7*V7*(1+$AD$3) -> 1600.62 | AK7: =$AC7*W7*(1+$AD$3) -> 1600.62 | ... AO7: =$AC7*AA7*(1+$AD$3) -> 1600.62 | AP7: =SUM(AD7:AO7) -> 19207.44 | AQ7: 1 | AR7: =$AQ7*AD7*(1+$AR$3) -> 1680.651 | AS7: =$AQ7*AE7*(1+$AR$3) -> 1680.651 | AT7: =$AQ7*AF7*(1+$AR$3) -> 1680.651 | AU7: =$AQ7*AG7*(1+$AR$3) -> 1680.651 | AV7: =$AQ7*AH7*(1+$AR$3) -> 1680.651 | AW7: =$AQ7*AI7*(1+$AR$3) -> 1680.651 | AX7: =$AQ7*AJ7*(1+$AR$3) -> 1680.651 | AY7: =$AQ7*AK7*(1+$AR$3) -> 1680.651 | ... BC7: =$AQ7*AO7*(1+$AR$3) -> 1680.651 | BD7: =SUM(AR7:BC7) -> 20167.812 | BE7: 1 | BF7: =$BE7*AR7*(1+$BF$3) -> 1764.6836 | BG7: =$BE7*AS7*(1+$BF$3) -> 1764.6836 | BH7: =$BE7*AT7*(1+$BF$3) -> 1764.6836 | BI7: =$BE7*AU7*(1+$BF$3) -> 1764.6836 | BJ7: =$BE7*AV7*(1+$BF$3) -> 1764.6836 | BK7: =$BE7*AW7*(1+$BF$3) -> 1764.6836 | BL7: =$BE7*AX7*(1+$BF$3) -> 1764.6836 | BM7: =$BE7*AY7*(1+$BF$3) -> 1764.6836 | ... BQ7: =$BE7*BC7*(1+$BF$3) -> 1764.6836 | BR7: =SUM(BF7:BQ7) -> 21176.203 | BS7: 1 | BT7: =$BS7*BF7*(1+$BT$3) -> 1852.9177 | BU7: =$BS7*BG7*(1+$BT$3) -> 1852.9177 | BV7: =$BS7*BH7*(1+$BT$3) -> 1852.9177 | BW7: =$BS7*BI7*(1+$BT$3) -> 1852.9177 | BX7: =$BS7*BJ7*(1+$BT$3) -> 1852.9177 | BY7: =$BS7*BK7*(1+$BT$3) -> 1852.9177 | BZ7: =$BS7*BL7*(1+$BT$3) -> 1852.9177 | CA7: =$BS7*BM7*(1+$BT$3) -> 1852.9177 | ... CE7: =$BS7*BQ7*(1+$BT$3) -> 1852.9177 | CF7: =SUM(BT7:CE7) -> 22235.013 | CG7: 1 | CH7: =$CG7*BT7*(1+$CH$3) -> 1945.5636 | CI7: =$CG7*BU7*(1+$CH$3) -> 1945.5636 | CJ7: =$CG7*BV7*(1+$CH$3) -> 1945.5636 | CK7: =$CG7*BW7*(1+$CH$3) -> 1945.5636 | CL7: =$CG7*BX7*(1+$CH$3) -> 1945.5636 | CM7: =$CG7*BY7*(1+$CH$3) -> 1945.5636 | CN7: =$CG7*BZ7*(1+$CH$3) -> 1945.5636 | CO7: =$CG7*CA7*(1+$CH$3) -> 1945.5636 | ... CS7: =$CG7*CE7*(1+$CH$3) -> 1945.5636 | CT7: =SUM(CH7:CS7) -> 23346.763 | CU7: 1 | CV7: =$CU7*CH7*(1+$CV$3) -> 2042.8418 | CW7: =$CU7*CI7*(1+$CV$3) -> 2042.8418 | CX7: =$CU7*CJ7*(1+$CV$3) -> 2042.8418 | CY7: =$CU7*CK7*(1+$CV$3) -> 2042.8418 | CZ7: =$CU7*CL7*(1+$CV$3) -> 2042.8418 | DA7: =$CU7*CM7*(1+$CV$3) -> 2042.8418 | DB7: =$CU7*CN7*(1+$CV$3) -> 2042.8418 | DC7: =$CU7*CO7*(1+$CV$3) -> 2042.8418 | ... DG7: =$CU7*CS7*(1+$CV$3) -> 2042.8418 | DH7: =SUM(CV7:DG7) -> 24514.102 | DI7: 1 | DJ7: =$DI7*CV7*(1+$DJ$3) -> 2144.9839 | DK7: =$DI7*CW7*(1+$DJ$3) -> 2144.9839 | DL7: =$DI7*CX7*(1+$DJ$3) -> 2144.9839 | DM7: =$DI7*CY7*(1+$DJ$3) -> 2144.9839 | DN7: =$DI7*CZ7*(1+$DJ$3) -> 2144.9839 | DO7: =$DI7*DA7*(1+$DJ$3) -> 2144.9839 | DP7: =$DI7*DB7*(1+$DJ$3) -> 2144.9839 | DQ7: =$DI7*DC7*(1+$DJ$3) -> 2144.9839 | ... DU7: =$DI7*DG7*(1+$DJ$3) -> 2144.9839 | DV7: =SUM(DJ7:DU7) -> 25739.807 | DW7: 1 | DX7: =$DW7*DJ7*(1+$DX$3) -> 2252.2331 | DY7: =$DW7*DK7*(1+$DX$3) -> 2252.2331 | DZ7: =$DW7*DL7*(1+$DX$3) -> 2252.2331 | EA7: =$DW7*DM7*(1+$DX$3) -> 2252.2331 | EB7: =$DW7*DN7*(1+$DX$3) -> 2252.2331 | EC7: =$DW7*DO7*(1+$DX$3) -> 2252.2331 | ED7: =$DW7*DP7*(1+$DX$3) -> 2252.2331 | EE7: =$DW7*DQ7*(1+$DX$3) -> 2252.2331 | ... EI7: =$DW7*DU7*(1+$DX$3) -> 2252.2331 | EJ7: =SUM(DX7:EI7) -> 27026.797
A8: Precio de venta (P) | B8: =400 -> 400 | C8: =B8 -> 400 | D8: =C8 -> 400 | E8: =D8 -> 400 | F8: =E8 -> 400 | G8: =F8 -> 400 | H8: =G8 -> 400 | I8: =H8 -> 400 | J8: =I8 -> 400 | ... M8: =L8 -> 400 | N8: =IF(N7>0,(SUMPRODUCT(B7:M7,B8:M8)/N7),0) -> 400 | O8: 1 | P8: =$O$8*B8*(1+$P$4) -> 428 | Q8: =$O$8*C8*(1+$P$4) -> 428 | R8: =$O$8*D8*(1+$P$4) -> 428 | S8: =$O$8*E8*(1+$P$4) -> 428 | T8: =$O$8*F8*(1+$P$4) -> 428 | U8: =$O$8*G8*(1+$P$4) -> 428 | V8: =$O$8*H8*(1+$P$4) -> 428 | W8: =$O$8*I8*(1+$P$4) -> 428 | ... AA8: =$O$8*M8*(1+$P$4) -> 428 | AB8: =IF(AB7>0,(SUMPRODUCT(P7:AA7,P8:AA8)/AB7),0) -> 428 | AC8: 1 | AD8: =$AC8*P8*(1+$AD$4) -> 453.68 | AE8: =$AC8*Q8*(1+$AD$4) -> 453.68 | AF8: =$AC8*R8*(1+$AD$4) -> 453.68 | AG8: =$AC8*S8*(1+$AD$4) -> 453.68 | AH8: =$AC8*T8*(1+$AD$4) -> 453.68 | AI8: =$AC8*U8*(1+$AD$4) -> 453.68 | AJ8: =$AC8*V8*(1+$AD$4) -> 453.68 | AK8: =$AC8*W8*(1+$AD$4) -> 453.68 | ... AO8: =$AC8*AA8*(1+$AD$4) -> 453.68 | AP8: =IF(AP7>0,(SUMPRODUCT(AD7:AO7,AD8:AO8)/AP7),0) -> 453.68 | AQ8: 1 | AR8: =$AQ8*AD8*(1+$AR$4) -> 480.9008 | AS8: =$AQ8*AE8*(1+$AR$4) -> 480.9008 | AT8: =$AQ8*AF8*(1+$AR$4) -> 480.9008 | AU8: =$AQ8*AG8*(1+$AR$4) -> 480.9008 | AV8: =$AQ8*AH8*(1+$AR$4) -> 480.9008 | AW8: =$AQ8*AI8*(1+$AR$4) -> 480.9008 | AX8: =$AQ8*AJ8*(1+$AR$4) -> 480.9008 | AY8: =$AQ8*AK8*(1+$AR$4) -> 480.9008 | ... BC8: =$AQ8*AO8*(1+$AR$4) -> 480.9008 | BD8: =IF(BD7>0,(SUMPRODUCT(AR7:BC7,AR8:BC8)/BD7),0) -> 480.9008 | BE8: 1 | BF8: =$BE8*AR8*(1+$BF$4) -> 509.75485 | BG8: =$BE8*AS8*(1+$BF$4) -> 509.75485 | BH8: =$BE8*AT8*(1+$BF$4) -> 509.75485 | BI8: =$BE8*AU8*(1+$BF$4) -> 509.75485 | BJ8: =$BE8*AV8*(1+$BF$4) -> 509.75485 | BK8: =$BE8*AW8*(1+$BF$4) -> 509.75485 | BL8: =$BE8*AX8*(1+$BF$4) -> 509.75485 | BM8: =$BE8*AY8*(1+$BF$4) -> 509.75485 | ... BQ8: =$BE8*BC8*(1+$BF$4) -> 509.75485 | BR8: =IF(BR7>0,(SUMPRODUCT(BF7:BQ7,BF8:BQ8)/BR7),0) -> 509.75485 | BS8: 1 | BT8: =$BS8*BF8*(1+$BT$4) -> 540.34014 | BU8: =$BS8*BG8*(1+$BT$4) -> 540.34014 | BV8: =$BS8*BH8*(1+$BT$4) -> 540.34014 | BW8: =$BS8*BI8*(1+$BT$4) -> 540.34014 | BX8: =$BS8*BJ8*(1+$BT$4) -> 540.34014 | BY8: =$BS8*BK8*(1+$BT$4) -> 540.34014 | BZ8: =$BS8*BL8*(1+$BT$4) -> 540.34014 | CA8: =$BS8*BM8*(1+$BT$4) -> 540.34014 | ... CE8: =$BS8*BQ8*(1+$BT$4) -> 540.34014 | CF8: =IF(CF7>0,(SUMPRODUCT(BT7:CE7,BT8:CE8)/CF7),0) -> 540.34014 | CG8: 1 | CH8: =$CG8*BT8*(1+$CH$4) -> 572.76055 | CI8: =$CG8*BU8*(1+$CH$4) -> 572.76055 | CJ8: =$CG8*BV8*(1+$CH$4) -> 572.76055 | CK8: =$CG8*BW8*(1+$CH$4) -> 572.76055 | CL8: =$CG8*BX8*(1+$CH$4) -> 572.76055 | CM8: =$CG8*BY8*(1+$CH$4) -> 572.76055 | CN8: =$CG8*BZ8*(1+$CH$4) -> 572.76055 | CO8: =$CG8*CA8*(1+$CH$4) -> 572.76055 | ... CS8: =$CG8*CE8*(1+$CH$4) -> 572.76055 | CT8: =IF(CT7>0,(SUMPRODUCT(CH7:CS7,CH8:CS8)/CT7),0) -> 572.76055 | CU8: 1 | CV8: =$CU8*CH8*(1+$CV$4) -> 607.12618 | CW8: =$CU8*CI8*(1+$CV$4) -> 607.12618 | CX8: =$CU8*CJ8*(1+$CV$4) -> 607.12618 | CY8: =$CU8*CK8*(1+$CV$4) -> 607.12618 | CZ8: =$CU8*CL8*(1+$CV$4) -> 607.12618 | DA8: =$CU8*CM8*(1+$CV$4) -> 607.12618 | DB8: =$CU8*CN8*(1+$CV$4) -> 607.12618 | DC8: =$CU8*CO8*(1+$CV$4) -> 607.12618 | ... DG8: =$CU8*CS8*(1+$CV$4) -> 607.12618 | DH8: =IF(DH7>0,(SUMPRODUCT(CV7:DG7,CV8:DG8)/DH7),0) -> 607.12618 | DI8: 1 | DJ8: =$DI8*CV8*(1+$DJ$4) -> 643.55375 | DK8: =$DI8*CW8*(1+$DJ$4) -> 643.55375 | DL8: =$DI8*CX8*(1+$DJ$4) -> 643.55375 | DM8: =$DI8*CY8*(1+$DJ$4) -> 643.55375 | DN8: =$DI8*CZ8*(1+$DJ$4) -> 643.55375 | DO8: =$DI8*DA8*(1+$DJ$4) -> 643.55375 | DP8: =$DI8*DB8*(1+$DJ$4) -> 643.55375 | DQ8: =$DI8*DC8*(1+$DJ$4) -> 643.55375 | ... DU8: =$DI8*DG8*(1+$DJ$4) -> 643.55375 | DV8: =IF(DV7>0,(SUMPRODUCT(DJ7:DU7,DJ8:DU8)/DV7),0) -> 643.55375 | DW8: 1 | DX8: =$DW8*DJ8*(1+$DX$4) -> 682.16698 | DY8: =$DW8*DK8*(1+$DX$4) -> 682.16698 | DZ8: =$DW8*DL8*(1+$DX$4) -> 682.16698 | EA8: =$DW8*DM8*(1+$DX$4) -> 682.16698 | EB8: =$DW8*DN8*(1+$DX$4) -> 682.16698 | EC8: =$DW8*DO8*(1+$DX$4) -> 682.16698 | ED8: =$DW8*DP8*(1+$DX$4) -> 682.16698 | EE8: =$DW8*DQ8*(1+$DX$4) -> 682.16698 | ... EI8: =$DW8*DU8*(1+$DX$4) -> 682.16698 | EJ8: =IF(EJ7>0,(SUMPRODUCT(DX7:EI7,DX8:EI8)/EJ7),0) -> 682.16698
A9: Ventas totales (VT) | B9: =B7*B8 -> 592000 | C9: =C7*C8 -> 592000 | D9: =D7*D8 -> 592000 | E9: =E7*E8 -> 592000 | F9: =F7*F8 -> 592000 | G9: =G7*G8 -> 592000 | H9: =H7*H8 -> 592000 | I9: =I7*I8 -> 592000 | ... N9: =N7*N8 -> 7104000 | P9: =P7*P8 -> 652443.2 | Q9: =Q7*Q8 -> 652443.2 | R9: =R7*R8 -> 652443.2 | S9: =S7*S8 -> 652443.2 | T9: =T7*T8 -> 652443.2 | U9: =U7*U8 -> 652443.2 | V9: =V7*V8 -> 652443.2 | W9: =W7*W8 -> 652443.2 | ... AB9: =AB7*AB8 -> 7829318.4 | AD9: =AD7*AD8 -> 726169.28 | AE9: =AE7*AE8 -> 726169.28 | AF9: =AF7*AF8 -> 726169.28 | AG9: =AG7*AG8 -> 726169.28 | AH9: =AH7*AH8 -> 726169.28 | AI9: =AI7*AI8 -> 726169.28 | AJ9: =AJ7*AJ8 -> 726169.28 | AK9: =AK7*AK8 -> 726169.28 | ... AP9: =AP7*AP8 -> 8714031.4 | AR9: =AR7*AR8 -> 808226.41 | AS9: =AS7*AS8 -> 808226.41 | AT9: =AT7*AT8 -> 808226.41 | AU9: =AU7*AU8 -> 808226.41 | AV9: =AV7*AV8 -> 808226.41 | AW9: =AW7*AW8 -> 808226.41 | AX9: =AX7*AX8 -> 808226.41 | AY9: =AY7*AY8 -> 808226.41 | ... BD9: =BD7*BD8 -> 9698716.9 | BF9: =BF7*BF8 -> 899555.99 | BG9: =BG7*BG8 -> 899555.99 | BH9: =BH7*BH8 -> 899555.99 | BI9: =BI7*BI8 -> 899555.99 | BJ9: =BJ7*BJ8 -> 899555.99 | BK9: =BK7*BK8 -> 899555.99 | BL9: =BL7*BL8 -> 899555.99 | BM9: =BM7*BM8 -> 899555.99 | ... BR9: =BR7*BR8 -> 10794672 | BT9: =BT7*BT8 -> 1001205.8 | BU9: =BU7*BU8 -> 1001205.8 | BV9: =BV7*BV8 -> 1001205.8 | BW9: =BW7*BW8 -> 1001205.8 | BX9: =BX7*BX8 -> 1001205.8 | BY9: =BY7*BY8 -> 1001205.8 | BZ9: =BZ7*BZ8 -> 1001205.8 | CA9: =CA7*CA8 -> 1001205.8 | ... CF9: =CF7*CF8 -> 12014470 | CH9: =CH7*CH8 -> 1114342.1 | CI9: =CI7*CI8 -> 1114342.1 | CJ9: =CJ7*CJ8 -> 1114342.1 | CK9: =CK7*CK8 -> 1114342.1 | CL9: =CL7*CL8 -> 1114342.1 | CM9: =CM7*CM8 -> 1114342.1 | CN9: =CN7*CN8 -> 1114342.1 | CO9: =CO7*CO8 -> 1114342.1 | ... CT9: =CT7*CT8 -> 13372105 | CV9: =CV7*CV8 -> 1240262.7 | CW9: =CW7*CW8 -> 1240262.7 | CX9: =CX7*CX8 -> 1240262.7 | CY9: =CY7*CY8 -> 1240262.7 | CZ9: =CZ7*CZ8 -> 1240262.7 | DA9: =DA7*DA8 -> 1240262.7 | DB9: =DB7*DB8 -> 1240262.7 | DC9: =DC7*DC8 -> 1240262.7 | ... DH9: =DH7*DH8 -> 14883153 | DJ9: =DJ7*DJ8 -> 1380412.4 | DK9: =DK7*DK8 -> 1380412.4 | DL9: =DL7*DL8 -> 1380412.4 | DM9: =DM7*DM8 -> 1380412.4 | DN9: =DN7*DN8 -> 1380412.4 | DO9: =DO7*DO8 -> 1380412.4 | DP9: =DP7*DP8 -> 1380412.4 | DQ9: =DQ7*DQ8 -> 1380412.4 | ... DV9: =DV7*DV8 -> 16564949 | DX9: =DX7*DX8 -> 1536399 | DY9: =DY7*DY8 -> 1536399 | DZ9: =DZ7*DZ8 -> 1536399 | EA9: =EA7*EA8 -> 1536399 | EB9: =EB7*EB8 -> 1536399 | EC9: =EC7*EC8 -> 1536399 | ED9: =ED7*ED8 -> 1536399 | EE9: =EE7*EE8 -> 1536399 | ... EJ9: =EJ7*EJ8 -> 18436788
A10: Otros ingresos (OI) | N10: =SUM(B10:M10) -> 0 | AB10: =SUM(P10:AA10) -> 0 | AP10: =SUM(AD10:AO10) -> 0 | BD10: =SUM(AR10:BC10) -> 0 | BR10: =SUM(BF10:BQ10) -> 0 | CF10: =SUM(BT10:CE10) -> 0 | CT10: =SUM(CH10:CS10) -> 0 | DH10: =SUM(CV10:DG10) -> 0 | DV10: =SUM(DJ10:DU10) -> 0 | EJ10: =SUM(DX10:EI10) -> 0
A11: Ingresos totales (IT) | B11: =B9+B10 -> 592000 | C11: =C9+C10 -> 592000 | D11: =D9+D10 -> 592000 | E11: =E9+E10 -> 592000 | F11: =F9+F10 -> 592000 | G11: =G9+G10 -> 592000 | H11: =H9+H10 -> 592000 | I11: =I9+I10 -> 592000 | ... N11: =N9+N10 -> 7104000 | P11: =P9+P10 -> 652443.2 | Q11: =Q9+Q10 -> 652443.2 | R11: =R9+R10 -> 652443.2 | S11: =S9+S10 -> 652443.2 | T11: =T9+T10 -> 652443.2 | U11: =U9+U10 -> 652443.2 | V11: =V9+V10 -> 652443.2 | W11: =W9+W10 -> 652443.2 | ... AB11: =AB9+AB10 -> 7829318.4 | AD11: =AD9+AD10 -> 726169.28 | AE11: =AE9+AE10 -> 726169.28 | AF11: =AF9+AF10 -> 726169.28 | AG11: =AG9+AG10 -> 726169.28 | AH11: =AH9+AH10 -> 726169.28 | AI11: =AI9+AI10 -> 726169.28 | AJ11: =AJ9+AJ10 -> 726169.28 | AK11: =AK9+AK10 -> 726169.28 | ... AP11: =AP9+AP10 -> 8714031.4 | AR11: =AR9+AR10 -> 808226.41 | AS11: =AS9+AS10 -> 808226.41 | AT11: =AT9+AT10 -> 808226.41 | AU11: =AU9+AU10 -> 808226.41 | AV11: =AV9+AV10 -> 808226.41 | AW11: =AW9+AW10 -> 808226.41 | AX11: =AX9+AX10 -> 808226.41 | AY11: =AY9+AY10 -> 808226.41 | ... BD11: =BD9+BD10 -> 9698716.9 | BF11: =BF9+BF10 -> 899555.99 | BG11: =BG9+BG10 -> 899555.99 | BH11: =BH9+BH10 -> 899555.99 | BI11: =BI9+BI10 -> 899555.99 | BJ11: =BJ9+BJ10 -> 899555.99 | BK11: =BK9+BK10 -> 899555.99 | BL11: =BL9+BL10 -> 899555.99 | BM11: =BM9+BM10 -> 899555.99 | ... BR11: =BR9+BR10 -> 10794672 | BT11: =BT9+BT10 -> 1001205.8 | BU11: =BU9+BU10 -> 1001205.8 | BV11: =BV9+BV10 -> 1001205.8 | BW11: =BW9+BW10 -> 1001205.8 | BX11: =BX9+BX10 -> 1001205.8 | BY11: =BY9+BY10 -> 1001205.8 | BZ11: =BZ9+BZ10 -> 1001205.8 | CA11: =CA9+CA10 -> 1001205.8 | ... CF11: =CF9+CF10 -> 12014470 | CH11: =CH9+CH10 -> 1114342.1 | CI11: =CI9+CI10 -> 1114342.1 | CJ11: =CJ9+CJ10 -> 1114342.1 | CK11: =CK9+CK10 -> 1114342.1 | CL11: =CL9+CL10 -> 1114342.1 | CM11: =CM9+CM10 -> 1114342.1 | CN11: =CN9+CN10 -> 1114342.1 | CO11: =CO9+CO10 -> 1114342.1 | ... CT11: =CT9+CT10 -> 13372105 | CV11: =CV9+CV10 -> 1240262.7 | CW11: =CW9+CW10 -> 1240262.7 | CX11: =CX9+CX10 -> 1240262.7 | CY11: =CY9+CY10 -> 1240262.7 | CZ11: =CZ9+CZ10 -> 1240262.7 | DA11: =DA9+DA10 -> 1240262.7 | DB11: =DB9+DB10 -> 1240262.7 | DC11: =DC9+DC10 -> 1240262.7 | ... DH11: =DH9+DH10 -> 14883153 | DJ11: =DJ9+DJ10 -> 1380412.4 | DK11: =DK9+DK10 -> 1380412.4 | DL11: =DL9+DL10 -> 1380412.4 | DM11: =DM9+DM10 -> 1380412.4 | DN11: =DN9+DN10 -> 1380412.4 | DO11: =DO9+DO10 -> 1380412.4 | DP11: =DP9+DP10 -> 1380412.4 | DQ11: =DQ9+DQ10 -> 1380412.4 | ... DV11: =DV9+DV10 -> 16564949 | DX11: =DX9+DX10 -> 1536399 | DY11: =DY9+DY10 -> 1536399 | DZ11: =DZ9+DZ10 -> 1536399 | EA11: =EA9+EA10 -> 1536399 | EB11: =EB9+EB10 -> 1536399 | EC11: =EC9+EC10 -> 1536399 | ED11: =ED9+ED10 -> 1536399 | EE11: =EE9+EE10 -> 1536399 | ... EJ11: =EJ9+EJ10 -> 18436788
A12: PROGRAMA DE EGRESOS | B12: AÑO 1 | P12: AÑO 2 | AD12: Año 3 | AR12: AÑO 4 | BF12: AÑO 5 | BT12: AÑO 6 | CH12: AÑO 7 | CV12: AÑO 8 | DJ12: AÑO 9 | DX12: AÑO 10
A13: DESCRIPCIÓN | B13: M1 | C13: M2 | D13: M3 | E13: M4 | F13: M5 | G13: M6 | H13: M7 | I13: M8 | J13: M9 | K13: M10 | L13: M11 | M13: M12 | N13: TOTAL | P13: M1 | Q13: M2 | R13: M3 | S13: M4 | T13: M5 | U13: M6 | V13: M7 | W13: M8 | X13: M9 | Y13: M10 | Z13: M11 | AA13: M12 | AB13: TOTAL | AD13: M1 | AE13: M2 | AF13: M3 | AG13: M4 | AH13: M5 | AI13: M6 | AJ13: M7 | AK13: M8 | AL13: M9 | AM13: M10 | AN13: M11 | AO13: M12 | AP13: TOTAL | AR13: M1 | AS13: M2 | AT13: M3 | AU13: M4 | AV13: M5 | AW13: M6 | AX13: M7 | AY13: M8 | AZ13: M9 | BA13: M10 | BB13: M11 | BC13: M12 | BD13: TOTAL | BF13: M1 | BG13: M2 | BH13: M3 | BI13: M4 | BJ13: M5 | BK13: M6 | BL13: M7 | BM13: M8 | BN13: M9 | BO13: M10 | BP13: M11 | BQ13: M12 | BR13: TOTAL | BT13: M1 | BU13: M2 | BV13: M3 | BW13: M4 | BX13: M5 | BY13: M6 | BZ13: M7 | CA13: M8 | CB13: M9 | CC13: M10 | CD13: M11 | CE13: M12 | CF13: TOTAL | CH13: M1 | CI13: M2 | CJ13: M3 | CK13: M4 | CL13: M5 | CM13: M6 | CN13: M7 | CO13: M8 | CP13: M9 | CQ13: M10 | CR13: M11 | CS13: M12 | CT13: TOTAL | CV13: M1 | CW13: M2 | CX13: M3 | CY13: M4 | CZ13: M5 | DA13: M6 | DB13: M7 | DC13: M8 | DD13: M9 | DE13: M10 | DF13: M11 | DG13: M12 | DH13: TOTAL | DJ13: M1 | DK13: M2 | DL13: M3 | DM13: M4 | DN13: M5 | DO13: M6 | DP13: M7 | DQ13: M8 | DR13: M9 | DS13: M10 | DT13: M11 | DU13: M12 | DV13: TOTAL | DX13: M1 | DY13: M2 | DZ13: M3 | EA13: M4 | EB13: M5 | EC13: M6 | ED13: M7 | EE13: M8 | EF13: M9 | EG13: M10 | EH13: M11 | EI13: M12 | EJ13: TOTAL
A14: 1. Costo de ventas | B14: =B15+B26+B30+B35 -> 362590 | C14: =C15+C26+C30+C35 -> 362590 | D14: =D15+D26+D30+D35 -> 362590 | E14: =E15+E26+E30+E35 -> 362590 | F14: =F15+F26+F30+F35 -> 362590 | G14: =G15+G26+G30+G35 -> 362590 | H14: =H15+H26+H30+H35 -> 362590 | I14: =I15+I26+I30+I35 -> 362590 | ... M14: =M15+M26+M30+M35 -> 362590 | N14: =SUM(B14:M14) -> 4351080 | P14: =P15+P26+P30+P35 -> 397029.6 | Q14: =Q15+Q26+Q30+Q35 -> 397029.6 | R14: =R15+R26+R30+R35 -> 397029.6 | S14: =S15+S26+S30+S35 -> 397029.6 | T14: =T15+T26+T30+T35 -> 397029.6 | U14: =U15+U26+U30+U35 -> 397029.6 | V14: =V15+V26+V30+V35 -> 397029.6 | W14: =W15+W26+W30+W35 -> 397029.6 | ... AA14: =AA15+AA26+AA30+AA35 -> 397029.6 | AB14: =SUM(P14:AA14) -> 4764355.2 | AD14: =AD15+AD26+AD30+AD35 -> 437334.46 | AE14: =AE15+AE26+AE30+AE35 -> 437334.46 | AF14: =AF15+AF26+AF30+AF35 -> 437334.46 | AG14: =AG15+AG26+AG30+AG35 -> 437334.46 | AH14: =AH15+AH26+AH30+AH35 -> 437334.46 | AI14: =AI15+AI26+AI30+AI35 -> 437334.46 | AJ14: =AJ15+AJ26+AJ30+AJ35 -> 437334.46 | AK14: =AK15+AK26+AK30+AK35 -> 437334.46 | ... AO14: =AO15+AO26+AO30+AO35 -> 437334.46 | AP14: =SUM(AD14:AO14) -> 5248013.5 | AR14: =AR15+AR26+AR30+AR35 -> 481920.2 | AS14: =AS15+AS26+AS30+AS35 -> 481920.2 | AT14: =AT15+AT26+AT30+AT35 -> 481920.2 | AU14: =AU15+AU26+AU30+AU35 -> 481920.2 | AV14: =AV15+AV26+AV30+AV35 -> 481920.2 | AW14: =AW15+AW26+AW30+AW35 -> 481920.2 | AX14: =AX15+AX26+AX30+AX35 -> 481920.2 | AY14: =AY15+AY26+AY30+AY35 -> 481920.2 | ... BC14: =BC15+BC26+BC30+BC35 -> 481920.2 | BD14: =SUM(AR14:BC14) -> 5783042.4 | BF14: =BF15+BF26+BF30+BF35 -> 531254.15 | BG14: =BG15+BG26+BG30+BG35 -> 531254.15 | BH14: =BH15+BH26+BH30+BH35 -> 531254.15 | BI14: =BI15+BI26+BI30+BI35 -> 531254.15 | BJ14: =BJ15+BJ26+BJ30+BJ35 -> 531254.15 | BK14: =BK15+BK26+BK30+BK35 -> 531254.15 | BL14: =BL15+BL26+BL30+BL35 -> 531254.15 | BM14: =BM15+BM26+BM30+BM35 -> 531254.15 | ... BQ14: =BQ15+BQ26+BQ30+BQ35 -> 531254.15 | BR14: =SUM(BF14:BQ14) -> 6375049.8 | BT14: =BT15+BT26+BT30+BT35 -> 585855.45 | BU14: =BU15+BU26+BU30+BU35 -> 585855.45 | BV14: =BV15+BV26+BV30+BV35 -> 585855.45 | BW14: =BW15+BW26+BW30+BW35 -> 585855.45 | BX14: =BX15+BX26+BX30+BX35 -> 585855.45 | BY14: =BY15+BY26+BY30+BY35 -> 585855.45 | BZ14: =BZ15+BZ26+BZ30+BZ35 -> 585855.45 | CA14: =CA15+CA26+CA30+CA35 -> 585855.45 | ... CE14: =CE15+CE26+CE30+CE35 -> 585855.45 | CF14: =SUM(BT14:CE14) -> 7030265.4 | CH14: =CH15+CH26+CH30+CH35 -> 646300.87 | CI14: =CI15+CI26+CI30+CI35 -> 646300.87 | CJ14: =CJ15+CJ26+CJ30+CJ35 -> 646300.87 | CK14: =CK15+CK26+CK30+CK35 -> 646300.87 | CL14: =CL15+CL26+CL30+CL35 -> 646300.87 | CM14: =CM15+CM26+CM30+CM35 -> 646300.87 | CN14: =CN15+CN26+CN30+CN35 -> 646300.87 | CO14: =CO15+CO26+CO30+CO35 -> 646300.87 | ... CS14: =CS15+CS26+CS30+CS35 -> 646300.87 | CT14: =SUM(CH14:CS14) -> 7755610.4 | CV14: =CV15+CV26+CV30+CV35 -> 713231.25 | CW14: =CW15+CW26+CW30+CW35 -> 713231.25 | CX14: =CX15+CX26+CX30+CX35 -> 713231.25 | CY14: =CY15+CY26+CY30+CY35 -> 713231.25 | CZ14: =CZ15+CZ26+CZ30+CZ35 -> 713231.25 | DA14: =DA15+DA26+DA30+DA35 -> 713231.25 | DB14: =DB15+DB26+DB30+DB35 -> 713231.25 | DC14: =DC15+DC26+DC30+DC35 -> 713231.25 | ... DG14: =DG15+DG26+DG30+DG35 -> 713231.25 | DH14: =SUM(CV14:DG14) -> 8558775 | DJ14: =DJ15+DJ26+DJ30+DJ35 -> 787358.67 | DK14: =DK15+DK26+DK30+DK35 -> 787358.67 | DL14: =DL15+DL26+DL30+DL35 -> 787358.67 | DM14: =DM15+DM26+DM30+DM35 -> 787358.67 | DN14: =DN15+DN26+DN30+DN35 -> 787358.67 | DO14: =DO15+DO26+DO30+DO35 -> 787358.67 | DP14: =DP15+DP26+DP30+DP35 -> 787358.67 | DQ14: =DQ15+DQ26+DQ30+DQ35 -> 787358.67 | ... DU14: =DU15+DU26+DU30+DU35 -> 787358.67 | DV14: =SUM(DJ14:DU14) -> 9448304 | DX14: =DX15+DX26+DX30+DX35 -> 869474.42 | DY14: =DY15+DY26+DY30+DY35 -> 869474.42 | DZ14: =DZ15+DZ26+DZ30+DZ35 -> 869474.42 | EA14: =EA15+EA26+EA30+EA35 -> 869474.42 | EB14: =EB15+EB26+EB30+EB35 -> 869474.42 | EC14: =EC15+EC26+EC30+EC35 -> 869474.42 | ED14: =ED15+ED26+ED30+ED35 -> 869474.42 | EE14: =EE15+EE26+EE30+EE35 -> 869474.42 | ... EI14: =EI15+EI26+EI30+EI35 -> 869474.42 | EJ14: =SUM(DX14:EI14) -> 10433693
A15: 1.1. Material directo | B15: =SUM(B16:B25) -> 256030 | C15: =SUM(C16:C25) -> 256030 | D15: =SUM(D16:D25) -> 256030 | E15: =SUM(E16:E25) -> 256030 | F15: =SUM(F16:F25) -> 256030 | G15: =SUM(G16:G25) -> 256030 | H15: =SUM(H16:H25) -> 256030 | I15: =SUM(I16:I25) -> 256030 | ... M15: =SUM(M16:M25) -> 256030 | N15: =SUM(B15:M15) -> 3072360 | P15: =SUM(P16:P25) -> 282170.66 | Q15: =SUM(Q16:Q25) -> 282170.66 | R15: =SUM(R16:R25) -> 282170.66 | S15: =SUM(S16:S25) -> 282170.66 | T15: =SUM(T16:T25) -> 282170.66 | U15: =SUM(U16:U25) -> 282170.66 | V15: =SUM(V16:V25) -> 282170.66 | W15: =SUM(W16:W25) -> 282170.66 | ... AA15: =SUM(AA16:AA25) -> 282170.66 | AB15: =SUM(P15:AA15) -> 3386048 | AD15: =SUM(AD16:AD25) -> 314055.95 | AE15: =SUM(AE16:AE25) -> 314055.95 | AF15: =SUM(AF16:AF25) -> 314055.95 | AG15: =SUM(AG16:AG25) -> 314055.95 | AH15: =SUM(AH16:AH25) -> 314055.95 | AI15: =SUM(AI16:AI25) -> 314055.95 | AJ15: =SUM(AJ16:AJ25) -> 314055.95 | AK15: =SUM(AK16:AK25) -> 314055.95 | ... AO15: =SUM(AO16:AO25) -> 314055.95 | AP15: =SUM(AD15:AO15) -> 3768671.4 | AR15: =SUM(AR16:AR25) -> 349544.27 | AS15: =SUM(AS16:AS25) -> 349544.27 | AT15: =SUM(AT16:AT25) -> 349544.27 | AU15: =SUM(AU16:AU25) -> 349544.27 | AV15: =SUM(AV16:AV25) -> 349544.27 | AW15: =SUM(AW16:AW25) -> 349544.27 | AX15: =SUM(AX16:AX25) -> 349544.27 | AY15: =SUM(AY16:AY25) -> 349544.27 | ... BC15: =SUM(BC16:BC25) -> 349544.27 | BD15: =SUM(AR15:BC15) -> 4194531.2 | BF15: =SUM(BF16:BF25) -> 389042.77 | BG15: =SUM(BG16:BG25) -> 389042.77 | BH15: =SUM(BH16:BH25) -> 389042.77 | BI15: =SUM(BI16:BI25) -> 389042.77 | BJ15: =SUM(BJ16:BJ25) -> 389042.77 | BK15: =SUM(BK16:BK25) -> 389042.77 | BL15: =SUM(BL16:BL25) -> 389042.77 | BM15: =SUM(BM16:BM25) -> 389042.77 | ... BQ15: =SUM(BQ16:BQ25) -> 389042.77 | BR15: =SUM(BF15:BQ15) -> 4668513.3 | BT15: =SUM(BT16:BT25) -> 433004.61 | BU15: =SUM(BU16:BU25) -> 433004.61 | BV15: =SUM(BV16:BV25) -> 433004.61 | BW15: =SUM(BW16:BW25) -> 433004.61 | BX15: =SUM(BX16:BX25) -> 433004.61 | BY15: =SUM(BY16:BY25) -> 433004.61 | BZ15: =SUM(BZ16:BZ25) -> 433004.61 | CA15: =SUM(CA16:CA25) -> 433004.61 | ... CE15: =SUM(CE16:CE25) -> 433004.61 | CF15: =SUM(BT15:CE15) -> 5196055.3 | CH15: =SUM(CH16:CH25) -> 481934.13 | CI15: =SUM(CI16:CI25) -> 481934.13 | CJ15: =SUM(CJ16:CJ25) -> 481934.13 | CK15: =SUM(CK16:CK25) -> 481934.13 | CL15: =SUM(CL16:CL25) -> 481934.13 | CM15: =SUM(CM16:CM25) -> 481934.13 | CN15: =SUM(CN16:CN25) -> 481934.13 | CO15: =SUM(CO16:CO25) -> 481934.13 | ... CS15: =SUM(CS16:CS25) -> 481934.13 | CT15: =SUM(CH15:CS15) -> 5783209.5 | CV15: =SUM(CV16:CV25) -> 536392.68 | CW15: =SUM(CW16:CW25) -> 536392.68 | CX15: =SUM(CX16:CX25) -> 536392.68 | CY15: =SUM(CY16:CY25) -> 536392.68 | CZ15: =SUM(CZ16:CZ25) -> 536392.68 | DA15: =SUM(DA16:DA25) -> 536392.68 | DB15: =SUM(DB16:DB25) -> 536392.68 | DC15: =SUM(DC16:DC25) -> 536392.68 | ... DG15: =SUM(DG16:DG25) -> 536392.68 | DH15: =SUM(CV15:DG15) -> 6436712.2 | DJ15: =SUM(DJ16:DJ25) -> 597005.06 | DK15: =SUM(DK16:DK25) -> 597005.06 | DL15: =SUM(DL16:DL25) -> 597005.06 | DM15: =SUM(DM16:DM25) -> 597005.06 | DN15: =SUM(DN16:DN25) -> 597005.06 | DO15: =SUM(DO16:DO25) -> 597005.06 | DP15: =SUM(DP16:DP25) -> 597005.06 | DQ15: =SUM(DQ16:DQ25) -> 597005.06 | ... DU15: =SUM(DU16:DU25) -> 597005.06 | DV15: =SUM(DJ15:DU15) -> 7164060.7 | DX15: =SUM(DX16:DX25) -> 664466.63 | DY15: =SUM(DY16:DY25) -> 664466.63 | DZ15: =SUM(DZ16:DZ25) -> 664466.63 | EA15: =SUM(EA16:EA25) -> 664466.63 | EB15: =SUM(EB16:EB25) -> 664466.63 | EC15: =SUM(EC16:EC25) -> 664466.63 | ED15: =SUM(ED16:ED25) -> 664466.63 | EE15: =SUM(EE16:EE25) -> 664466.63 | ... EI15: =SUM(EI16:EI25) -> 664466.63 | EJ15: =SUM(DX15:EI15) -> 7973599.5
A16: Madera | B16: =(1.08*B7*75) -> 119880 | C16: =B16*(1+C$3) -> 119880 | D16: =C16*(1+D$3) -> 119880 | E16: =D16*(1+E$3) -> 119880 | F16: =E16*(1+F$3) -> 119880 | G16: =F16*(1+G$3) -> 119880 | H16: =G16*(1+H$3) -> 119880 | I16: =H16*(1+I$3) -> 119880 | J16: =I16*(1+J$3) -> 119880 | ... M16: =L16*(1+M$3) -> 119880 | N16: =SUM(B16:M16) -> 1438560 | O16: 1 | P16: =$O16*B16*(1+$P$3)*(1+$P$4) -> 132119.75 | Q16: =$O16*C16*(1+$P$3)*(1+$P$4) -> 132119.75 | R16: =$O16*D16*(1+$P$3)*(1+$P$4) -> 132119.75 | S16: =$O16*E16*(1+$P$3)*(1+$P$4) -> 132119.75 | T16: =$O16*F16*(1+$P$3)*(1+$P$4) -> 132119.75 | U16: =$O16*G16*(1+$P$3)*(1+$P$4) -> 132119.75 | V16: =$O16*H16*(1+$P$3)*(1+$P$4) -> 132119.75 | W16: =$O16*I16*(1+$P$3)*(1+$P$4) -> 132119.75 | ... AA16: =$O16*M16*(1+$P$3)*(1+$P$4) -> 132119.75 | AB16: =SUM(P16:AA16) -> 1585437 | AC16: 1 | AD16: =$AC16*P16*(1+$AD$3)*(1+$AD$4) -> 147049.28 | AE16: =$AC16*Q16*(1+$AD$3)*(1+$AD$4) -> 147049.28 | AF16: =$AC16*R16*(1+$AD$3)*(1+$AD$4) -> 147049.28 | AG16: =$AC16*S16*(1+$AD$3)*(1+$AD$4) -> 147049.28 | AH16: =$AC16*T16*(1+$AD$3)*(1+$AD$4) -> 147049.28 | AI16: =$AC16*U16*(1+$AD$3)*(1+$AD$4) -> 147049.28 | AJ16: =$AC16*V16*(1+$AD$3)*(1+$AD$4) -> 147049.28 | AK16: =$AC16*W16*(1+$AD$3)*(1+$AD$4) -> 147049.28 | ... AO16: =$AC16*AA16*(1+$AD$3)*(1+$AD$4) -> 147049.28 | AP16: =SUM(AD16:AO16) -> 1764591.4 | AQ16: 1 | AR16: =$AQ16*AD16*(1+$AR$3)*(1+$AR$4) -> 163665.85 | AS16: =$AQ16*AE16*(1+$AR$3)*(1+$AR$4) -> 163665.85 | AT16: =$AQ16*AF16*(1+$AR$3)*(1+$AR$4) -> 163665.85 | AU16: =$AQ16*AG16*(1+$AR$3)*(1+$AR$4) -> 163665.85 | AV16: =$AQ16*AH16*(1+$AR$3)*(1+$AR$4) -> 163665.85 | AW16: =$AQ16*AI16*(1+$AR$3)*(1+$AR$4) -> 163665.85 | AX16: =$AQ16*AJ16*(1+$AR$3)*(1+$AR$4) -> 163665.85 | AY16: =$AQ16*AK16*(1+$AR$3)*(1+$AR$4) -> 163665.85 | ... BC16: =$AQ16*AO16*(1+$AR$3)*(1+$AR$4) -> 163665.85 | BD16: =SUM(AR16:BC16) -> 1963990.2 | BE16: 1 | BF16: =$BE16*AR16*(1+$BF$3)*(1+$BF$4) -> 182160.09 | BG16: =$BE16*AS16*(1+$BF$3)*(1+$BF$4) -> 182160.09 | BH16: =$BE16*AT16*(1+$BF$3)*(1+$BF$4) -> 182160.09 | BI16: =$BE16*AU16*(1+$BF$3)*(1+$BF$4) -> 182160.09 | BJ16: =$BE16*AV16*(1+$BF$3)*(1+$BF$4) -> 182160.09 | BK16: =$BE16*AW16*(1+$BF$3)*(1+$BF$4) -> 182160.09 | BL16: =$BE16*AX16*(1+$BF$3)*(1+$BF$4) -> 182160.09 | BM16: =$BE16*AY16*(1+$BF$3)*(1+$BF$4) -> 182160.09 | ... BQ16: =$BE16*BC16*(1+$BF$3)*(1+$BF$4) -> 182160.09 | BR16: =SUM(BF16:BQ16) -> 2185921.1 | BS16: 1 | BT16: =$BS16*BF16*(1+$BT$3)*(1+$BT$4) -> 202744.18 | BU16: =$BS16*BG16*(1+$BT$3)*(1+$BT$4) -> 202744.18 | BV16: =$BS16*BH16*(1+$BT$3)*(1+$BT$4) -> 202744.18 | BW16: =$BS16*BI16*(1+$BT$3)*(1+$BT$4) -> 202744.18 | BX16: =$BS16*BJ16*(1+$BT$3)*(1+$BT$4) -> 202744.18 | BY16: =$BS16*BK16*(1+$BT$3)*(1+$BT$4) -> 202744.18 | BZ16: =$BS16*BL16*(1+$BT$3)*(1+$BT$4) -> 202744.18 | CA16: =$BS16*BM16*(1+$BT$3)*(1+$BT$4) -> 202744.18 | ... CE16: =$BS16*BQ16*(1+$BT$3)*(1+$BT$4) -> 202744.18 | CF16: =SUM(BT16:CE16) -> 2432930.1 | CG16: 1 | CH16: =$CG16*BT16*(1+$CH$3)*(1+$CH$4) -> 225654.27 | CI16: =$CG16*BU16*(1+$CH$3)*(1+$CH$4) -> 225654.27 | CJ16: =$CG16*BV16*(1+$CH$3)*(1+$CH$4) -> 225654.27 | CK16: =$CG16*BW16*(1+$CH$3)*(1+$CH$4) -> 225654.27 | CL16: =$CG16*BX16*(1+$CH$3)*(1+$CH$4) -> 225654.27 | CM16: =$CG16*BY16*(1+$CH$3)*(1+$CH$4) -> 225654.27 | CN16: =$CG16*BZ16*(1+$CH$3)*(1+$CH$4) -> 225654.27 | CO16: =$CG16*CA16*(1+$CH$3)*(1+$CH$4) -> 225654.27 | ... CS16: =$CG16*CE16*(1+$CH$3)*(1+$CH$4) -> 225654.27 | CT16: =SUM(CH16:CS16) -> 2707851.3 | CU16: 1 | CV16: =$CU16*CH16*(1+$CV$3)*(1+$CV$4) -> 251153.2 | CW16: =$CU16*CI16*(1+$CV$3)*(1+$CV$4) -> 251153.2 | CX16: =$CU16*CJ16*(1+$CV$3)*(1+$CV$4) -> 251153.2 | CY16: =$CU16*CK16*(1+$CV$3)*(1+$CV$4) -> 251153.2 | CZ16: =$CU16*CL16*(1+$CV$3)*(1+$CV$4) -> 251153.2 | DA16: =$CU16*CM16*(1+$CV$3)*(1+$CV$4) -> 251153.2 | DB16: =$CU16*CN16*(1+$CV$3)*(1+$CV$4) -> 251153.2 | DC16: =$CU16*CO16*(1+$CV$3)*(1+$CV$4) -> 251153.2 | ... DG16: =$CU16*CS16*(1+$CV$3)*(1+$CV$4) -> 251153.2 | DH16: =SUM(CV16:DG16) -> 3013838.4 | DI16: 1 | DJ16: =$DI16*CV16*(1+$DJ$3)*(1+$DJ$4) -> 279533.52 | DK16: =$DI16*CW16*(1+$DJ$3)*(1+$DJ$4) -> 279533.52 | DL16: =$DI16*CX16*(1+$DJ$3)*(1+$DJ$4) -> 279533.52 | DM16: =$DI16*CY16*(1+$DJ$3)*(1+$DJ$4) -> 279533.52 | DN16: =$DI16*CZ16*(1+$DJ$3)*(1+$DJ$4) -> 279533.52 | DO16: =$DI16*DA16*(1+$DJ$3)*(1+$DJ$4) -> 279533.52 | DP16: =$DI16*DB16*(1+$DJ$3)*(1+$DJ$4) -> 279533.52 | DQ16: =$DI16*DC16*(1+$DJ$3)*(1+$DJ$4) -> 279533.52 | ... DU16: =$DI16*DG16*(1+$DJ$3)*(1+$DJ$4) -> 279533.52 | DV16: =SUM(DJ16:DU16) -> 3354402.2 | DW16: 1 | DX16: =$DW16*DJ16*(1+$DX$3)*(1+$DX$4) -> 311120.8 | DY16: =$DW16*DK16*(1+$DX$3)*(1+$DX$4) -> 311120.8 | DZ16: =$DW16*DL16*(1+$DX$3)*(1+$DX$4) -> 311120.8 | EA16: =$DW16*DM16*(1+$DX$3)*(1+$DX$4) -> 311120.8 | EB16: =$DW16*DN16*(1+$DX$3)*(1+$DX$4) -> 311120.8 | EC16: =$DW16*DO16*(1+$DX$3)*(1+$DX$4) -> 311120.8 | ED16: =$DW16*DP16*(1+$DX$3)*(1+$DX$4) -> 311120.8 | EE16: =$DW16*DQ16*(1+$DX$3)*(1+$DX$4) -> 311120.8 | ... EI16: =$DW16*DU16*(1+$DX$3)*(1+$DX$4) -> 311120.8 | EJ16: =SUM(DX16:EI16) -> 3733449.6
A17: MDF | B17: =B7*100*0.9 -> 133200 | C17: =B17*(1+C$3) -> 133200 | D17: =C17*(1+D$3) -> 133200 | E17: =D17*(1+E$3) -> 133200 | F17: =E17*(1+F$3) -> 133200 | G17: =F17*(1+G$3) -> 133200 | H17: =G17*(1+H$3) -> 133200 | I17: =H17*(1+I$3) -> 133200 | J17: =I17*(1+J$3) -> 133200 | ... M17: =L17*(1+M$3) -> 133200 | N17: =SUM(B17:M17) -> 1598400 | O17: 1 | P17: =$O17*B17*(1+$P$3)*(1+$P$4) -> 146799.72 | Q17: =$O17*C17*(1+$P$3)*(1+$P$4) -> 146799.72 | R17: =$O17*D17*(1+$P$3)*(1+$P$4) -> 146799.72 | S17: =$O17*E17*(1+$P$3)*(1+$P$4) -> 146799.72 | T17: =$O17*F17*(1+$P$3)*(1+$P$4) -> 146799.72 | U17: =$O17*G17*(1+$P$3)*(1+$P$4) -> 146799.72 | V17: =$O17*H17*(1+$P$3)*(1+$P$4) -> 146799.72 | W17: =$O17*I17*(1+$P$3)*(1+$P$4) -> 146799.72 | ... AA17: =$O17*M17*(1+$P$3)*(1+$P$4) -> 146799.72 | AB17: =SUM(P17:AA17) -> 1761596.6 | AC17: 1 | AD17: =$AC17*P17*(1+$AD$3)*(1+$AD$4) -> 163388.09 | AE17: =$AC17*Q17*(1+$AD$3)*(1+$AD$4) -> 163388.09 | AF17: =$AC17*R17*(1+$AD$3)*(1+$AD$4) -> 163388.09 | AG17: =$AC17*S17*(1+$AD$3)*(1+$AD$4) -> 163388.09 | AH17: =$AC17*T17*(1+$AD$3)*(1+$AD$4) -> 163388.09 | AI17: =$AC17*U17*(1+$AD$3)*(1+$AD$4) -> 163388.09 | AJ17: =$AC17*V17*(1+$AD$3)*(1+$AD$4) -> 163388.09 | AK17: =$AC17*W17*(1+$AD$3)*(1+$AD$4) -> 163388.09 | ... AO17: =$AC17*AA17*(1+$AD$3)*(1+$AD$4) -> 163388.09 | AP17: =SUM(AD17:AO17) -> 1960657.1 | AQ17: 1 | AR17: =$AQ17*AD17*(1+$AR$3)*(1+$AR$4) -> 181850.94 | AS17: =$AQ17*AE17*(1+$AR$3)*(1+$AR$4) -> 181850.94 | AT17: =$AQ17*AF17*(1+$AR$3)*(1+$AR$4) -> 181850.94 | AU17: =$AQ17*AG17*(1+$AR$3)*(1+$AR$4) -> 181850.94 | AV17: =$AQ17*AH17*(1+$AR$3)*(1+$AR$4) -> 181850.94 | AW17: =$AQ17*AI17*(1+$AR$3)*(1+$AR$4) -> 181850.94 | AX17: =$AQ17*AJ17*(1+$AR$3)*(1+$AR$4) -> 181850.94 | AY17: =$AQ17*AK17*(1+$AR$3)*(1+$AR$4) -> 181850.94 | ... BC17: =$AQ17*AO17*(1+$AR$3)*(1+$AR$4) -> 181850.94 | BD17: =SUM(AR17:BC17) -> 2182211.3 | BE17: 1 | BF17: =$BE17*AR17*(1+$BF$3)*(1+$BF$4) -> 202400.1 | BG17: =$BE17*AS17*(1+$BF$3)*(1+$BF$4) -> 202400.1 | BH17: =$BE17*AT17*(1+$BF$3)*(1+$BF$4) -> 202400.1 | BI17: =$BE17*AU17*(1+$BF$3)*(1+$BF$4) -> 202400.1 | BJ17: =$BE17*AV17*(1+$BF$3)*(1+$BF$4) -> 202400.1 | BK17: =$BE17*AW17*(1+$BF$3)*(1+$BF$4) -> 202400.1 | BL17: =$BE17*AX17*(1+$BF$3)*(1+$BF$4) -> 202400.1 | BM17: =$BE17*AY17*(1+$BF$3)*(1+$BF$4) -> 202400.1 | ... BQ17: =$BE17*BC17*(1+$BF$3)*(1+$BF$4) -> 202400.1 | BR17: =SUM(BF17:BQ17) -> 2428801.2 | BS17: 1 | BT17: =$BS17*BF17*(1+$BT$3)*(1+$BT$4) -> 225271.31 | BU17: =$BS17*BG17*(1+$BT$3)*(1+$BT$4) -> 225271.31 | BV17: =$BS17*BH17*(1+$BT$3)*(1+$BT$4) -> 225271.31 | BW17: =$BS17*BI17*(1+$BT$3)*(1+$BT$4) -> 225271.31 | BX17: =$BS17*BJ17*(1+$BT$3)*(1+$BT$4) -> 225271.31 | BY17: =$BS17*BK17*(1+$BT$3)*(1+$BT$4) -> 225271.31 | BZ17: =$BS17*BL17*(1+$BT$3)*(1+$BT$4) -> 225271.31 | CA17: =$BS17*BM17*(1+$BT$3)*(1+$BT$4) -> 225271.31 | ... CE17: =$BS17*BQ17*(1+$BT$3)*(1+$BT$4) -> 225271.31 | CF17: =SUM(BT17:CE17) -> 2703255.7 | CG17: 1 | CH17: =$CG17*BT17*(1+$CH$3)*(1+$CH$4) -> 250726.97 | CI17: =$CG17*BU17*(1+$CH$3)*(1+$CH$4) -> 250726.97 | CJ17: =$CG17*BV17*(1+$CH$3)*(1+$CH$4) -> 250726.97 | CK17: =$CG17*BW17*(1+$CH$3)*(1+$CH$4) -> 250726.97 | CL17: =$CG17*BX17*(1+$CH$3)*(1+$CH$4) -> 250726.97 | CM17: =$CG17*BY17*(1+$CH$3)*(1+$CH$4) -> 250726.97 | CN17: =$CG17*BZ17*(1+$CH$3)*(1+$CH$4) -> 250726.97 | CO17: =$CG17*CA17*(1+$CH$3)*(1+$CH$4) -> 250726.97 | ... CS17: =$CG17*CE17*(1+$CH$3)*(1+$CH$4) -> 250726.97 | CT17: =SUM(CH17:CS17) -> 3008723.6 | CU17: 1 | CV17: =$CU17*CH17*(1+$CV$3)*(1+$CV$4) -> 279059.12 | CW17: =$CU17*CI17*(1+$CV$3)*(1+$CV$4) -> 279059.12 | CX17: =$CU17*CJ17*(1+$CV$3)*(1+$CV$4) -> 279059.12 | CY17: =$CU17*CK17*(1+$CV$3)*(1+$CV$4) -> 279059.12 | CZ17: =$CU17*CL17*(1+$CV$3)*(1+$CV$4) -> 279059.12 | DA17: =$CU17*CM17*(1+$CV$3)*(1+$CV$4) -> 279059.12 | DB17: =$CU17*CN17*(1+$CV$3)*(1+$CV$4) -> 279059.12 | DC17: =$CU17*CO17*(1+$CV$3)*(1+$CV$4) -> 279059.12 | ... DG17: =$CU17*CS17*(1+$CV$3)*(1+$CV$4) -> 279059.12 | DH17: =SUM(CV17:DG17) -> 3348709.4 | DI17: 1 | DJ17: =$DI17*CV17*(1+$DJ$3)*(1+$DJ$4) -> 310592.8 | DK17: =$DI17*CW17*(1+$DJ$3)*(1+$DJ$4) -> 310592.8 | DL17: =$DI17*CX17*(1+$DJ$3)*(1+$DJ$4) -> 310592.8 | DM17: =$DI17*CY17*(1+$DJ$3)*(1+$DJ$4) -> 310592.8 | DN17: =$DI17*CZ17*(1+$DJ$3)*(1+$DJ$4) -> 310592.8 | DO17: =$DI17*DA17*(1+$DJ$3)*(1+$DJ$4) -> 310592.8 | DP17: =$DI17*DB17*(1+$DJ$3)*(1+$DJ$4) -> 310592.8 | DQ17: =$DI17*DC17*(1+$DJ$3)*(1+$DJ$4) -> 310592.8 | ... DU17: =$DI17*DG17*(1+$DJ$3)*(1+$DJ$4) -> 310592.8 | DV17: =SUM(DJ17:DU17) -> 3727113.5 | DW17: 1 | DX17: =$DW17*DJ17*(1+$DX$3)*(1+$DX$4) -> 345689.78 | DY17: =$DW17*DK17*(1+$DX$3)*(1+$DX$4) -> 345689.78 | DZ17: =$DW17*DL17*(1+$DX$3)*(1+$DX$4) -> 345689.78 | EA17: =$DW17*DM17*(1+$DX$3)*(1+$DX$4) -> 345689.78 | EB17: =$DW17*DN17*(1+$DX$3)*(1+$DX$4) -> 345689.78 | EC17: =$DW17*DO17*(1+$DX$3)*(1+$DX$4) -> 345689.78 | ED17: =$DW17*DP17*(1+$DX$3)*(1+$DX$4) -> 345689.78 | EE17: =$DW17*DQ17*(1+$DX$3)*(1+$DX$4) -> 345689.78 | ... EI17: =$DW17*DU17*(1+$DX$3)*(1+$DX$4) -> 345689.78 | EJ17: =SUM(DX17:EI17) -> 4148277.4
A18: Pegamento para madera | B18: 800 | C18: =B18*(1+C$3) -> 800 | D18: =C18*(1+D$3) -> 800 | E18: =D18*(1+E$3) -> 800 | F18: =E18*(1+F$3) -> 800 | G18: =F18*(1+G$3) -> 800 | H18: =G18*(1+H$3) -> 800 | I18: =H18*(1+I$3) -> 800 | J18: =I18*(1+J$3) -> 800 | ... M18: =L18*(1+M$3) -> 800 | N18: =SUM(B18:M18) -> 9600 | O18: 1 | P18: =$O18*B18*(1+$P$3)*(1+$P$4) -> 881.68 | Q18: =$O18*C18*(1+$P$3)*(1+$P$4) -> 881.68 | R18: =$O18*D18*(1+$P$3)*(1+$P$4) -> 881.68 | S18: =$O18*E18*(1+$P$3)*(1+$P$4) -> 881.68 | T18: =$O18*F18*(1+$P$3)*(1+$P$4) -> 881.68 | U18: =$O18*G18*(1+$P$3)*(1+$P$4) -> 881.68 | V18: =$O18*H18*(1+$P$3)*(1+$P$4) -> 881.68 | W18: =$O18*I18*(1+$P$3)*(1+$P$4) -> 881.68 | ... AA18: =$O18*M18*(1+$P$3)*(1+$P$4) -> 881.68 | AB18: =SUM(P18:AA18) -> 10580.16 | AC18: 1 | AD18: =$AC18*P18*(1+$AD$3)*(1+$AD$4) -> 981.30984 | AE18: =$AC18*Q18*(1+$AD$3)*(1+$AD$4) -> 981.30984 | AF18: =$AC18*R18*(1+$AD$3)*(1+$AD$4) -> 981.30984 | AG18: =$AC18*S18*(1+$AD$3)*(1+$AD$4) -> 981.30984 | AH18: =$AC18*T18*(1+$AD$3)*(1+$AD$4) -> 981.30984 | AI18: =$AC18*U18*(1+$AD$3)*(1+$AD$4) -> 981.30984 | AJ18: =$AC18*V18*(1+$AD$3)*(1+$AD$4) -> 981.30984 | AK18: =$AC18*W18*(1+$AD$3)*(1+$AD$4) -> 981.30984 | ... AO18: =$AC18*AA18*(1+$AD$3)*(1+$AD$4) -> 981.30984 | AP18: =SUM(AD18:AO18) -> 11775.718 | AQ18: 1 | AR18: =$AQ18*AD18*(1+$AR$3)*(1+$AR$4) -> 1092.1979 | AS18: =$AQ18*AE18*(1+$AR$3)*(1+$AR$4) -> 1092.1979 | AT18: =$AQ18*AF18*(1+$AR$3)*(1+$AR$4) -> 1092.1979 | AU18: =$AQ18*AG18*(1+$AR$3)*(1+$AR$4) -> 1092.1979 | AV18: =$AQ18*AH18*(1+$AR$3)*(1+$AR$4) -> 1092.1979 | AW18: =$AQ18*AI18*(1+$AR$3)*(1+$AR$4) -> 1092.1979 | AX18: =$AQ18*AJ18*(1+$AR$3)*(1+$AR$4) -> 1092.1979 | AY18: =$AQ18*AK18*(1+$AR$3)*(1+$AR$4) -> 1092.1979 | ... BC18: =$AQ18*AO18*(1+$AR$3)*(1+$AR$4) -> 1092.1979 | BD18: =SUM(AR18:BC18) -> 13106.374 | BE18: 1 | BF18: =$BE18*AR18*(1+$BF$3)*(1+$BF$4) -> 1215.6162 | BG18: =$BE18*AS18*(1+$BF$3)*(1+$BF$4) -> 1215.6162 | BH18: =$BE18*AT18*(1+$BF$3)*(1+$BF$4) -> 1215.6162 | BI18: =$BE18*AU18*(1+$BF$3)*(1+$BF$4) -> 1215.6162 | BJ18: =$BE18*AV18*(1+$BF$3)*(1+$BF$4) -> 1215.6162 | BK18: =$BE18*AW18*(1+$BF$3)*(1+$BF$4) -> 1215.6162 | BL18: =$BE18*AX18*(1+$BF$3)*(1+$BF$4) -> 1215.6162 | BM18: =$BE18*AY18*(1+$BF$3)*(1+$BF$4) -> 1215.6162 | ... BQ18: =$BE18*BC18*(1+$BF$3)*(1+$BF$4) -> 1215.6162 | BR18: =SUM(BF18:BQ18) -> 14587.395 | BS18: 1 | BT18: =$BS18*BF18*(1+$BT$3)*(1+$BT$4) -> 1352.9808 | BU18: =$BS18*BG18*(1+$BT$3)*(1+$BT$4) -> 1352.9808 | BV18: =$BS18*BH18*(1+$BT$3)*(1+$BT$4) -> 1352.9808 | BW18: =$BS18*BI18*(1+$BT$3)*(1+$BT$4) -> 1352.9808 | BX18: =$BS18*BJ18*(1+$BT$3)*(1+$BT$4) -> 1352.9808 | BY18: =$BS18*BK18*(1+$BT$3)*(1+$BT$4) -> 1352.9808 | BZ18: =$BS18*BL18*(1+$BT$3)*(1+$BT$4) -> 1352.9808 | CA18: =$BS18*BM18*(1+$BT$3)*(1+$BT$4) -> 1352.9808 | ... CE18: =$BS18*BQ18*(1+$BT$3)*(1+$BT$4) -> 1352.9808 | CF18: =SUM(BT18:CE18) -> 16235.77 | CG18: 1 | CH18: =$CG18*BT18*(1+$CH$3)*(1+$CH$4) -> 1505.8677 | CI18: =$CG18*BU18*(1+$CH$3)*(1+$CH$4) -> 1505.8677 | CJ18: =$CG18*BV18*(1+$CH$3)*(1+$CH$4) -> 1505.8677 | CK18: =$CG18*BW18*(1+$CH$3)*(1+$CH$4) -> 1505.8677 | CL18: =$CG18*BX18*(1+$CH$3)*(1+$CH$4) -> 1505.8677 | CM18: =$CG18*BY18*(1+$CH$3)*(1+$CH$4) -> 1505.8677 | CN18: =$CG18*BZ18*(1+$CH$3)*(1+$CH$4) -> 1505.8677 | CO18: =$CG18*CA18*(1+$CH$3)*(1+$CH$4) -> 1505.8677 | ... CS18: =$CG18*CE18*(1+$CH$3)*(1+$CH$4) -> 1505.8677 | CT18: =SUM(CH18:CS18) -> 18070.412 | CU18: 1 | CV18: =$CU18*CH18*(1+$CV$3)*(1+$CV$4) -> 1676.0307 | CW18: =$CU18*CI18*(1+$CV$3)*(1+$CV$4) -> 1676.0307 | CX18: =$CU18*CJ18*(1+$CV$3)*(1+$CV$4) -> 1676.0307 | CY18: =$CU18*CK18*(1+$CV$3)*(1+$CV$4) -> 1676.0307 | CZ18: =$CU18*CL18*(1+$CV$3)*(1+$CV$4) -> 1676.0307 | DA18: =$CU18*CM18*(1+$CV$3)*(1+$CV$4) -> 1676.0307 | DB18: =$CU18*CN18*(1+$CV$3)*(1+$CV$4) -> 1676.0307 | DC18: =$CU18*CO18*(1+$CV$3)*(1+$CV$4) -> 1676.0307 | ... DG18: =$CU18*CS18*(1+$CV$3)*(1+$CV$4) -> 1676.0307 | DH18: =SUM(CV18:DG18) -> 20112.369 | DI18: 1 | DJ18: =$DI18*CV18*(1+$DJ$3)*(1+$DJ$4) -> 1865.4222 | DK18: =$DI18*CW18*(1+$DJ$3)*(1+$DJ$4) -> 1865.4222 | DL18: =$DI18*CX18*(1+$DJ$3)*(1+$DJ$4) -> 1865.4222 | DM18: =$DI18*CY18*(1+$DJ$3)*(1+$DJ$4) -> 1865.4222 | DN18: =$DI18*CZ18*(1+$DJ$3)*(1+$DJ$4) -> 1865.4222 | DO18: =$DI18*DA18*(1+$DJ$3)*(1+$DJ$4) -> 1865.4222 | DP18: =$DI18*DB18*(1+$DJ$3)*(1+$DJ$4) -> 1865.4222 | DQ18: =$DI18*DC18*(1+$DJ$3)*(1+$DJ$4) -> 1865.4222 | ... DU18: =$DI18*DG18*(1+$DJ$3)*(1+$DJ$4) -> 1865.4222 | DV18: =SUM(DJ18:DU18) -> 22385.066 | DW18: 1 | DX18: =$DW18*DJ18*(1+$DX$3)*(1+$DX$4) -> 2076.2149 | DY18: =$DW18*DK18*(1+$DX$3)*(1+$DX$4) -> 2076.2149 | DZ18: =$DW18*DL18*(1+$DX$3)*(1+$DX$4) -> 2076.2149 | EA18: =$DW18*DM18*(1+$DX$3)*(1+$DX$4) -> 2076.2149 | EB18: =$DW18*DN18*(1+$DX$3)*(1+$DX$4) -> 2076.2149 | EC18: =$DW18*DO18*(1+$DX$3)*(1+$DX$4) -> 2076.2149 | ED18: =$DW18*DP18*(1+$DX$3)*(1+$DX$4) -> 2076.2149 | EE18: =$DW18*DQ18*(1+$DX$3)*(1+$DX$4) -> 2076.2149 | ... EI18: =$DW18*DU18*(1+$DX$3)*(1+$DX$4) -> 2076.2149 | EJ18: =SUM(DX18:EI18) -> 24914.579
A19: Clavos | B19: 150 | C19: =B19*(1+C$3) -> 150 | D19: =C19*(1+D$3) -> 150 | E19: =D19*(1+E$3) -> 150 | F19: =E19*(1+F$3) -> 150 | G19: =F19*(1+G$3) -> 150 | H19: =G19*(1+H$3) -> 150 | I19: =H19*(1+I$3) -> 150 | J19: =I19*(1+J$3) -> 150 | ... M19: =L19*(1+M$3) -> 150 | N19: =SUM(B19:M19) -> 1800 | O19: 1 | P19: =$O19*B19*(1+$P$3)*(1+$P$4) -> 165.315 | Q19: =$O19*C19*(1+$P$3)*(1+$P$4) -> 165.315 | R19: =$O19*D19*(1+$P$3)*(1+$P$4) -> 165.315 | S19: =$O19*E19*(1+$P$3)*(1+$P$4) -> 165.315 | T19: =$O19*F19*(1+$P$3)*(1+$P$4) -> 165.315 | U19: =$O19*G19*(1+$P$3)*(1+$P$4) -> 165.315 | V19: =$O19*H19*(1+$P$3)*(1+$P$4) -> 165.315 | W19: =$O19*I19*(1+$P$3)*(1+$P$4) -> 165.315 | ... AA19: =$O19*M19*(1+$P$3)*(1+$P$4) -> 165.315 | AB19: =SUM(P19:AA19) -> 1983.78 | AC19: 1 | AD19: =$AC19*P19*(1+$AD$3)*(1+$AD$4) -> 183.9956 | AE19: =$AC19*Q19*(1+$AD$3)*(1+$AD$4) -> 183.9956 | AF19: =$AC19*R19*(1+$AD$3)*(1+$AD$4) -> 183.9956 | AG19: =$AC19*S19*(1+$AD$3)*(1+$AD$4) -> 183.9956 | AH19: =$AC19*T19*(1+$AD$3)*(1+$AD$4) -> 183.9956 | AI19: =$AC19*U19*(1+$AD$3)*(1+$AD$4) -> 183.9956 | AJ19: =$AC19*V19*(1+$AD$3)*(1+$AD$4) -> 183.9956 | AK19: =$AC19*W19*(1+$AD$3)*(1+$AD$4) -> 183.9956 | ... AO19: =$AC19*AA19*(1+$AD$3)*(1+$AD$4) -> 183.9956 | AP19: =SUM(AD19:AO19) -> 2207.9471 | AQ19: 1 | AR19: =$AQ19*AD19*(1+$AR$3)*(1+$AR$4) -> 204.7871 | AS19: =$AQ19*AE19*(1+$AR$3)*(1+$AR$4) -> 204.7871 | AT19: =$AQ19*AF19*(1+$AR$3)*(1+$AR$4) -> 204.7871 | AU19: =$AQ19*AG19*(1+$AR$3)*(1+$AR$4) -> 204.7871 | AV19: =$AQ19*AH19*(1+$AR$3)*(1+$AR$4) -> 204.7871 | AW19: =$AQ19*AI19*(1+$AR$3)*(1+$AR$4) -> 204.7871 | AX19: =$AQ19*AJ19*(1+$AR$3)*(1+$AR$4) -> 204.7871 | AY19: =$AQ19*AK19*(1+$AR$3)*(1+$AR$4) -> 204.7871 | ... BC19: =$AQ19*AO19*(1+$AR$3)*(1+$AR$4) -> 204.7871 | BD19: =SUM(AR19:BC19) -> 2457.4452 | BE19: 1 | BF19: =$BE19*AR19*(1+$BF$3)*(1+$BF$4) -> 227.92804 | BG19: =$BE19*AS19*(1+$BF$3)*(1+$BF$4) -> 227.92804 | BH19: =$BE19*AT19*(1+$BF$3)*(1+$BF$4) -> 227.92804 | BI19: =$BE19*AU19*(1+$BF$3)*(1+$BF$4) -> 227.92804 | BJ19: =$BE19*AV19*(1+$BF$3)*(1+$BF$4) -> 227.92804 | BK19: =$BE19*AW19*(1+$BF$3)*(1+$BF$4) -> 227.92804 | BL19: =$BE19*AX19*(1+$BF$3)*(1+$BF$4) -> 227.92804 | BM19: =$BE19*AY19*(1+$BF$3)*(1+$BF$4) -> 227.92804 | ... BQ19: =$BE19*BC19*(1+$BF$3)*(1+$BF$4) -> 227.92804 | BR19: =SUM(BF19:BQ19) -> 2735.1365 | BS19: 1 | BT19: =$BS19*BF19*(1+$BT$3)*(1+$BT$4) -> 253.68391 | BU19: =$BS19*BG19*(1+$BT$3)*(1+$BT$4) -> 253.68391 | BV19: =$BS19*BH19*(1+$BT$3)*(1+$BT$4) -> 253.68391 | BW19: =$BS19*BI19*(1+$BT$3)*(1+$BT$4) -> 253.68391 | BX19: =$BS19*BJ19*(1+$BT$3)*(1+$BT$4) -> 253.68391 | BY19: =$BS19*BK19*(1+$BT$3)*(1+$BT$4) -> 253.68391 | BZ19: =$BS19*BL19*(1+$BT$3)*(1+$BT$4) -> 253.68391 | CA19: =$BS19*BM19*(1+$BT$3)*(1+$BT$4) -> 253.68391 | ... CE19: =$BS19*BQ19*(1+$BT$3)*(1+$BT$4) -> 253.68391 | CF19: =SUM(BT19:CE19) -> 3044.2069 | CG19: 1 | CH19: =$CG19*BT19*(1+$CH$3)*(1+$CH$4) -> 282.35019 | CI19: =$CG19*BU19*(1+$CH$3)*(1+$CH$4) -> 282.35019 | CJ19: =$CG19*BV19*(1+$CH$3)*(1+$CH$4) -> 282.35019 | CK19: =$CG19*BW19*(1+$CH$3)*(1+$CH$4) -> 282.35019 | CL19: =$CG19*BX19*(1+$CH$3)*(1+$CH$4) -> 282.35019 | CM19: =$CG19*BY19*(1+$CH$3)*(1+$CH$4) -> 282.35019 | CN19: =$CG19*BZ19*(1+$CH$3)*(1+$CH$4) -> 282.35019 | CO19: =$CG19*CA19*(1+$CH$3)*(1+$CH$4) -> 282.35019 | ... CS19: =$CG19*CE19*(1+$CH$3)*(1+$CH$4) -> 282.35019 | CT19: =SUM(CH19:CS19) -> 3388.2023 | CU19: 1 | CV19: =$CU19*CH19*(1+$CV$3)*(1+$CV$4) -> 314.25576 | CW19: =$CU19*CI19*(1+$CV$3)*(1+$CV$4) -> 314.25576 | CX19: =$CU19*CJ19*(1+$CV$3)*(1+$CV$4) -> 314.25576 | CY19: =$CU19*CK19*(1+$CV$3)*(1+$CV$4) -> 314.25576 | CZ19: =$CU19*CL19*(1+$CV$3)*(1+$CV$4) -> 314.25576 | DA19: =$CU19*CM19*(1+$CV$3)*(1+$CV$4) -> 314.25576 | DB19: =$CU19*CN19*(1+$CV$3)*(1+$CV$4) -> 314.25576 | DC19: =$CU19*CO19*(1+$CV$3)*(1+$CV$4) -> 314.25576 | ... DG19: =$CU19*CS19*(1+$CV$3)*(1+$CV$4) -> 314.25576 | DH19: =SUM(CV19:DG19) -> 3771.0691 | DI19: 1 | DJ19: =$DI19*CV19*(1+$DJ$3)*(1+$DJ$4) -> 349.76666 | DK19: =$DI19*CW19*(1+$DJ$3)*(1+$DJ$4) -> 349.76666 | DL19: =$DI19*CX19*(1+$DJ$3)*(1+$DJ$4) -> 349.76666 | DM19: =$DI19*CY19*(1+$DJ$3)*(1+$DJ$4) -> 349.76666 | DN19: =$DI19*CZ19*(1+$DJ$3)*(1+$DJ$4) -> 349.76666 | DO19: =$DI19*DA19*(1+$DJ$3)*(1+$DJ$4) -> 349.76666 | DP19: =$DI19*DB19*(1+$DJ$3)*(1+$DJ$4) -> 349.76666 | DQ19: =$DI19*DC19*(1+$DJ$3)*(1+$DJ$4) -> 349.76666 | ... DU19: =$DI19*DG19*(1+$DJ$3)*(1+$DJ$4) -> 349.76666 | DV19: =SUM(DJ19:DU19) -> 4197.1999 | DW19: 1 | DX19: =$DW19*DJ19*(1+$DX$3)*(1+$DX$4) -> 389.29029 | DY19: =$DW19*DK19*(1+$DX$3)*(1+$DX$4) -> 389.29029 | DZ19: =$DW19*DL19*(1+$DX$3)*(1+$DX$4) -> 389.29029 | EA19: =$DW19*DM19*(1+$DX$3)*(1+$DX$4) -> 389.29029 | EB19: =$DW19*DN19*(1+$DX$3)*(1+$DX$4) -> 389.29029 | EC19: =$DW19*DO19*(1+$DX$3)*(1+$DX$4) -> 389.29029 | ED19: =$DW19*DP19*(1+$DX$3)*(1+$DX$4) -> 389.29029 | EE19: =$DW19*DQ19*(1+$DX$3)*(1+$DX$4) -> 389.29029 | ... EI19: =$DW19*DU19*(1+$DX$3)*(1+$DX$4) -> 389.29029 | EJ19: =SUM(DX19:EI19) -> 4671.4835
A20: Grapas | B20: 120 | C20: =B20*(1+C$3) -> 120 | D20: =C20*(1+D$3) -> 120 | E20: =D20*(1+E$3) -> 120 | F20: =E20*(1+F$3) -> 120 | G20: =F20*(1+G$3) -> 120 | H20: =G20*(1+H$3) -> 120 | I20: =H20*(1+I$3) -> 120 | J20: =I20*(1+J$3) -> 120 | ... M20: =L20*(1+M$3) -> 120 | N20: =SUM(B20:M20) -> 1440 | O20: 1 | P20: =$O20*B20*(1+$P$3)*(1+$P$4) -> 132.252 | Q20: =$O20*C20*(1+$P$3)*(1+$P$4) -> 132.252 | R20: =$O20*D20*(1+$P$3)*(1+$P$4) -> 132.252 | S20: =$O20*E20*(1+$P$3)*(1+$P$4) -> 132.252 | T20: =$O20*F20*(1+$P$3)*(1+$P$4) -> 132.252 | U20: =$O20*G20*(1+$P$3)*(1+$P$4) -> 132.252 | V20: =$O20*H20*(1+$P$3)*(1+$P$4) -> 132.252 | W20: =$O20*I20*(1+$P$3)*(1+$P$4) -> 132.252 | ... AA20: =$O20*M20*(1+$P$3)*(1+$P$4) -> 132.252 | AB20: =SUM(P20:AA20) -> 1587.024 | AC20: 1 | AD20: =$AC20*P20*(1+$AD$3)*(1+$AD$4) -> 147.19648 | AE20: =$AC20*Q20*(1+$AD$3)*(1+$AD$4) -> 147.19648 | AF20: =$AC20*R20*(1+$AD$3)*(1+$AD$4) -> 147.19648 | AG20: =$AC20*S20*(1+$AD$3)*(1+$AD$4) -> 147.19648 | AH20: =$AC20*T20*(1+$AD$3)*(1+$AD$4) -> 147.19648 | AI20: =$AC20*U20*(1+$AD$3)*(1+$AD$4) -> 147.19648 | AJ20: =$AC20*V20*(1+$AD$3)*(1+$AD$4) -> 147.19648 | AK20: =$AC20*W20*(1+$AD$3)*(1+$AD$4) -> 147.19648 | ... AO20: =$AC20*AA20*(1+$AD$3)*(1+$AD$4) -> 147.19648 | AP20: =SUM(AD20:AO20) -> 1766.3577 | AQ20: 1 | AR20: =$AQ20*AD20*(1+$AR$3)*(1+$AR$4) -> 163.82968 | AS20: =$AQ20*AE20*(1+$AR$3)*(1+$AR$4) -> 163.82968 | AT20: =$AQ20*AF20*(1+$AR$3)*(1+$AR$4) -> 163.82968 | AU20: =$AQ20*AG20*(1+$AR$3)*(1+$AR$4) -> 163.82968 | AV20: =$AQ20*AH20*(1+$AR$3)*(1+$AR$4) -> 163.82968 | AW20: =$AQ20*AI20*(1+$AR$3)*(1+$AR$4) -> 163.82968 | AX20: =$AQ20*AJ20*(1+$AR$3)*(1+$AR$4) -> 163.82968 | AY20: =$AQ20*AK20*(1+$AR$3)*(1+$AR$4) -> 163.82968 | ... BC20: =$AQ20*AO20*(1+$AR$3)*(1+$AR$4) -> 163.82968 | BD20: =SUM(AR20:BC20) -> 1965.9561 | BE20: 1 | BF20: =$BE20*AR20*(1+$BF$3)*(1+$BF$4) -> 182.34243 | BG20: =$BE20*AS20*(1+$BF$3)*(1+$BF$4) -> 182.34243 | BH20: =$BE20*AT20*(1+$BF$3)*(1+$BF$4) -> 182.34243 | BI20: =$BE20*AU20*(1+$BF$3)*(1+$BF$4) -> 182.34243 | BJ20: =$BE20*AV20*(1+$BF$3)*(1+$BF$4) -> 182.34243 | BK20: =$BE20*AW20*(1+$BF$3)*(1+$BF$4) -> 182.34243 | BL20: =$BE20*AX20*(1+$BF$3)*(1+$BF$4) -> 182.34243 | BM20: =$BE20*AY20*(1+$BF$3)*(1+$BF$4) -> 182.34243 | ... BQ20: =$BE20*BC20*(1+$BF$3)*(1+$BF$4) -> 182.34243 | BR20: =SUM(BF20:BQ20) -> 2188.1092 | BS20: 1 | BT20: =$BS20*BF20*(1+$BT$3)*(1+$BT$4) -> 202.94713 | BU20: =$BS20*BG20*(1+$BT$3)*(1+$BT$4) -> 202.94713 | BV20: =$BS20*BH20*(1+$BT$3)*(1+$BT$4) -> 202.94713 | BW20: =$BS20*BI20*(1+$BT$3)*(1+$BT$4) -> 202.94713 | BX20: =$BS20*BJ20*(1+$BT$3)*(1+$BT$4) -> 202.94713 | BY20: =$BS20*BK20*(1+$BT$3)*(1+$BT$4) -> 202.94713 | BZ20: =$BS20*BL20*(1+$BT$3)*(1+$BT$4) -> 202.94713 | CA20: =$BS20*BM20*(1+$BT$3)*(1+$BT$4) -> 202.94713 | ... CE20: =$BS20*BQ20*(1+$BT$3)*(1+$BT$4) -> 202.94713 | CF20: =SUM(BT20:CE20) -> 2435.3655 | CG20: 1 | CH20: =$CG20*BT20*(1+$CH$3)*(1+$CH$4) -> 225.88015 | CI20: =$CG20*BU20*(1+$CH$3)*(1+$CH$4) -> 225.88015 | CJ20: =$CG20*BV20*(1+$CH$3)*(1+$CH$4) -> 225.88015 | CK20: =$CG20*BW20*(1+$CH$3)*(1+$CH$4) -> 225.88015 | CL20: =$CG20*BX20*(1+$CH$3)*(1+$CH$4) -> 225.88015 | CM20: =$CG20*BY20*(1+$CH$3)*(1+$CH$4) -> 225.88015 | CN20: =$CG20*BZ20*(1+$CH$3)*(1+$CH$4) -> 225.88015 | CO20: =$CG20*CA20*(1+$CH$3)*(1+$CH$4) -> 225.88015 | ... CS20: =$CG20*CE20*(1+$CH$3)*(1+$CH$4) -> 225.88015 | CT20: =SUM(CH20:CS20) -> 2710.5618 | CU20: 1 | CV20: =$CU20*CH20*(1+$CV$3)*(1+$CV$4) -> 251.40461 | CW20: =$CU20*CI20*(1+$CV$3)*(1+$CV$4) -> 251.40461 | CX20: =$CU20*CJ20*(1+$CV$3)*(1+$CV$4) -> 251.40461 | CY20: =$CU20*CK20*(1+$CV$3)*(1+$CV$4) -> 251.40461 | CZ20: =$CU20*CL20*(1+$CV$3)*(1+$CV$4) -> 251.40461 | DA20: =$CU20*CM20*(1+$CV$3)*(1+$CV$4) -> 251.40461 | DB20: =$CU20*CN20*(1+$CV$3)*(1+$CV$4) -> 251.40461 | DC20: =$CU20*CO20*(1+$CV$3)*(1+$CV$4) -> 251.40461 | ... DG20: =$CU20*CS20*(1+$CV$3)*(1+$CV$4) -> 251.40461 | DH20: =SUM(CV20:DG20) -> 3016.8553 | DI20: 1 | DJ20: =$DI20*CV20*(1+$DJ$3)*(1+$DJ$4) -> 279.81333 | DK20: =$DI20*CW20*(1+$DJ$3)*(1+$DJ$4) -> 279.81333 | DL20: =$DI20*CX20*(1+$DJ$3)*(1+$DJ$4) -> 279.81333 | DM20: =$DI20*CY20*(1+$DJ$3)*(1+$DJ$4) -> 279.81333 | DN20: =$DI20*CZ20*(1+$DJ$3)*(1+$DJ$4) -> 279.81333 | DO20: =$DI20*DA20*(1+$DJ$3)*(1+$DJ$4) -> 279.81333 | DP20: =$DI20*DB20*(1+$DJ$3)*(1+$DJ$4) -> 279.81333 | DQ20: =$DI20*DC20*(1+$DJ$3)*(1+$DJ$4) -> 279.81333 | ... DU20: =$DI20*DG20*(1+$DJ$3)*(1+$DJ$4) -> 279.81333 | DV20: =SUM(DJ20:DU20) -> 3357.76 | DW20: 1 | DX20: =$DW20*DJ20*(1+$DX$3)*(1+$DX$4) -> 311.43224 | DY20: =$DW20*DK20*(1+$DX$3)*(1+$DX$4) -> 311.43224 | DZ20: =$DW20*DL20*(1+$DX$3)*(1+$DX$4) -> 311.43224 | EA20: =$DW20*DM20*(1+$DX$3)*(1+$DX$4) -> 311.43224 | EB20: =$DW20*DN20*(1+$DX$3)*(1+$DX$4) -> 311.43224 | EC20: =$DW20*DO20*(1+$DX$3)*(1+$DX$4) -> 311.43224 | ED20: =$DW20*DP20*(1+$DX$3)*(1+$DX$4) -> 311.43224 | EE20: =$DW20*DQ20*(1+$DX$3)*(1+$DX$4) -> 311.43224 | ... EI20: =$DW20*DU20*(1+$DX$3)*(1+$DX$4) -> 311.43224 | EJ20: =SUM(DX20:EI20) -> 3737.1868
A21: Lija | B21: 300 | C21: =B21*(1+C$3) -> 300 | D21: =C21*(1+D$3) -> 300 | E21: =D21*(1+E$3) -> 300 | F21: =E21*(1+F$3) -> 300 | G21: =F21*(1+G$3) -> 300 | H21: =G21*(1+H$3) -> 300 | I21: =H21*(1+I$3) -> 300 | J21: =I21*(1+J$3) -> 300 | ... M21: =L21*(1+M$3) -> 300 | N21: =SUM(B21:M21) -> 3600 | O21: 1 | P21: =$O21*B21*(1+$P$3)*(1+$P$4) -> 330.63 | Q21: =$O21*C21*(1+$P$3)*(1+$P$4) -> 330.63 | R21: =$O21*D21*(1+$P$3)*(1+$P$4) -> 330.63 | S21: =$O21*E21*(1+$P$3)*(1+$P$4) -> 330.63 | T21: =$O21*F21*(1+$P$3)*(1+$P$4) -> 330.63 | U21: =$O21*G21*(1+$P$3)*(1+$P$4) -> 330.63 | V21: =$O21*H21*(1+$P$3)*(1+$P$4) -> 330.63 | W21: =$O21*I21*(1+$P$3)*(1+$P$4) -> 330.63 | ... AA21: =$O21*M21*(1+$P$3)*(1+$P$4) -> 330.63 | AB21: =SUM(P21:AA21) -> 3967.56 | AC21: 1 | AD21: =$AC21*P21*(1+$AD$3)*(1+$AD$4) -> 367.99119 | AE21: =$AC21*Q21*(1+$AD$3)*(1+$AD$4) -> 367.99119 | AF21: =$AC21*R21*(1+$AD$3)*(1+$AD$4) -> 367.99119 | AG21: =$AC21*S21*(1+$AD$3)*(1+$AD$4) -> 367.99119 | AH21: =$AC21*T21*(1+$AD$3)*(1+$AD$4) -> 367.99119 | AI21: =$AC21*U21*(1+$AD$3)*(1+$AD$4) -> 367.99119 | AJ21: =$AC21*V21*(1+$AD$3)*(1+$AD$4) -> 367.99119 | AK21: =$AC21*W21*(1+$AD$3)*(1+$AD$4) -> 367.99119 | ... AO21: =$AC21*AA21*(1+$AD$3)*(1+$AD$4) -> 367.99119 | AP21: =SUM(AD21:AO21) -> 4415.8943 | AQ21: 1 | AR21: =$AQ21*AD21*(1+$AR$3)*(1+$AR$4) -> 409.57419 | AS21: =$AQ21*AE21*(1+$AR$3)*(1+$AR$4) -> 409.57419 | AT21: =$AQ21*AF21*(1+$AR$3)*(1+$AR$4) -> 409.57419 | AU21: =$AQ21*AG21*(1+$AR$3)*(1+$AR$4) -> 409.57419 | AV21: =$AQ21*AH21*(1+$AR$3)*(1+$AR$4) -> 409.57419 | AW21: =$AQ21*AI21*(1+$AR$3)*(1+$AR$4) -> 409.57419 | AX21: =$AQ21*AJ21*(1+$AR$3)*(1+$AR$4) -> 409.57419 | AY21: =$AQ21*AK21*(1+$AR$3)*(1+$AR$4) -> 409.57419 | ... BC21: =$AQ21*AO21*(1+$AR$3)*(1+$AR$4) -> 409.57419 | BD21: =SUM(AR21:BC21) -> 4914.8903 | BE21: 1 | BF21: =$BE21*AR21*(1+$BF$3)*(1+$BF$4) -> 455.85608 | BG21: =$BE21*AS21*(1+$BF$3)*(1+$BF$4) -> 455.85608 | BH21: =$BE21*AT21*(1+$BF$3)*(1+$BF$4) -> 455.85608 | BI21: =$BE21*AU21*(1+$BF$3)*(1+$BF$4) -> 455.85608 | BJ21: =$BE21*AV21*(1+$BF$3)*(1+$BF$4) -> 455.85608 | BK21: =$BE21*AW21*(1+$BF$3)*(1+$BF$4) -> 455.85608 | BL21: =$BE21*AX21*(1+$BF$3)*(1+$BF$4) -> 455.85608 | BM21: =$BE21*AY21*(1+$BF$3)*(1+$BF$4) -> 455.85608 | ... BQ21: =$BE21*BC21*(1+$BF$3)*(1+$BF$4) -> 455.85608 | BR21: =SUM(BF21:BQ21) -> 5470.2729 | BS21: 1 | BT21: =$BS21*BF21*(1+$BT$3)*(1+$BT$4) -> 507.36782 | BU21: =$BS21*BG21*(1+$BT$3)*(1+$BT$4) -> 507.36782 | BV21: =$BS21*BH21*(1+$BT$3)*(1+$BT$4) -> 507.36782 | BW21: =$BS21*BI21*(1+$BT$3)*(1+$BT$4) -> 507.36782 | BX21: =$BS21*BJ21*(1+$BT$3)*(1+$BT$4) -> 507.36782 | BY21: =$BS21*BK21*(1+$BT$3)*(1+$BT$4) -> 507.36782 | BZ21: =$BS21*BL21*(1+$BT$3)*(1+$BT$4) -> 507.36782 | CA21: =$BS21*BM21*(1+$BT$3)*(1+$BT$4) -> 507.36782 | ... CE21: =$BS21*BQ21*(1+$BT$3)*(1+$BT$4) -> 507.36782 | CF21: =SUM(BT21:CE21) -> 6088.4138 | CG21: 1 | CH21: =$CG21*BT21*(1+$CH$3)*(1+$CH$4) -> 564.70038 | CI21: =$CG21*BU21*(1+$CH$3)*(1+$CH$4) -> 564.70038 | CJ21: =$CG21*BV21*(1+$CH$3)*(1+$CH$4) -> 564.70038 | CK21: =$CG21*BW21*(1+$CH$3)*(1+$CH$4) -> 564.70038 | CL21: =$CG21*BX21*(1+$CH$3)*(1+$CH$4) -> 564.70038 | CM21: =$CG21*BY21*(1+$CH$3)*(1+$CH$4) -> 564.70038 | CN21: =$CG21*BZ21*(1+$CH$3)*(1+$CH$4) -> 564.70038 | CO21: =$CG21*CA21*(1+$CH$3)*(1+$CH$4) -> 564.70038 | ... CS21: =$CG21*CE21*(1+$CH$3)*(1+$CH$4) -> 564.70038 | CT21: =SUM(CH21:CS21) -> 6776.4045 | CU21: 1 | CV21: =$CU21*CH21*(1+$CV$3)*(1+$CV$4) -> 628.51152 | CW21: =$CU21*CI21*(1+$CV$3)*(1+$CV$4) -> 628.51152 | CX21: =$CU21*CJ21*(1+$CV$3)*(1+$CV$4) -> 628.51152 | CY21: =$CU21*CK21*(1+$CV$3)*(1+$CV$4) -> 628.51152 | CZ21: =$CU21*CL21*(1+$CV$3)*(1+$CV$4) -> 628.51152 | DA21: =$CU21*CM21*(1+$CV$3)*(1+$CV$4) -> 628.51152 | DB21: =$CU21*CN21*(1+$CV$3)*(1+$CV$4) -> 628.51152 | DC21: =$CU21*CO21*(1+$CV$3)*(1+$CV$4) -> 628.51152 | ... DG21: =$CU21*CS21*(1+$CV$3)*(1+$CV$4) -> 628.51152 | DH21: =SUM(CV21:DG21) -> 7542.1383 | DI21: 1 | DJ21: =$DI21*CV21*(1+$DJ$3)*(1+$DJ$4) -> 699.53332 | DK21: =$DI21*CW21*(1+$DJ$3)*(1+$DJ$4) -> 699.53332 | DL21: =$DI21*CX21*(1+$DJ$3)*(1+$DJ$4) -> 699.53332 | DM21: =$DI21*CY21*(1+$DJ$3)*(1+$DJ$4) -> 699.53332 | DN21: =$DI21*CZ21*(1+$DJ$3)*(1+$DJ$4) -> 699.53332 | DO21: =$DI21*DA21*(1+$DJ$3)*(1+$DJ$4) -> 699.53332 | DP21: =$DI21*DB21*(1+$DJ$3)*(1+$DJ$4) -> 699.53332 | DQ21: =$DI21*DC21*(1+$DJ$3)*(1+$DJ$4) -> 699.53332 | ... DU21: =$DI21*DG21*(1+$DJ$3)*(1+$DJ$4) -> 699.53332 | DV21: =SUM(DJ21:DU21) -> 8394.3999 | DW21: 1 | DX21: =$DW21*DJ21*(1+$DX$3)*(1+$DX$4) -> 778.58059 | DY21: =$DW21*DK21*(1+$DX$3)*(1+$DX$4) -> 778.58059 | DZ21: =$DW21*DL21*(1+$DX$3)*(1+$DX$4) -> 778.58059 | EA21: =$DW21*DM21*(1+$DX$3)*(1+$DX$4) -> 778.58059 | EB21: =$DW21*DN21*(1+$DX$3)*(1+$DX$4) -> 778.58059 | EC21: =$DW21*DO21*(1+$DX$3)*(1+$DX$4) -> 778.58059 | ED21: =$DW21*DP21*(1+$DX$3)*(1+$DX$4) -> 778.58059 | EE21: =$DW21*DQ21*(1+$DX$3)*(1+$DX$4) -> 778.58059 | ... EI21: =$DW21*DU21*(1+$DX$3)*(1+$DX$4) -> 778.58059 | EJ21: =SUM(DX21:EI21) -> 9342.9671
A22: Pintura o barniz | B22: 800 | C22: =B22*(1+C$3) -> 800 | D22: =C22*(1+D$3) -> 800 | E22: =D22*(1+E$3) -> 800 | F22: =E22*(1+F$3) -> 800 | G22: =F22*(1+G$3) -> 800 | H22: =G22*(1+H$3) -> 800 | I22: =H22*(1+I$3) -> 800 | J22: =I22*(1+J$3) -> 800 | ... M22: =L22*(1+M$3) -> 800 | N22: =SUM(B22:M22) -> 9600 | O22: 1 | P22: =$O22*B22*(1+$P$3)*(1+$P$4) -> 881.68 | Q22: =$O22*C22*(1+$P$3)*(1+$P$4) -> 881.68 | R22: =$O22*D22*(1+$P$3)*(1+$P$4) -> 881.68 | S22: =$O22*E22*(1+$P$3)*(1+$P$4) -> 881.68 | T22: =$O22*F22*(1+$P$3)*(1+$P$4) -> 881.68 | U22: =$O22*G22*(1+$P$3)*(1+$P$4) -> 881.68 | V22: =$O22*H22*(1+$P$3)*(1+$P$4) -> 881.68 | W22: =$O22*I22*(1+$P$3)*(1+$P$4) -> 881.68 | ... AA22: =$O22*M22*(1+$P$3)*(1+$P$4) -> 881.68 | AB22: =SUM(P22:AA22) -> 10580.16 | AC22: 1 | AD22: =$AC22*P22*(1+$AD$3)*(1+$AD$4) -> 981.30984 | AE22: =$AC22*Q22*(1+$AD$3)*(1+$AD$4) -> 981.30984 | AF22: =$AC22*R22*(1+$AD$3)*(1+$AD$4) -> 981.30984 | AG22: =$AC22*S22*(1+$AD$3)*(1+$AD$4) -> 981.30984 | AH22: =$AC22*T22*(1+$AD$3)*(1+$AD$4) -> 981.30984 | AI22: =$AC22*U22*(1+$AD$3)*(1+$AD$4) -> 981.30984 | AJ22: =$AC22*V22*(1+$AD$3)*(1+$AD$4) -> 981.30984 | AK22: =$AC22*W22*(1+$AD$3)*(1+$AD$4) -> 981.30984 | ... AO22: =$AC22*AA22*(1+$AD$3)*(1+$AD$4) -> 981.30984 | AP22: =SUM(AD22:AO22) -> 11775.718 | AQ22: 1 | AR22: =$AQ22*AD22*(1+$AR$3)*(1+$AR$4) -> 1092.1979 | AS22: =$AQ22*AE22*(1+$AR$3)*(1+$AR$4) -> 1092.1979 | AT22: =$AQ22*AF22*(1+$AR$3)*(1+$AR$4) -> 1092.1979 | AU22: =$AQ22*AG22*(1+$AR$3)*(1+$AR$4) -> 1092.1979 | AV22: =$AQ22*AH22*(1+$AR$3)*(1+$AR$4) -> 1092.1979 | AW22: =$AQ22*AI22*(1+$AR$3)*(1+$AR$4) -> 1092.1979 | AX22: =$AQ22*AJ22*(1+$AR$3)*(1+$AR$4) -> 1092.1979 | AY22: =$AQ22*AK22*(1+$AR$3)*(1+$AR$4) -> 1092.1979 | ... BC22: =$AQ22*AO22*(1+$AR$3)*(1+$AR$4) -> 1092.1979 | BD22: =SUM(AR22:BC22) -> 13106.374 | BE22: 1 | BF22: =$BE22*AR22*(1+$BF$3)*(1+$BF$4) -> 1215.6162 | BG22: =$BE22*AS22*(1+$BF$3)*(1+$BF$4) -> 1215.6162 | BH22: =$BE22*AT22*(1+$BF$3)*(1+$BF$4) -> 1215.6162 | BI22: =$BE22*AU22*(1+$BF$3)*(1+$BF$4) -> 1215.6162 | BJ22: =$BE22*AV22*(1+$BF$3)*(1+$BF$4) -> 1215.6162 | BK22: =$BE22*AW22*(1+$BF$3)*(1+$BF$4) -> 1215.6162 | BL22: =$BE22*AX22*(1+$BF$3)*(1+$BF$4) -> 1215.6162 | BM22: =$BE22*AY22*(1+$BF$3)*(1+$BF$4) -> 1215.6162 | ... BQ22: =$BE22*BC22*(1+$BF$3)*(1+$BF$4) -> 1215.6162 | BR22: =SUM(BF22:BQ22) -> 14587.395 | BS22: 1 | BT22: =$BS22*BF22*(1+$BT$3)*(1+$BT$4) -> 1352.9808 | BU22: =$BS22*BG22*(1+$BT$3)*(1+$BT$4) -> 1352.9808 | BV22: =$BS22*BH22*(1+$BT$3)*(1+$BT$4) -> 1352.9808 | BW22: =$BS22*BI22*(1+$BT$3)*(1+$BT$4) -> 1352.9808 | BX22: =$BS22*BJ22*(1+$BT$3)*(1+$BT$4) -> 1352.9808 | BY22: =$BS22*BK22*(1+$BT$3)*(1+$BT$4) -> 1352.9808 | BZ22: =$BS22*BL22*(1+$BT$3)*(1+$BT$4) -> 1352.9808 | CA22: =$BS22*BM22*(1+$BT$3)*(1+$BT$4) -> 1352.9808 | ... CE22: =$BS22*BQ22*(1+$BT$3)*(1+$BT$4) -> 1352.9808 | CF22: =SUM(BT22:CE22) -> 16235.77 | CG22: 1 | CH22: =$CG22*BT22*(1+$CH$3)*(1+$CH$4) -> 1505.8677 | CI22: =$CG22*BU22*(1+$CH$3)*(1+$CH$4) -> 1505.8677 | CJ22: =$CG22*BV22*(1+$CH$3)*(1+$CH$4) -> 1505.8677 | CK22: =$CG22*BW22*(1+$CH$3)*(1+$CH$4) -> 1505.8677 | CL22: =$CG22*BX22*(1+$CH$3)*(1+$CH$4) -> 1505.8677 | CM22: =$CG22*BY22*(1+$CH$3)*(1+$CH$4) -> 1505.8677 | CN22: =$CG22*BZ22*(1+$CH$3)*(1+$CH$4) -> 1505.8677 | CO22: =$CG22*CA22*(1+$CH$3)*(1+$CH$4) -> 1505.8677 | ... CS22: =$CG22*CE22*(1+$CH$3)*(1+$CH$4) -> 1505.8677 | CT22: =SUM(CH22:CS22) -> 18070.412 | CU22: 1 | CV22: =$CU22*CH22*(1+$CV$3)*(1+$CV$4) -> 1676.0307 | CW22: =$CU22*CI22*(1+$CV$3)*(1+$CV$4) -> 1676.0307 | CX22: =$CU22*CJ22*(1+$CV$3)*(1+$CV$4) -> 1676.0307 | CY22: =$CU22*CK22*(1+$CV$3)*(1+$CV$4) -> 1676.0307 | CZ22: =$CU22*CL22*(1+$CV$3)*(1+$CV$4) -> 1676.0307 | DA22: =$CU22*CM22*(1+$CV$3)*(1+$CV$4) -> 1676.0307 | DB22: =$CU22*CN22*(1+$CV$3)*(1+$CV$4) -> 1676.0307 | DC22: =$CU22*CO22*(1+$CV$3)*(1+$CV$4) -> 1676.0307 | ... DG22: =$CU22*CS22*(1+$CV$3)*(1+$CV$4) -> 1676.0307 | DH22: =SUM(CV22:DG22) -> 20112.369 | DI22: 1 | DJ22: =$DI22*CV22*(1+$DJ$3)*(1+$DJ$4) -> 1865.4222 | DK22: =$DI22*CW22*(1+$DJ$3)*(1+$DJ$4) -> 1865.4222 | DL22: =$DI22*CX22*(1+$DJ$3)*(1+$DJ$4) -> 1865.4222 | DM22: =$DI22*CY22*(1+$DJ$3)*(1+$DJ$4) -> 1865.4222 | DN22: =$DI22*CZ22*(1+$DJ$3)*(1+$DJ$4) -> 1865.4222 | DO22: =$DI22*DA22*(1+$DJ$3)*(1+$DJ$4) -> 1865.4222 | DP22: =$DI22*DB22*(1+$DJ$3)*(1+$DJ$4) -> 1865.4222 | DQ22: =$DI22*DC22*(1+$DJ$3)*(1+$DJ$4) -> 1865.4222 | ... DU22: =$DI22*DG22*(1+$DJ$3)*(1+$DJ$4) -> 1865.4222 | DV22: =SUM(DJ22:DU22) -> 22385.066 | DW22: 1 | DX22: =$DW22*DJ22*(1+$DX$3)*(1+$DX$4) -> 2076.2149 | DY22: =$DW22*DK22*(1+$DX$3)*(1+$DX$4) -> 2076.2149 | DZ22: =$DW22*DL22*(1+$DX$3)*(1+$DX$4) -> 2076.2149 | EA22: =$DW22*DM22*(1+$DX$3)*(1+$DX$4) -> 2076.2149 | EB22: =$DW22*DN22*(1+$DX$3)*(1+$DX$4) -> 2076.2149 | EC22: =$DW22*DO22*(1+$DX$3)*(1+$DX$4) -> 2076.2149 | ED22: =$DW22*DP22*(1+$DX$3)*(1+$DX$4) -> 2076.2149 | EE22: =$DW22*DQ22*(1+$DX$3)*(1+$DX$4) -> 2076.2149 | ... EI22: =$DW22*DU22*(1+$DX$3)*(1+$DX$4) -> 2076.2149 | EJ22: =SUM(DX22:EI22) -> 24914.579
A23: Tornillos pequeños | B23: 80 | C23: =B23*(1+C$3) -> 80 | D23: =C23*(1+D$3) -> 80 | E23: =D23*(1+E$3) -> 80 | F23: =E23*(1+F$3) -> 80 | G23: =F23*(1+G$3) -> 80 | H23: =G23*(1+H$3) -> 80 | I23: =H23*(1+I$3) -> 80 | J23: =I23*(1+J$3) -> 80 | ... M23: =L23*(1+M$3) -> 80 | N23: =SUM(B23:M23) -> 960 | O23: 1 | P23: =$O23*B23*(1+$P$3)*(1+$P$4) -> 88.168 | Q23: =$O23*C23*(1+$P$3)*(1+$P$4) -> 88.168 | R23: =$O23*D23*(1+$P$3)*(1+$P$4) -> 88.168 | S23: =$O23*E23*(1+$P$3)*(1+$P$4) -> 88.168 | T23: =$O23*F23*(1+$P$3)*(1+$P$4) -> 88.168 | U23: =$O23*G23*(1+$P$3)*(1+$P$4) -> 88.168 | V23: =$O23*H23*(1+$P$3)*(1+$P$4) -> 88.168 | W23: =$O23*I23*(1+$P$3)*(1+$P$4) -> 88.168 | ... AA23: =$O23*M23*(1+$P$3)*(1+$P$4) -> 88.168 | AB23: =SUM(P23:AA23) -> 1058.016 | AC23: 1 | AD23: =$AC23*P23*(1+$AD$3)*(1+$AD$4) -> 98.130984 | AE23: =$AC23*Q23*(1+$AD$3)*(1+$AD$4) -> 98.130984 | AF23: =$AC23*R23*(1+$AD$3)*(1+$AD$4) -> 98.130984 | AG23: =$AC23*S23*(1+$AD$3)*(1+$AD$4) -> 98.130984 | AH23: =$AC23*T23*(1+$AD$3)*(1+$AD$4) -> 98.130984 | AI23: =$AC23*U23*(1+$AD$3)*(1+$AD$4) -> 98.130984 | AJ23: =$AC23*V23*(1+$AD$3)*(1+$AD$4) -> 98.130984 | AK23: =$AC23*W23*(1+$AD$3)*(1+$AD$4) -> 98.130984 | ... AO23: =$AC23*AA23*(1+$AD$3)*(1+$AD$4) -> 98.130984 | AP23: =SUM(AD23:AO23) -> 1177.5718 | AQ23: 1 | AR23: =$AQ23*AD23*(1+$AR$3)*(1+$AR$4) -> 109.21979 | AS23: =$AQ23*AE23*(1+$AR$3)*(1+$AR$4) -> 109.21979 | AT23: =$AQ23*AF23*(1+$AR$3)*(1+$AR$4) -> 109.21979 | AU23: =$AQ23*AG23*(1+$AR$3)*(1+$AR$4) -> 109.21979 | AV23: =$AQ23*AH23*(1+$AR$3)*(1+$AR$4) -> 109.21979 | AW23: =$AQ23*AI23*(1+$AR$3)*(1+$AR$4) -> 109.21979 | AX23: =$AQ23*AJ23*(1+$AR$3)*(1+$AR$4) -> 109.21979 | AY23: =$AQ23*AK23*(1+$AR$3)*(1+$AR$4) -> 109.21979 | ... BC23: =$AQ23*AO23*(1+$AR$3)*(1+$AR$4) -> 109.21979 | BD23: =SUM(AR23:BC23) -> 1310.6374 | BE23: 1 | BF23: =$BE23*AR23*(1+$BF$3)*(1+$BF$4) -> 121.56162 | BG23: =$BE23*AS23*(1+$BF$3)*(1+$BF$4) -> 121.56162 | BH23: =$BE23*AT23*(1+$BF$3)*(1+$BF$4) -> 121.56162 | BI23: =$BE23*AU23*(1+$BF$3)*(1+$BF$4) -> 121.56162 | BJ23: =$BE23*AV23*(1+$BF$3)*(1+$BF$4) -> 121.56162 | BK23: =$BE23*AW23*(1+$BF$3)*(1+$BF$4) -> 121.56162 | BL23: =$BE23*AX23*(1+$BF$3)*(1+$BF$4) -> 121.56162 | BM23: =$BE23*AY23*(1+$BF$3)*(1+$BF$4) -> 121.56162 | ... BQ23: =$BE23*BC23*(1+$BF$3)*(1+$BF$4) -> 121.56162 | BR23: =SUM(BF23:BQ23) -> 1458.7395 | BS23: 1 | BT23: =$BS23*BF23*(1+$BT$3)*(1+$BT$4) -> 135.29808 | BU23: =$BS23*BG23*(1+$BT$3)*(1+$BT$4) -> 135.29808 | BV23: =$BS23*BH23*(1+$BT$3)*(1+$BT$4) -> 135.29808 | BW23: =$BS23*BI23*(1+$BT$3)*(1+$BT$4) -> 135.29808 | BX23: =$BS23*BJ23*(1+$BT$3)*(1+$BT$4) -> 135.29808 | BY23: =$BS23*BK23*(1+$BT$3)*(1+$BT$4) -> 135.29808 | BZ23: =$BS23*BL23*(1+$BT$3)*(1+$BT$4) -> 135.29808 | CA23: =$BS23*BM23*(1+$BT$3)*(1+$BT$4) -> 135.29808 | ... CE23: =$BS23*BQ23*(1+$BT$3)*(1+$BT$4) -> 135.29808 | CF23: =SUM(BT23:CE23) -> 1623.577 | CG23: 1 | CH23: =$CG23*BT23*(1+$CH$3)*(1+$CH$4) -> 150.58677 | CI23: =$CG23*BU23*(1+$CH$3)*(1+$CH$4) -> 150.58677 | CJ23: =$CG23*BV23*(1+$CH$3)*(1+$CH$4) -> 150.58677 | CK23: =$CG23*BW23*(1+$CH$3)*(1+$CH$4) -> 150.58677 | CL23: =$CG23*BX23*(1+$CH$3)*(1+$CH$4) -> 150.58677 | CM23: =$CG23*BY23*(1+$CH$3)*(1+$CH$4) -> 150.58677 | CN23: =$CG23*BZ23*(1+$CH$3)*(1+$CH$4) -> 150.58677 | CO23: =$CG23*CA23*(1+$CH$3)*(1+$CH$4) -> 150.58677 | ... CS23: =$CG23*CE23*(1+$CH$3)*(1+$CH$4) -> 150.58677 | CT23: =SUM(CH23:CS23) -> 1807.0412 | CU23: 1 | CV23: =$CU23*CH23*(1+$CV$3)*(1+$CV$4) -> 167.60307 | CW23: =$CU23*CI23*(1+$CV$3)*(1+$CV$4) -> 167.60307 | CX23: =$CU23*CJ23*(1+$CV$3)*(1+$CV$4) -> 167.60307 | CY23: =$CU23*CK23*(1+$CV$3)*(1+$CV$4) -> 167.60307 | CZ23: =$CU23*CL23*(1+$CV$3)*(1+$CV$4) -> 167.60307 | DA23: =$CU23*CM23*(1+$CV$3)*(1+$CV$4) -> 167.60307 | DB23: =$CU23*CN23*(1+$CV$3)*(1+$CV$4) -> 167.60307 | DC23: =$CU23*CO23*(1+$CV$3)*(1+$CV$4) -> 167.60307 | ... DG23: =$CU23*CS23*(1+$CV$3)*(1+$CV$4) -> 167.60307 | DH23: =SUM(CV23:DG23) -> 2011.2369 | DI23: 1 | DJ23: =$DI23*CV23*(1+$DJ$3)*(1+$DJ$4) -> 186.54222 | DK23: =$DI23*CW23*(1+$DJ$3)*(1+$DJ$4) -> 186.54222 | DL23: =$DI23*CX23*(1+$DJ$3)*(1+$DJ$4) -> 186.54222 | DM23: =$DI23*CY23*(1+$DJ$3)*(1+$DJ$4) -> 186.54222 | DN23: =$DI23*CZ23*(1+$DJ$3)*(1+$DJ$4) -> 186.54222 | DO23: =$DI23*DA23*(1+$DJ$3)*(1+$DJ$4) -> 186.54222 | DP23: =$DI23*DB23*(1+$DJ$3)*(1+$DJ$4) -> 186.54222 | DQ23: =$DI23*DC23*(1+$DJ$3)*(1+$DJ$4) -> 186.54222 | ... DU23: =$DI23*DG23*(1+$DJ$3)*(1+$DJ$4) -> 186.54222 | DV23: =SUM(DJ23:DU23) -> 2238.5066 | DW23: 1 | DX23: =$DW23*DJ23*(1+$DX$3)*(1+$DX$4) -> 207.62149 | DY23: =$DW23*DK23*(1+$DX$3)*(1+$DX$4) -> 207.62149 | DZ23: =$DW23*DL23*(1+$DX$3)*(1+$DX$4) -> 207.62149 | EA23: =$DW23*DM23*(1+$DX$3)*(1+$DX$4) -> 207.62149 | EB23: =$DW23*DN23*(1+$DX$3)*(1+$DX$4) -> 207.62149 | EC23: =$DW23*DO23*(1+$DX$3)*(1+$DX$4) -> 207.62149 | ED23: =$DW23*DP23*(1+$DX$3)*(1+$DX$4) -> 207.62149 | EE23: =$DW23*DQ23*(1+$DX$3)*(1+$DX$4) -> 207.62149 | ... EI23: =$DW23*DU23*(1+$DX$3)*(1+$DX$4) -> 207.62149 | EJ23: =SUM(DX23:EI23) -> 2491.4579
A24: Prime o sellador de madera | B24: 600 | C24: =B24*(1+C$3) -> 600 | D24: =C24*(1+D$3) -> 600 | E24: =D24*(1+E$3) -> 600 | F24: =E24*(1+F$3) -> 600 | G24: =F24*(1+G$3) -> 600 | H24: =G24*(1+H$3) -> 600 | I24: =H24*(1+I$3) -> 600 | J24: =I24*(1+J$3) -> 600 | ... M24: =L24*(1+M$3) -> 600 | N24: =SUM(B24:M24) -> 7200 | O24: 1 | P24: =$O24*B24*(1+$P$3)*(1+$P$4) -> 661.26 | Q24: =$O24*C24*(1+$P$3)*(1+$P$4) -> 661.26 | R24: =$O24*D24*(1+$P$3)*(1+$P$4) -> 661.26 | S24: =$O24*E24*(1+$P$3)*(1+$P$4) -> 661.26 | T24: =$O24*F24*(1+$P$3)*(1+$P$4) -> 661.26 | U24: =$O24*G24*(1+$P$3)*(1+$P$4) -> 661.26 | V24: =$O24*H24*(1+$P$3)*(1+$P$4) -> 661.26 | W24: =$O24*I24*(1+$P$3)*(1+$P$4) -> 661.26 | ... AA24: =$O24*M24*(1+$P$3)*(1+$P$4) -> 661.26 | AB24: =SUM(P24:AA24) -> 7935.12 | AC24: 1 | AD24: =$AC24*P24*(1+$AD$3)*(1+$AD$4) -> 735.98238 | AE24: =$AC24*Q24*(1+$AD$3)*(1+$AD$4) -> 735.98238 | AF24: =$AC24*R24*(1+$AD$3)*(1+$AD$4) -> 735.98238 | AG24: =$AC24*S24*(1+$AD$3)*(1+$AD$4) -> 735.98238 | AH24: =$AC24*T24*(1+$AD$3)*(1+$AD$4) -> 735.98238 | AI24: =$AC24*U24*(1+$AD$3)*(1+$AD$4) -> 735.98238 | AJ24: =$AC24*V24*(1+$AD$3)*(1+$AD$4) -> 735.98238 | AK24: =$AC24*W24*(1+$AD$3)*(1+$AD$4) -> 735.98238 | ... AO24: =$AC24*AA24*(1+$AD$3)*(1+$AD$4) -> 735.98238 | AP24: =SUM(AD24:AO24) -> 8831.7886 | AQ24: 1 | AR24: =$AQ24*AD24*(1+$AR$3)*(1+$AR$4) -> 819.14839 | AS24: =$AQ24*AE24*(1+$AR$3)*(1+$AR$4) -> 819.14839 | AT24: =$AQ24*AF24*(1+$AR$3)*(1+$AR$4) -> 819.14839 | AU24: =$AQ24*AG24*(1+$AR$3)*(1+$AR$4) -> 819.14839 | AV24: =$AQ24*AH24*(1+$AR$3)*(1+$AR$4) -> 819.14839 | AW24: =$AQ24*AI24*(1+$AR$3)*(1+$AR$4) -> 819.14839 | AX24: =$AQ24*AJ24*(1+$AR$3)*(1+$AR$4) -> 819.14839 | AY24: =$AQ24*AK24*(1+$AR$3)*(1+$AR$4) -> 819.14839 | ... BC24: =$AQ24*AO24*(1+$AR$3)*(1+$AR$4) -> 819.14839 | BD24: =SUM(AR24:BC24) -> 9829.7807 | BE24: 1 | BF24: =$BE24*AR24*(1+$BF$3)*(1+$BF$4) -> 911.71216 | BG24: =$BE24*AS24*(1+$BF$3)*(1+$BF$4) -> 911.71216 | BH24: =$BE24*AT24*(1+$BF$3)*(1+$BF$4) -> 911.71216 | BI24: =$BE24*AU24*(1+$BF$3)*(1+$BF$4) -> 911.71216 | BJ24: =$BE24*AV24*(1+$BF$3)*(1+$BF$4) -> 911.71216 | BK24: =$BE24*AW24*(1+$BF$3)*(1+$BF$4) -> 911.71216 | BL24: =$BE24*AX24*(1+$BF$3)*(1+$BF$4) -> 911.71216 | BM24: =$BE24*AY24*(1+$BF$3)*(1+$BF$4) -> 911.71216 | ... BQ24: =$BE24*BC24*(1+$BF$3)*(1+$BF$4) -> 911.71216 | BR24: =SUM(BF24:BQ24) -> 10940.546 | BS24: 1 | BT24: =$BS24*BF24*(1+$BT$3)*(1+$BT$4) -> 1014.7356 | BU24: =$BS24*BG24*(1+$BT$3)*(1+$BT$4) -> 1014.7356 | BV24: =$BS24*BH24*(1+$BT$3)*(1+$BT$4) -> 1014.7356 | BW24: =$BS24*BI24*(1+$BT$3)*(1+$BT$4) -> 1014.7356 | BX24: =$BS24*BJ24*(1+$BT$3)*(1+$BT$4) -> 1014.7356 | BY24: =$BS24*BK24*(1+$BT$3)*(1+$BT$4) -> 1014.7356 | BZ24: =$BS24*BL24*(1+$BT$3)*(1+$BT$4) -> 1014.7356 | CA24: =$BS24*BM24*(1+$BT$3)*(1+$BT$4) -> 1014.7356 | ... CE24: =$BS24*BQ24*(1+$BT$3)*(1+$BT$4) -> 1014.7356 | CF24: =SUM(BT24:CE24) -> 12176.828 | CG24: 1 | CH24: =$CG24*BT24*(1+$CH$3)*(1+$CH$4) -> 1129.4008 | CI24: =$CG24*BU24*(1+$CH$3)*(1+$CH$4) -> 1129.4008 | CJ24: =$CG24*BV24*(1+$CH$3)*(1+$CH$4) -> 1129.4008 | CK24: =$CG24*BW24*(1+$CH$3)*(1+$CH$4) -> 1129.4008 | CL24: =$CG24*BX24*(1+$CH$3)*(1+$CH$4) -> 1129.4008 | CM24: =$CG24*BY24*(1+$CH$3)*(1+$CH$4) -> 1129.4008 | CN24: =$CG24*BZ24*(1+$CH$3)*(1+$CH$4) -> 1129.4008 | CO24: =$CG24*CA24*(1+$CH$3)*(1+$CH$4) -> 1129.4008 | ... CS24: =$CG24*CE24*(1+$CH$3)*(1+$CH$4) -> 1129.4008 | CT24: =SUM(CH24:CS24) -> 13552.809 | CU24: 1 | CV24: =$CU24*CH24*(1+$CV$3)*(1+$CV$4) -> 1257.023 | CW24: =$CU24*CI24*(1+$CV$3)*(1+$CV$4) -> 1257.023 | CX24: =$CU24*CJ24*(1+$CV$3)*(1+$CV$4) -> 1257.023 | CY24: =$CU24*CK24*(1+$CV$3)*(1+$CV$4) -> 1257.023 | CZ24: =$CU24*CL24*(1+$CV$3)*(1+$CV$4) -> 1257.023 | DA24: =$CU24*CM24*(1+$CV$3)*(1+$CV$4) -> 1257.023 | DB24: =$CU24*CN24*(1+$CV$3)*(1+$CV$4) -> 1257.023 | DC24: =$CU24*CO24*(1+$CV$3)*(1+$CV$4) -> 1257.023 | ... DG24: =$CU24*CS24*(1+$CV$3)*(1+$CV$4) -> 1257.023 | DH24: =SUM(CV24:DG24) -> 15084.277 | DI24: 1 | DJ24: =$DI24*CV24*(1+$DJ$3)*(1+$DJ$4) -> 1399.0666 | DK24: =$DI24*CW24*(1+$DJ$3)*(1+$DJ$4) -> 1399.0666 | DL24: =$DI24*CX24*(1+$DJ$3)*(1+$DJ$4) -> 1399.0666 | DM24: =$DI24*CY24*(1+$DJ$3)*(1+$DJ$4) -> 1399.0666 | DN24: =$DI24*CZ24*(1+$DJ$3)*(1+$DJ$4) -> 1399.0666 | DO24: =$DI24*DA24*(1+$DJ$3)*(1+$DJ$4) -> 1399.0666 | DP24: =$DI24*DB24*(1+$DJ$3)*(1+$DJ$4) -> 1399.0666 | DQ24: =$DI24*DC24*(1+$DJ$3)*(1+$DJ$4) -> 1399.0666 | ... DU24: =$DI24*DG24*(1+$DJ$3)*(1+$DJ$4) -> 1399.0666 | DV24: =SUM(DJ24:DU24) -> 16788.8 | DW24: 1 | DX24: =$DW24*DJ24*(1+$DX$3)*(1+$DX$4) -> 1557.1612 | DY24: =$DW24*DK24*(1+$DX$3)*(1+$DX$4) -> 1557.1612 | DZ24: =$DW24*DL24*(1+$DX$3)*(1+$DX$4) -> 1557.1612 | EA24: =$DW24*DM24*(1+$DX$3)*(1+$DX$4) -> 1557.1612 | EB24: =$DW24*DN24*(1+$DX$3)*(1+$DX$4) -> 1557.1612 | EC24: =$DW24*DO24*(1+$DX$3)*(1+$DX$4) -> 1557.1612 | ED24: =$DW24*DP24*(1+$DX$3)*(1+$DX$4) -> 1557.1612 | EE24: =$DW24*DQ24*(1+$DX$3)*(1+$DX$4) -> 1557.1612 | ... EI24: =$DW24*DU24*(1+$DX$3)*(1+$DX$4) -> 1557.1612 | EJ24: =SUM(DX24:EI24) -> 18685.934
A25: Soporte para colgar marco | B25: 100 | C25: =B25*(1+C$3) -> 100 | D25: =C25*(1+D$3) -> 100 | E25: =D25*(1+E$3) -> 100 | F25: =E25*(1+F$3) -> 100 | G25: =F25*(1+G$3) -> 100 | H25: =G25*(1+H$3) -> 100 | I25: =H25*(1+I$3) -> 100 | J25: =I25*(1+J$3) -> 100 | ... M25: =L25*(1+M$3) -> 100 | N25: =SUM(B25:M25) -> 1200 | O25: 1 | P25: =$O25*B25*(1+$P$3)*(1+$P$4) -> 110.21 | Q25: =$O25*C25*(1+$P$3)*(1+$P$4) -> 110.21 | R25: =$O25*D25*(1+$P$3)*(1+$P$4) -> 110.21 | S25: =$O25*E25*(1+$P$3)*(1+$P$4) -> 110.21 | T25: =$O25*F25*(1+$P$3)*(1+$P$4) -> 110.21 | U25: =$O25*G25*(1+$P$3)*(1+$P$4) -> 110.21 | V25: =$O25*H25*(1+$P$3)*(1+$P$4) -> 110.21 | W25: =$O25*I25*(1+$P$3)*(1+$P$4) -> 110.21 | ... AA25: =$O25*M25*(1+$P$3)*(1+$P$4) -> 110.21 | AB25: =SUM(P25:AA25) -> 1322.52 | AC25: 1 | AD25: =$AC25*P25*(1+$AD$3)*(1+$AD$4) -> 122.66373 | AE25: =$AC25*Q25*(1+$AD$3)*(1+$AD$4) -> 122.66373 | AF25: =$AC25*R25*(1+$AD$3)*(1+$AD$4) -> 122.66373 | AG25: =$AC25*S25*(1+$AD$3)*(1+$AD$4) -> 122.66373 | AH25: =$AC25*T25*(1+$AD$3)*(1+$AD$4) -> 122.66373 | AI25: =$AC25*U25*(1+$AD$3)*(1+$AD$4) -> 122.66373 | AJ25: =$AC25*V25*(1+$AD$3)*(1+$AD$4) -> 122.66373 | AK25: =$AC25*W25*(1+$AD$3)*(1+$AD$4) -> 122.66373 | ... AO25: =$AC25*AA25*(1+$AD$3)*(1+$AD$4) -> 122.66373 | AP25: =SUM(AD25:AO25) -> 1471.9648 | AQ25: 1 | AR25: =$AQ25*AD25*(1+$AR$3)*(1+$AR$4) -> 136.52473 | AS25: =$AQ25*AE25*(1+$AR$3)*(1+$AR$4) -> 136.52473 | AT25: =$AQ25*AF25*(1+$AR$3)*(1+$AR$4) -> 136.52473 | AU25: =$AQ25*AG25*(1+$AR$3)*(1+$AR$4) -> 136.52473 | AV25: =$AQ25*AH25*(1+$AR$3)*(1+$AR$4) -> 136.52473 | AW25: =$AQ25*AI25*(1+$AR$3)*(1+$AR$4) -> 136.52473 | AX25: =$AQ25*AJ25*(1+$AR$3)*(1+$AR$4) -> 136.52473 | AY25: =$AQ25*AK25*(1+$AR$3)*(1+$AR$4) -> 136.52473 | ... BC25: =$AQ25*AO25*(1+$AR$3)*(1+$AR$4) -> 136.52473 | BD25: =SUM(AR25:BC25) -> 1638.2968 | BE25: 1 | BF25: =$BE25*AR25*(1+$BF$3)*(1+$BF$4) -> 151.95203 | BG25: =$BE25*AS25*(1+$BF$3)*(1+$BF$4) -> 151.95203 | BH25: =$BE25*AT25*(1+$BF$3)*(1+$BF$4) -> 151.95203 | BI25: =$BE25*AU25*(1+$BF$3)*(1+$BF$4) -> 151.95203 | BJ25: =$BE25*AV25*(1+$BF$3)*(1+$BF$4) -> 151.95203 | BK25: =$BE25*AW25*(1+$BF$3)*(1+$BF$4) -> 151.95203 | BL25: =$BE25*AX25*(1+$BF$3)*(1+$BF$4) -> 151.95203 | BM25: =$BE25*AY25*(1+$BF$3)*(1+$BF$4) -> 151.95203 | ... BQ25: =$BE25*BC25*(1+$BF$3)*(1+$BF$4) -> 151.95203 | BR25: =SUM(BF25:BQ25) -> 1823.4243 | BS25: 1 | BT25: =$BS25*BF25*(1+$BT$3)*(1+$BT$4) -> 169.12261 | BU25: =$BS25*BG25*(1+$BT$3)*(1+$BT$4) -> 169.12261 | BV25: =$BS25*BH25*(1+$BT$3)*(1+$BT$4) -> 169.12261 | BW25: =$BS25*BI25*(1+$BT$3)*(1+$BT$4) -> 169.12261 | BX25: =$BS25*BJ25*(1+$BT$3)*(1+$BT$4) -> 169.12261 | BY25: =$BS25*BK25*(1+$BT$3)*(1+$BT$4) -> 169.12261 | BZ25: =$BS25*BL25*(1+$BT$3)*(1+$BT$4) -> 169.12261 | CA25: =$BS25*BM25*(1+$BT$3)*(1+$BT$4) -> 169.12261 | ... CE25: =$BS25*BQ25*(1+$BT$3)*(1+$BT$4) -> 169.12261 | CF25: =SUM(BT25:CE25) -> 2029.4713 | CG25: 1 | CH25: =$CG25*BT25*(1+$CH$3)*(1+$CH$4) -> 188.23346 | CI25: =$CG25*BU25*(1+$CH$3)*(1+$CH$4) -> 188.23346 | CJ25: =$CG25*BV25*(1+$CH$3)*(1+$CH$4) -> 188.23346 | CK25: =$CG25*BW25*(1+$CH$3)*(1+$CH$4) -> 188.23346 | CL25: =$CG25*BX25*(1+$CH$3)*(1+$CH$4) -> 188.23346 | CM25: =$CG25*BY25*(1+$CH$3)*(1+$CH$4) -> 188.23346 | CN25: =$CG25*BZ25*(1+$CH$3)*(1+$CH$4) -> 188.23346 | CO25: =$CG25*CA25*(1+$CH$3)*(1+$CH$4) -> 188.23346 | ... CS25: =$CG25*CE25*(1+$CH$3)*(1+$CH$4) -> 188.23346 | CT25: =SUM(CH25:CS25) -> 2258.8015 | CU25: 1 | CV25: =$CU25*CH25*(1+$CV$3)*(1+$CV$4) -> 209.50384 | CW25: =$CU25*CI25*(1+$CV$3)*(1+$CV$4) -> 209.50384 | CX25: =$CU25*CJ25*(1+$CV$3)*(1+$CV$4) -> 209.50384 | CY25: =$CU25*CK25*(1+$CV$3)*(1+$CV$4) -> 209.50384 | CZ25: =$CU25*CL25*(1+$CV$3)*(1+$CV$4) -> 209.50384 | DA25: =$CU25*CM25*(1+$CV$3)*(1+$CV$4) -> 209.50384 | DB25: =$CU25*CN25*(1+$CV$3)*(1+$CV$4) -> 209.50384 | DC25: =$CU25*CO25*(1+$CV$3)*(1+$CV$4) -> 209.50384 | ... DG25: =$CU25*CS25*(1+$CV$3)*(1+$CV$4) -> 209.50384 | DH25: =SUM(CV25:DG25) -> 2514.0461 | DI25: 1 | DJ25: =$DI25*CV25*(1+$DJ$3)*(1+$DJ$4) -> 233.17777 | DK25: =$DI25*CW25*(1+$DJ$3)*(1+$DJ$4) -> 233.17777 | DL25: =$DI25*CX25*(1+$DJ$3)*(1+$DJ$4) -> 233.17777 | DM25: =$DI25*CY25*(1+$DJ$3)*(1+$DJ$4) -> 233.17777 | DN25: =$DI25*CZ25*(1+$DJ$3)*(1+$DJ$4) -> 233.17777 | DO25: =$DI25*DA25*(1+$DJ$3)*(1+$DJ$4) -> 233.17777 | DP25: =$DI25*DB25*(1+$DJ$3)*(1+$DJ$4) -> 233.17777 | DQ25: =$DI25*DC25*(1+$DJ$3)*(1+$DJ$4) -> 233.17777 | ... DU25: =$DI25*DG25*(1+$DJ$3)*(1+$DJ$4) -> 233.17777 | DV25: =SUM(DJ25:DU25) -> 2798.1333 | DW25: 1 | DX25: =$DW25*DJ25*(1+$DX$3)*(1+$DX$4) -> 259.52686 | DY25: =$DW25*DK25*(1+$DX$3)*(1+$DX$4) -> 259.52686 | DZ25: =$DW25*DL25*(1+$DX$3)*(1+$DX$4) -> 259.52686 | EA25: =$DW25*DM25*(1+$DX$3)*(1+$DX$4) -> 259.52686 | EB25: =$DW25*DN25*(1+$DX$3)*(1+$DX$4) -> 259.52686 | EC25: =$DW25*DO25*(1+$DX$3)*(1+$DX$4) -> 259.52686 | ED25: =$DW25*DP25*(1+$DX$3)*(1+$DX$4) -> 259.52686 | EE25: =$DW25*DQ25*(1+$DX$3)*(1+$DX$4) -> 259.52686 | ... EI25: =$DW25*DU25*(1+$DX$3)*(1+$DX$4) -> 259.52686 | EJ25: =SUM(DX25:EI25) -> 3114.3224
A26: 1.2. Personal directo (mano de obra) | B26: =SUM(B27:B29) -> 25400 | C26: =SUM(C27:C29) -> 25400 | D26: =SUM(D27:D29) -> 25400 | E26: =SUM(E27:E29) -> 25400 | F26: =SUM(F27:F29) -> 25400 | G26: =SUM(G27:G29) -> 25400 | H26: =SUM(H27:H29) -> 25400 | I26: =SUM(I27:I29) -> 25400 | ... M26: =SUM(M27:M29) -> 25400 | N26: =SUM(B26:M26) -> 304800 | P26: =SUM(P27:P29) -> 27178 | Q26: =SUM(Q27:Q29) -> 27178 | R26: =SUM(R27:R29) -> 27178 | S26: =SUM(S27:S29) -> 27178 | T26: =SUM(T27:T29) -> 27178 | U26: =SUM(U27:U29) -> 27178 | V26: =SUM(V27:V29) -> 27178 | W26: =SUM(W27:W29) -> 27178 | ... AA26: =SUM(AA27:AA29) -> 27178 | AB26: =SUM(P26:AA26) -> 326136 | AD26: =SUM(AD27:AD29) -> 28808.68 | AE26: =SUM(AE27:AE29) -> 28808.68 | AF26: =SUM(AF27:AF29) -> 28808.68 | AG26: =SUM(AG27:AG29) -> 28808.68 | AH26: =SUM(AH27:AH29) -> 28808.68 | AI26: =SUM(AI27:AI29) -> 28808.68 | AJ26: =SUM(AJ27:AJ29) -> 28808.68 | AK26: =SUM(AK27:AK29) -> 28808.68 | ... AO26: =SUM(AO27:AO29) -> 28808.68 | AP26: =SUM(AD26:AO26) -> 345704.16 | AR26: =SUM(AR27:AR29) -> 30537.201 | AS26: =SUM(AS27:AS29) -> 30537.201 | AT26: =SUM(AT27:AT29) -> 30537.201 | AU26: =SUM(AU27:AU29) -> 30537.201 | AV26: =SUM(AV27:AV29) -> 30537.201 | AW26: =SUM(AW27:AW29) -> 30537.201 | AX26: =SUM(AX27:AX29) -> 30537.201 | AY26: =SUM(AY27:AY29) -> 30537.201 | ... BC26: =SUM(BC27:BC29) -> 30537.201 | BD26: =SUM(AR26:BC26) -> 366446.41 | BF26: =SUM(BF27:BF29) -> 32369.433 | BG26: =SUM(BG27:BG29) -> 32369.433 | BH26: =SUM(BH27:BH29) -> 32369.433 | BI26: =SUM(BI27:BI29) -> 32369.433 | BJ26: =SUM(BJ27:BJ29) -> 32369.433 | BK26: =SUM(BK27:BK29) -> 32369.433 | BL26: =SUM(BL27:BL29) -> 32369.433 | BM26: =SUM(BM27:BM29) -> 32369.433 | ... BQ26: =SUM(BQ27:BQ29) -> 32369.433 | BR26: =SUM(BF26:BQ26) -> 388433.19 | BT26: =SUM(BT27:BT29) -> 34311.599 | BU26: =SUM(BU27:BU29) -> 34311.599 | BV26: =SUM(BV27:BV29) -> 34311.599 | BW26: =SUM(BW27:BW29) -> 34311.599 | BX26: =SUM(BX27:BX29) -> 34311.599 | BY26: =SUM(BY27:BY29) -> 34311.599 | BZ26: =SUM(BZ27:BZ29) -> 34311.599 | CA26: =SUM(CA27:CA29) -> 34311.599 | ... CE26: =SUM(CE27:CE29) -> 34311.599 | CF26: =SUM(BT26:CE26) -> 411739.19 | CH26: =SUM(CH27:CH29) -> 36370.295 | CI26: =SUM(CI27:CI29) -> 36370.295 | CJ26: =SUM(CJ27:CJ29) -> 36370.295 | CK26: =SUM(CK27:CK29) -> 36370.295 | CL26: =SUM(CL27:CL29) -> 36370.295 | CM26: =SUM(CM27:CM29) -> 36370.295 | CN26: =SUM(CN27:CN29) -> 36370.295 | CO26: =SUM(CO27:CO29) -> 36370.295 | ... CS26: =SUM(CS27:CS29) -> 36370.295 | CT26: =SUM(CH26:CS26) -> 436443.54 | CV26: =SUM(CV27:CV29) -> 38552.512 | CW26: =SUM(CW27:CW29) -> 38552.512 | CX26: =SUM(CX27:CX29) -> 38552.512 | CY26: =SUM(CY27:CY29) -> 38552.512 | CZ26: =SUM(CZ27:CZ29) -> 38552.512 | DA26: =SUM(DA27:DA29) -> 38552.512 | DB26: =SUM(DB27:DB29) -> 38552.512 | DC26: =SUM(DC27:DC29) -> 38552.512 | ... DG26: =SUM(DG27:DG29) -> 38552.512 | DH26: =SUM(CV26:DG26) -> 462630.15 | DJ26: =SUM(DJ27:DJ29) -> 40865.663 | DK26: =SUM(DK27:DK29) -> 40865.663 | DL26: =SUM(DL27:DL29) -> 40865.663 | DM26: =SUM(DM27:DM29) -> 40865.663 | DN26: =SUM(DN27:DN29) -> 40865.663 | DO26: =SUM(DO27:DO29) -> 40865.663 | DP26: =SUM(DP27:DP29) -> 40865.663 | DQ26: =SUM(DQ27:DQ29) -> 40865.663 | ... DU26: =SUM(DU27:DU29) -> 40865.663 | DV26: =SUM(DJ26:DU26) -> 490387.96 | DX26: =SUM(DX27:DX29) -> 43317.603 | DY26: =SUM(DY27:DY29) -> 43317.603 | DZ26: =SUM(DZ27:DZ29) -> 43317.603 | EA26: =SUM(EA27:EA29) -> 43317.603 | EB26: =SUM(EB27:EB29) -> 43317.603 | EC26: =SUM(EC27:EC29) -> 43317.603 | ED26: =SUM(ED27:ED29) -> 43317.603 | EE26: =SUM(EE27:EE29) -> 43317.603 | ... EI26: =SUM(EI27:EI29) -> 43317.603 | EJ26: =SUM(DX26:EI26) -> 519811.24
A27: Carpintero | B27: 8000 | C27: =B27*(1+C$3) -> 8000 | D27: =C27*(1+D$3) -> 8000 | E27: =D27*(1+E$3) -> 8000 | F27: =E27*(1+F$3) -> 8000 | G27: =F27*(1+G$3) -> 8000 | H27: =G27*(1+H$3) -> 8000 | I27: =H27*(1+I$3) -> 8000 | J27: =I27*(1+J$3) -> 8000 | ... M27: =L27*(1+M$3) -> 8000 | N27: =SUM(B27:M27) -> 96000 | O27: 1 | P27: =$O27*B27*(1+$P$4) -> 8560 | Q27: =$O27*C27*(1+$P$4) -> 8560 | R27: =$O27*D27*(1+$P$4) -> 8560 | S27: =$O27*E27*(1+$P$4) -> 8560 | T27: =$O27*F27*(1+$P$4) -> 8560 | U27: =$O27*G27*(1+$P$4) -> 8560 | V27: =$O27*H27*(1+$P$4) -> 8560 | W27: =$O27*I27*(1+$P$4) -> 8560 | ... AA27: =$O27*M27*(1+$P$4) -> 8560 | AB27: =SUM(P27:AA27) -> 102720 | AC27: 1 | AD27: =$AC27*P27*(1+$AD$4) -> 9073.6 | AE27: =$AC27*Q27*(1+$AD$4) -> 9073.6 | AF27: =$AC27*R27*(1+$AD$4) -> 9073.6 | AG27: =$AC27*S27*(1+$AD$4) -> 9073.6 | AH27: =$AC27*T27*(1+$AD$4) -> 9073.6 | AI27: =$AC27*U27*(1+$AD$4) -> 9073.6 | AJ27: =$AC27*V27*(1+$AD$4) -> 9073.6 | AK27: =$AC27*W27*(1+$AD$4) -> 9073.6 | ... AO27: =$AC27*AA27*(1+$AD$4) -> 9073.6 | AP27: =SUM(AD27:AO27) -> 108883.2 | AQ27: 1 | AR27: =$AQ27*AD27*(1+$AR$4) -> 9618.016 | AS27: =$AQ27*AE27*(1+$AR$4) -> 9618.016 | AT27: =$AQ27*AF27*(1+$AR$4) -> 9618.016 | AU27: =$AQ27*AG27*(1+$AR$4) -> 9618.016 | AV27: =$AQ27*AH27*(1+$AR$4) -> 9618.016 | AW27: =$AQ27*AI27*(1+$AR$4) -> 9618.016 | AX27: =$AQ27*AJ27*(1+$AR$4) -> 9618.016 | AY27: =$AQ27*AK27*(1+$AR$4) -> 9618.016 | ... BC27: =$AQ27*AO27*(1+$AR$4) -> 9618.016 | BD27: =SUM(AR27:BC27) -> 115416.19 | BE27: 1 | BF27: =$BE27*AR27*(1+$BF$4) -> 10195.097 | BG27: =$BE27*AS27*(1+$BF$4) -> 10195.097 | BH27: =$BE27*AT27*(1+$BF$4) -> 10195.097 | BI27: =$BE27*AU27*(1+$BF$4) -> 10195.097 | BJ27: =$BE27*AV27*(1+$BF$4) -> 10195.097 | BK27: =$BE27*AW27*(1+$BF$4) -> 10195.097 | BL27: =$BE27*AX27*(1+$BF$4) -> 10195.097 | BM27: =$BE27*AY27*(1+$BF$4) -> 10195.097 | ... BQ27: =$BE27*BC27*(1+$BF$4) -> 10195.097 | BR27: =SUM(BF27:BQ27) -> 122341.16 | BS27: 1 | BT27: =$BS27*BF27*(1+$BT$4) -> 10806.803 | BU27: =$BS27*BG27*(1+$BT$4) -> 10806.803 | BV27: =$BS27*BH27*(1+$BT$4) -> 10806.803 | BW27: =$BS27*BI27*(1+$BT$4) -> 10806.803 | BX27: =$BS27*BJ27*(1+$BT$4) -> 10806.803 | BY27: =$BS27*BK27*(1+$BT$4) -> 10806.803 | BZ27: =$BS27*BL27*(1+$BT$4) -> 10806.803 | CA27: =$BS27*BM27*(1+$BT$4) -> 10806.803 | ... CE27: =$BS27*BQ27*(1+$BT$4) -> 10806.803 | CF27: =SUM(BT27:CE27) -> 129681.63 | CG27: 1 | CH27: =$CG27*BT27*(1+$CH$4) -> 11455.211 | CI27: =$CG27*BU27*(1+$CH$4) -> 11455.211 | CJ27: =$CG27*BV27*(1+$CH$4) -> 11455.211 | CK27: =$CG27*BW27*(1+$CH$4) -> 11455.211 | CL27: =$CG27*BX27*(1+$CH$4) -> 11455.211 | CM27: =$CG27*BY27*(1+$CH$4) -> 11455.211 | CN27: =$CG27*BZ27*(1+$CH$4) -> 11455.211 | CO27: =$CG27*CA27*(1+$CH$4) -> 11455.211 | ... CS27: =$CG27*CE27*(1+$CH$4) -> 11455.211 | CT27: =SUM(CH27:CS27) -> 137462.53 | CU27: 1 | CV27: =$CU27*CH27*(1+$CV$4) -> 12142.524 | CW27: =$CU27*CI27*(1+$CV$4) -> 12142.524 | CX27: =$CU27*CJ27*(1+$CV$4) -> 12142.524 | CY27: =$CU27*CK27*(1+$CV$4) -> 12142.524 | CZ27: =$CU27*CL27*(1+$CV$4) -> 12142.524 | DA27: =$CU27*CM27*(1+$CV$4) -> 12142.524 | DB27: =$CU27*CN27*(1+$CV$4) -> 12142.524 | DC27: =$CU27*CO27*(1+$CV$4) -> 12142.524 | ... DG27: =$CU27*CS27*(1+$CV$4) -> 12142.524 | DH27: =SUM(CV27:DG27) -> 145710.28 | DI27: 1 | DJ27: =$DI27*CV27*(1+$DJ$4) -> 12871.075 | DK27: =$DI27*CW27*(1+$DJ$4) -> 12871.075 | DL27: =$DI27*CX27*(1+$DJ$4) -> 12871.075 | DM27: =$DI27*CY27*(1+$DJ$4) -> 12871.075 | DN27: =$DI27*CZ27*(1+$DJ$4) -> 12871.075 | DO27: =$DI27*DA27*(1+$DJ$4) -> 12871.075 | DP27: =$DI27*DB27*(1+$DJ$4) -> 12871.075 | DQ27: =$DI27*DC27*(1+$DJ$4) -> 12871.075 | ... DU27: =$DI27*DG27*(1+$DJ$4) -> 12871.075 | DV27: =SUM(DJ27:DU27) -> 154452.9 | DW27: 1 | DX27: =$DW27*DJ27*(1+$DX$4) -> 13643.34 | DY27: =$DW27*DK27*(1+$DX$4) -> 13643.34 | DZ27: =$DW27*DL27*(1+$DX$4) -> 13643.34 | EA27: =$DW27*DM27*(1+$DX$4) -> 13643.34 | EB27: =$DW27*DN27*(1+$DX$4) -> 13643.34 | EC27: =$DW27*DO27*(1+$DX$4) -> 13643.34 | ED27: =$DW27*DP27*(1+$DX$4) -> 13643.34 | EE27: =$DW27*DQ27*(1+$DX$4) -> 13643.34 | ... EI27: =$DW27*DU27*(1+$DX$4) -> 13643.34 | EJ27: =SUM(DX27:EI27) -> 163720.07
A28: Técnico en acabados | B28: 8400 | C28: =B28*(1+C$3) -> 8400 | D28: =C28*(1+D$3) -> 8400 | E28: =D28*(1+E$3) -> 8400 | F28: =E28*(1+F$3) -> 8400 | G28: =F28*(1+G$3) -> 8400 | H28: =G28*(1+H$3) -> 8400 | I28: =H28*(1+I$3) -> 8400 | J28: =I28*(1+J$3) -> 8400 | ... M28: =L28*(1+M$3) -> 8400 | N28: =SUM(B28:M28) -> 100800 | O28: 1 | P28: =$O28*B28*(1+$P$4) -> 8988 | Q28: =$O28*C28*(1+$P$4) -> 8988 | R28: =$O28*D28*(1+$P$4) -> 8988 | S28: =$O28*E28*(1+$P$4) -> 8988 | T28: =$O28*F28*(1+$P$4) -> 8988 | U28: =$O28*G28*(1+$P$4) -> 8988 | V28: =$O28*H28*(1+$P$4) -> 8988 | W28: =$O28*I28*(1+$P$4) -> 8988 | ... AA28: =$O28*M28*(1+$P$4) -> 8988 | AB28: =SUM(P28:AA28) -> 107856 | AC28: 1 | AD28: =$AC28*P28*(1+$AD$4) -> 9527.28 | AE28: =$AC28*Q28*(1+$AD$4) -> 9527.28 | AF28: =$AC28*R28*(1+$AD$4) -> 9527.28 | AG28: =$AC28*S28*(1+$AD$4) -> 9527.28 | AH28: =$AC28*T28*(1+$AD$4) -> 9527.28 | AI28: =$AC28*U28*(1+$AD$4) -> 9527.28 | AJ28: =$AC28*V28*(1+$AD$4) -> 9527.28 | AK28: =$AC28*W28*(1+$AD$4) -> 9527.28 | ... AO28: =$AC28*AA28*(1+$AD$4) -> 9527.28 | AP28: =SUM(AD28:AO28) -> 114327.36 | AQ28: 1 | AR28: =$AQ28*AD28*(1+$AR$4) -> 10098.917 | AS28: =$AQ28*AE28*(1+$AR$4) -> 10098.917 | AT28: =$AQ28*AF28*(1+$AR$4) -> 10098.917 | AU28: =$AQ28*AG28*(1+$AR$4) -> 10098.917 | AV28: =$AQ28*AH28*(1+$AR$4) -> 10098.917 | AW28: =$AQ28*AI28*(1+$AR$4) -> 10098.917 | AX28: =$AQ28*AJ28*(1+$AR$4) -> 10098.917 | AY28: =$AQ28*AK28*(1+$AR$4) -> 10098.917 | ... BC28: =$AQ28*AO28*(1+$AR$4) -> 10098.917 | BD28: =SUM(AR28:BC28) -> 121187 | BE28: 1 | BF28: =$BE28*AR28*(1+$BF$4) -> 10704.852 | BG28: =$BE28*AS28*(1+$BF$4) -> 10704.852 | BH28: =$BE28*AT28*(1+$BF$4) -> 10704.852 | BI28: =$BE28*AU28*(1+$BF$4) -> 10704.852 | BJ28: =$BE28*AV28*(1+$BF$4) -> 10704.852 | BK28: =$BE28*AW28*(1+$BF$4) -> 10704.852 | BL28: =$BE28*AX28*(1+$BF$4) -> 10704.852 | BM28: =$BE28*AY28*(1+$BF$4) -> 10704.852 | ... BQ28: =$BE28*BC28*(1+$BF$4) -> 10704.852 | BR28: =SUM(BF28:BQ28) -> 128458.22 | BS28: 1 | BT28: =$BS28*BF28*(1+$BT$4) -> 11347.143 | BU28: =$BS28*BG28*(1+$BT$4) -> 11347.143 | BV28: =$BS28*BH28*(1+$BT$4) -> 11347.143 | BW28: =$BS28*BI28*(1+$BT$4) -> 11347.143 | BX28: =$BS28*BJ28*(1+$BT$4) -> 11347.143 | BY28: =$BS28*BK28*(1+$BT$4) -> 11347.143 | BZ28: =$BS28*BL28*(1+$BT$4) -> 11347.143 | CA28: =$BS28*BM28*(1+$BT$4) -> 11347.143 | ... CE28: =$BS28*BQ28*(1+$BT$4) -> 11347.143 | CF28: =SUM(BT28:CE28) -> 136165.71 | CG28: 1 | CH28: =$CG28*BT28*(1+$CH$4) -> 12027.971 | CI28: =$CG28*BU28*(1+$CH$4) -> 12027.971 | CJ28: =$CG28*BV28*(1+$CH$4) -> 12027.971 | CK28: =$CG28*BW28*(1+$CH$4) -> 12027.971 | CL28: =$CG28*BX28*(1+$CH$4) -> 12027.971 | CM28: =$CG28*BY28*(1+$CH$4) -> 12027.971 | CN28: =$CG28*BZ28*(1+$CH$4) -> 12027.971 | CO28: =$CG28*CA28*(1+$CH$4) -> 12027.971 | ... CS28: =$CG28*CE28*(1+$CH$4) -> 12027.971 | CT28: =SUM(CH28:CS28) -> 144335.66 | CU28: 1 | CV28: =$CU28*CH28*(1+$CV$4) -> 12749.65 | CW28: =$CU28*CI28*(1+$CV$4) -> 12749.65 | CX28: =$CU28*CJ28*(1+$CV$4) -> 12749.65 | CY28: =$CU28*CK28*(1+$CV$4) -> 12749.65 | CZ28: =$CU28*CL28*(1+$CV$4) -> 12749.65 | DA28: =$CU28*CM28*(1+$CV$4) -> 12749.65 | DB28: =$CU28*CN28*(1+$CV$4) -> 12749.65 | DC28: =$CU28*CO28*(1+$CV$4) -> 12749.65 | ... DG28: =$CU28*CS28*(1+$CV$4) -> 12749.65 | DH28: =SUM(CV28:DG28) -> 152995.8 | DI28: 1 | DJ28: =$DI28*CV28*(1+$DJ$4) -> 13514.629 | DK28: =$DI28*CW28*(1+$DJ$4) -> 13514.629 | DL28: =$DI28*CX28*(1+$DJ$4) -> 13514.629 | DM28: =$DI28*CY28*(1+$DJ$4) -> 13514.629 | DN28: =$DI28*CZ28*(1+$DJ$4) -> 13514.629 | DO28: =$DI28*DA28*(1+$DJ$4) -> 13514.629 | DP28: =$DI28*DB28*(1+$DJ$4) -> 13514.629 | DQ28: =$DI28*DC28*(1+$DJ$4) -> 13514.629 | ... DU28: =$DI28*DG28*(1+$DJ$4) -> 13514.629 | DV28: =SUM(DJ28:DU28) -> 162175.55 | DW28: 1 | DX28: =$DW28*DJ28*(1+$DX$4) -> 14325.506 | DY28: =$DW28*DK28*(1+$DX$4) -> 14325.506 | DZ28: =$DW28*DL28*(1+$DX$4) -> 14325.506 | EA28: =$DW28*DM28*(1+$DX$4) -> 14325.506 | EB28: =$DW28*DN28*(1+$DX$4) -> 14325.506 | EC28: =$DW28*DO28*(1+$DX$4) -> 14325.506 | ED28: =$DW28*DP28*(1+$DX$4) -> 14325.506 | EE28: =$DW28*DQ28*(1+$DX$4) -> 14325.506 | ... EI28: =$DW28*DU28*(1+$DX$4) -> 14325.506 | EJ28: =SUM(DX28:EI28) -> 171906.08
A29: Operador de maquinaria | B29: 9000 | C29: =B29*(1+C$3) -> 9000 | D29: =C29*(1+D$3) -> 9000 | E29: =D29*(1+E$3) -> 9000 | F29: =E29*(1+F$3) -> 9000 | G29: =F29*(1+G$3) -> 9000 | H29: =G29*(1+H$3) -> 9000 | I29: =H29*(1+I$3) -> 9000 | J29: =I29*(1+J$3) -> 9000 | ... M29: =L29*(1+M$3) -> 9000 | N29: =SUM(B29:M29) -> 108000 | O29: 1 | P29: =$O29*B29*(1+$P$4) -> 9630 | Q29: =$O29*C29*(1+$P$4) -> 9630 | R29: =$O29*D29*(1+$P$4) -> 9630 | S29: =$O29*E29*(1+$P$4) -> 9630 | T29: =$O29*F29*(1+$P$4) -> 9630 | U29: =$O29*G29*(1+$P$4) -> 9630 | V29: =$O29*H29*(1+$P$4) -> 9630 | W29: =$O29*I29*(1+$P$4) -> 9630 | ... AA29: =$O29*M29*(1+$P$4) -> 9630 | AB29: =SUM(P29:AA29) -> 115560 | AC29: 1 | AD29: =$AC29*P29*(1+$AD$4) -> 10207.8 | AE29: =$AC29*Q29*(1+$AD$4) -> 10207.8 | AF29: =$AC29*R29*(1+$AD$4) -> 10207.8 | AG29: =$AC29*S29*(1+$AD$4) -> 10207.8 | AH29: =$AC29*T29*(1+$AD$4) -> 10207.8 | AI29: =$AC29*U29*(1+$AD$4) -> 10207.8 | AJ29: =$AC29*V29*(1+$AD$4) -> 10207.8 | AK29: =$AC29*W29*(1+$AD$4) -> 10207.8 | ... AO29: =$AC29*AA29*(1+$AD$4) -> 10207.8 | AP29: =SUM(AD29:AO29) -> 122493.6 | AQ29: 1 | AR29: =$AQ29*AD29*(1+$AR$4) -> 10820.268 | AS29: =$AQ29*AE29*(1+$AR$4) -> 10820.268 | AT29: =$AQ29*AF29*(1+$AR$4) -> 10820.268 | AU29: =$AQ29*AG29*(1+$AR$4) -> 10820.268 | AV29: =$AQ29*AH29*(1+$AR$4) -> 10820.268 | AW29: =$AQ29*AI29*(1+$AR$4) -> 10820.268 | AX29: =$AQ29*AJ29*(1+$AR$4) -> 10820.268 | AY29: =$AQ29*AK29*(1+$AR$4) -> 10820.268 | ... BC29: =$AQ29*AO29*(1+$AR$4) -> 10820.268 | BD29: =SUM(AR29:BC29) -> 129843.22 | BE29: 1 | BF29: =$BE29*AR29*(1+$BF$4) -> 11469.484 | BG29: =$BE29*AS29*(1+$BF$4) -> 11469.484 | BH29: =$BE29*AT29*(1+$BF$4) -> 11469.484 | BI29: =$BE29*AU29*(1+$BF$4) -> 11469.484 | BJ29: =$BE29*AV29*(1+$BF$4) -> 11469.484 | BK29: =$BE29*AW29*(1+$BF$4) -> 11469.484 | BL29: =$BE29*AX29*(1+$BF$4) -> 11469.484 | BM29: =$BE29*AY29*(1+$BF$4) -> 11469.484 | ... BQ29: =$BE29*BC29*(1+$BF$4) -> 11469.484 | BR29: =SUM(BF29:BQ29) -> 137633.81 | BS29: 1 | BT29: =$BS29*BF29*(1+$BT$4) -> 12157.653 | BU29: =$BS29*BG29*(1+$BT$4) -> 12157.653 | BV29: =$BS29*BH29*(1+$BT$4) -> 12157.653 | BW29: =$BS29*BI29*(1+$BT$4) -> 12157.653 | BX29: =$BS29*BJ29*(1+$BT$4) -> 12157.653 | BY29: =$BS29*BK29*(1+$BT$4) -> 12157.653 | BZ29: =$BS29*BL29*(1+$BT$4) -> 12157.653 | CA29: =$BS29*BM29*(1+$BT$4) -> 12157.653 | ... CE29: =$BS29*BQ29*(1+$BT$4) -> 12157.653 | CF29: =SUM(BT29:CE29) -> 145891.84 | CG29: 1 | CH29: =$CG29*BT29*(1+$CH$4) -> 12887.112 | CI29: =$CG29*BU29*(1+$CH$4) -> 12887.112 | CJ29: =$CG29*BV29*(1+$CH$4) -> 12887.112 | CK29: =$CG29*BW29*(1+$CH$4) -> 12887.112 | CL29: =$CG29*BX29*(1+$CH$4) -> 12887.112 | CM29: =$CG29*BY29*(1+$CH$4) -> 12887.112 | CN29: =$CG29*BZ29*(1+$CH$4) -> 12887.112 | CO29: =$CG29*CA29*(1+$CH$4) -> 12887.112 | ... CS29: =$CG29*CE29*(1+$CH$4) -> 12887.112 | CT29: =SUM(CH29:CS29) -> 154645.35 | CU29: 1 | CV29: =$CU29*CH29*(1+$CV$4) -> 13660.339 | CW29: =$CU29*CI29*(1+$CV$4) -> 13660.339 | CX29: =$CU29*CJ29*(1+$CV$4) -> 13660.339 | CY29: =$CU29*CK29*(1+$CV$4) -> 13660.339 | CZ29: =$CU29*CL29*(1+$CV$4) -> 13660.339 | DA29: =$CU29*CM29*(1+$CV$4) -> 13660.339 | DB29: =$CU29*CN29*(1+$CV$4) -> 13660.339 | DC29: =$CU29*CO29*(1+$CV$4) -> 13660.339 | ... DG29: =$CU29*CS29*(1+$CV$4) -> 13660.339 | DH29: =SUM(CV29:DG29) -> 163924.07 | DI29: 1 | DJ29: =$DI29*CV29*(1+$DJ$4) -> 14479.959 | DK29: =$DI29*CW29*(1+$DJ$4) -> 14479.959 | DL29: =$DI29*CX29*(1+$DJ$4) -> 14479.959 | DM29: =$DI29*CY29*(1+$DJ$4) -> 14479.959 | DN29: =$DI29*CZ29*(1+$DJ$4) -> 14479.959 | DO29: =$DI29*DA29*(1+$DJ$4) -> 14479.959 | DP29: =$DI29*DB29*(1+$DJ$4) -> 14479.959 | DQ29: =$DI29*DC29*(1+$DJ$4) -> 14479.959 | ... DU29: =$DI29*DG29*(1+$DJ$4) -> 14479.959 | DV29: =SUM(DJ29:DU29) -> 173759.51 | DW29: 1 | DX29: =$DW29*DJ29*(1+$DX$4) -> 15348.757 | DY29: =$DW29*DK29*(1+$DX$4) -> 15348.757 | DZ29: =$DW29*DL29*(1+$DX$4) -> 15348.757 | EA29: =$DW29*DM29*(1+$DX$4) -> 15348.757 | EB29: =$DW29*DN29*(1+$DX$4) -> 15348.757 | EC29: =$DW29*DO29*(1+$DX$4) -> 15348.757 | ED29: =$DW29*DP29*(1+$DX$4) -> 15348.757 | EE29: =$DW29*DQ29*(1+$DX$4) -> 15348.757 | ... EI29: =$DW29*DU29*(1+$DX$4) -> 15348.757 | EJ29: =SUM(DX29:EI29) -> 184185.08
A30: 1.3. Material indirecto | B30: =SUM(B31:B34) -> 35160 | C30: =SUM(C31:C34) -> 35160 | D30: =SUM(D31:D34) -> 35160 | E30: =SUM(E31:E34) -> 35160 | F30: =SUM(F31:F34) -> 35160 | G30: =SUM(G31:G34) -> 35160 | H30: =SUM(H31:H34) -> 35160 | I30: =SUM(I31:I34) -> 35160 | ... M30: =SUM(M31:M34) -> 35160 | N30: =SUM(B30:M30) -> 421920 | P30: =SUM(P31:P34) -> 38460.936 | Q30: =SUM(Q31:Q34) -> 38460.936 | R30: =SUM(R31:R34) -> 38460.936 | S30: =SUM(S31:S34) -> 38460.936 | T30: =SUM(T31:T34) -> 38460.936 | U30: =SUM(U31:U34) -> 38460.936 | V30: =SUM(V31:V34) -> 38460.936 | W30: =SUM(W31:W34) -> 38460.936 | ... AA30: =SUM(AA31:AA34) -> 38460.936 | AB30: =SUM(P30:AA30) -> 461531.23 | AD30: =SUM(AD31:AD34) -> 42296.632 | AE30: =SUM(AE31:AE34) -> 42296.632 | AF30: =SUM(AF31:AF34) -> 42296.632 | AG30: =SUM(AG31:AG34) -> 42296.632 | AH30: =SUM(AH31:AH34) -> 42296.632 | AI30: =SUM(AI31:AI34) -> 42296.632 | AJ30: =SUM(AJ31:AJ34) -> 42296.632 | AK30: =SUM(AK31:AK34) -> 42296.632 | ... AO30: =SUM(AO31:AO34) -> 42296.632 | AP30: =SUM(AD30:AO30) -> 507559.58 | AR30: =SUM(AR31:AR34) -> 46535.138 | AS30: =SUM(AS31:AS34) -> 46535.138 | AT30: =SUM(AT31:AT34) -> 46535.138 | AU30: =SUM(AU31:AU34) -> 46535.138 | AV30: =SUM(AV31:AV34) -> 46535.138 | AW30: =SUM(AW31:AW34) -> 46535.138 | AX30: =SUM(AX31:AX34) -> 46535.138 | AY30: =SUM(AY31:AY34) -> 46535.138 | ... BC30: =SUM(BC31:BC34) -> 46535.138 | BD30: =SUM(AR30:BC30) -> 558421.65 | BF30: =SUM(BF31:BF34) -> 51220.134 | BG30: =SUM(BG31:BG34) -> 51220.134 | BH30: =SUM(BH31:BH34) -> 51220.134 | BI30: =SUM(BI31:BI34) -> 51220.134 | BJ30: =SUM(BJ31:BJ34) -> 51220.134 | BK30: =SUM(BK31:BK34) -> 51220.134 | BL30: =SUM(BL31:BL34) -> 51220.134 | BM30: =SUM(BM31:BM34) -> 51220.134 | ... BQ30: =SUM(BQ31:BQ34) -> 51220.134 | BR30: =SUM(BF30:BQ30) -> 614641.61 | BT30: =SUM(BT31:BT34) -> 56400.127 | BU30: =SUM(BU31:BU34) -> 56400.127 | BV30: =SUM(BV31:BV34) -> 56400.127 | BW30: =SUM(BW31:BW34) -> 56400.127 | BX30: =SUM(BX31:BX34) -> 56400.127 | BY30: =SUM(BY31:BY34) -> 56400.127 | BZ30: =SUM(BZ31:BZ34) -> 56400.127 | CA30: =SUM(CA31:CA34) -> 56400.127 | ... CE30: =SUM(CE31:CE34) -> 56400.127 | CF30: =SUM(BT30:CE30) -> 676801.52 | CH30: =SUM(CH31:CH34) -> 62128.985 | CI30: =SUM(CI31:CI34) -> 62128.985 | CJ30: =SUM(CJ31:CJ34) -> 62128.985 | CK30: =SUM(CK31:CK34) -> 62128.985 | CL30: =SUM(CL31:CL34) -> 62128.985 | CM30: =SUM(CM31:CM34) -> 62128.985 | CN30: =SUM(CN31:CN34) -> 62128.985 | CO30: =SUM(CO31:CO34) -> 62128.985 | ... CS30: =SUM(CS31:CS34) -> 62128.985 | CT30: =SUM(CH30:CS30) -> 745547.82 | CV30: =SUM(CV31:CV34) -> 68466.544 | CW30: =SUM(CW31:CW34) -> 68466.544 | CX30: =SUM(CX31:CX34) -> 68466.544 | CY30: =SUM(CY31:CY34) -> 68466.544 | CZ30: =SUM(CZ31:CZ34) -> 68466.544 | DA30: =SUM(DA31:DA34) -> 68466.544 | DB30: =SUM(DB31:DB34) -> 68466.544 | DC30: =SUM(DC31:DC34) -> 68466.544 | ... DG30: =SUM(DG31:DG34) -> 68466.544 | DH30: =SUM(CV30:DG30) -> 821598.52 | DJ30: =SUM(DJ31:DJ34) -> 75479.265 | DK30: =SUM(DK31:DK34) -> 75479.265 | DL30: =SUM(DL31:DL34) -> 75479.265 | DM30: =SUM(DM31:DM34) -> 75479.265 | DN30: =SUM(DN31:DN34) -> 75479.265 | DO30: =SUM(DO31:DO34) -> 75479.265 | DP30: =SUM(DP31:DP34) -> 75479.265 | DQ30: =SUM(DQ31:DQ34) -> 75479.265 | ... DU30: =SUM(DU31:DU34) -> 75479.265 | DV30: =SUM(DJ30:DU30) -> 905751.18 | DX30: =SUM(DX31:DX34) -> 83240.984 | DY30: =SUM(DY31:DY34) -> 83240.984 | DZ30: =SUM(DZ31:DZ34) -> 83240.984 | EA30: =SUM(EA31:EA34) -> 83240.984 | EB30: =SUM(EB31:EB34) -> 83240.984 | EC30: =SUM(EC31:EC34) -> 83240.984 | ED30: =SUM(ED31:ED34) -> 83240.984 | EE30: =SUM(EE31:EE34) -> 83240.984 | ... EI30: =SUM(EI31:EI34) -> 83240.984 | EJ30: =SUM(DX30:EI30) -> 998891.81
A31: Rollo de latex | B31: 400 | C31: =B31*(1+C$3) -> 400 | D31: =C31*(1+D$3) -> 400 | E31: =D31*(1+E$3) -> 400 | F31: =E31*(1+F$3) -> 400 | G31: =F31*(1+G$3) -> 400 | H31: =G31*(1+H$3) -> 400 | I31: =H31*(1+I$3) -> 400 | J31: =I31*(1+J$3) -> 400 | ... M31: =L31*(1+M$3) -> 400 | N31: =SUM(B31:M31) -> 4800 | O31: 1 | P31: =$O31*B31*(1+$P$3)*(1+$P$4) -> 440.84 | Q31: =$O31*C31*(1+$P$3)*(1+$P$4) -> 440.84 | R31: =$O31*D31*(1+$P$3)*(1+$P$4) -> 440.84 | S31: =$O31*E31*(1+$P$3)*(1+$P$4) -> 440.84 | T31: =$O31*F31*(1+$P$3)*(1+$P$4) -> 440.84 | U31: =$O31*G31*(1+$P$3)*(1+$P$4) -> 440.84 | V31: =$O31*H31*(1+$P$3)*(1+$P$4) -> 440.84 | W31: =$O31*I31*(1+$P$3)*(1+$P$4) -> 440.84 | ... AA31: =$O31*M31*(1+$P$3)*(1+$P$4) -> 440.84 | AB31: =SUM(P31:AA31) -> 5290.08 | AC31: 1 | AD31: =$AC31*P31*(1+$AD$3)*(1+$AD$4) -> 490.65492 | AE31: =$AC31*Q31*(1+$AD$3)*(1+$AD$4) -> 490.65492 | AF31: =$AC31*R31*(1+$AD$3)*(1+$AD$4) -> 490.65492 | AG31: =$AC31*S31*(1+$AD$3)*(1+$AD$4) -> 490.65492 | AH31: =$AC31*T31*(1+$AD$3)*(1+$AD$4) -> 490.65492 | AI31: =$AC31*U31*(1+$AD$3)*(1+$AD$4) -> 490.65492 | AJ31: =$AC31*V31*(1+$AD$3)*(1+$AD$4) -> 490.65492 | AK31: =$AC31*W31*(1+$AD$3)*(1+$AD$4) -> 490.65492 | ... AO31: =$AC31*AA31*(1+$AD$3)*(1+$AD$4) -> 490.65492 | AP31: =SUM(AD31:AO31) -> 5887.859 | AQ31: 1 | AR31: =$AQ31*AD31*(1+$AR$3)*(1+$AR$4) -> 546.09893 | AS31: =$AQ31*AE31*(1+$AR$3)*(1+$AR$4) -> 546.09893 | AT31: =$AQ31*AF31*(1+$AR$3)*(1+$AR$4) -> 546.09893 | AU31: =$AQ31*AG31*(1+$AR$3)*(1+$AR$4) -> 546.09893 | AV31: =$AQ31*AH31*(1+$AR$3)*(1+$AR$4) -> 546.09893 | AW31: =$AQ31*AI31*(1+$AR$3)*(1+$AR$4) -> 546.09893 | AX31: =$AQ31*AJ31*(1+$AR$3)*(1+$AR$4) -> 546.09893 | AY31: =$AQ31*AK31*(1+$AR$3)*(1+$AR$4) -> 546.09893 | ... BC31: =$AQ31*AO31*(1+$AR$3)*(1+$AR$4) -> 546.09893 | BD31: =SUM(AR31:BC31) -> 6553.1871 | BE31: 1 | BF31: =$BE31*AR31*(1+$BF$3)*(1+$BF$4) -> 607.8081 | BG31: =$BE31*AS31*(1+$BF$3)*(1+$BF$4) -> 607.8081 | BH31: =$BE31*AT31*(1+$BF$3)*(1+$BF$4) -> 607.8081 | BI31: =$BE31*AU31*(1+$BF$3)*(1+$BF$4) -> 607.8081 | BJ31: =$BE31*AV31*(1+$BF$3)*(1+$BF$4) -> 607.8081 | BK31: =$BE31*AW31*(1+$BF$3)*(1+$BF$4) -> 607.8081 | BL31: =$BE31*AX31*(1+$BF$3)*(1+$BF$4) -> 607.8081 | BM31: =$BE31*AY31*(1+$BF$3)*(1+$BF$4) -> 607.8081 | ... BQ31: =$BE31*BC31*(1+$BF$3)*(1+$BF$4) -> 607.8081 | BR31: =SUM(BF31:BQ31) -> 7293.6973 | BS31: 1 | BT31: =$BS31*BF31*(1+$BT$3)*(1+$BT$4) -> 676.49042 | BU31: =$BS31*BG31*(1+$BT$3)*(1+$BT$4) -> 676.49042 | BV31: =$BS31*BH31*(1+$BT$3)*(1+$BT$4) -> 676.49042 | BW31: =$BS31*BI31*(1+$BT$3)*(1+$BT$4) -> 676.49042 | BX31: =$BS31*BJ31*(1+$BT$3)*(1+$BT$4) -> 676.49042 | BY31: =$BS31*BK31*(1+$BT$3)*(1+$BT$4) -> 676.49042 | BZ31: =$BS31*BL31*(1+$BT$3)*(1+$BT$4) -> 676.49042 | CA31: =$BS31*BM31*(1+$BT$3)*(1+$BT$4) -> 676.49042 | ... CE31: =$BS31*BQ31*(1+$BT$3)*(1+$BT$4) -> 676.49042 | CF31: =SUM(BT31:CE31) -> 8117.885 | CG31: 1 | CH31: =$CG31*BT31*(1+$CH$3)*(1+$CH$4) -> 752.93384 | CI31: =$CG31*BU31*(1+$CH$3)*(1+$CH$4) -> 752.93384 | CJ31: =$CG31*BV31*(1+$CH$3)*(1+$CH$4) -> 752.93384 | CK31: =$CG31*BW31*(1+$CH$3)*(1+$CH$4) -> 752.93384 | CL31: =$CG31*BX31*(1+$CH$3)*(1+$CH$4) -> 752.93384 | CM31: =$CG31*BY31*(1+$CH$3)*(1+$CH$4) -> 752.93384 | CN31: =$CG31*BZ31*(1+$CH$3)*(1+$CH$4) -> 752.93384 | CO31: =$CG31*CA31*(1+$CH$3)*(1+$CH$4) -> 752.93384 | ... CS31: =$CG31*CE31*(1+$CH$3)*(1+$CH$4) -> 752.93384 | CT31: =SUM(CH31:CS31) -> 9035.2061 | CU31: 1 | CV31: =$CU31*CH31*(1+$CV$3)*(1+$CV$4) -> 838.01536 | CW31: =$CU31*CI31*(1+$CV$3)*(1+$CV$4) -> 838.01536 | CX31: =$CU31*CJ31*(1+$CV$3)*(1+$CV$4) -> 838.01536 | CY31: =$CU31*CK31*(1+$CV$3)*(1+$CV$4) -> 838.01536 | CZ31: =$CU31*CL31*(1+$CV$3)*(1+$CV$4) -> 838.01536 | DA31: =$CU31*CM31*(1+$CV$3)*(1+$CV$4) -> 838.01536 | DB31: =$CU31*CN31*(1+$CV$3)*(1+$CV$4) -> 838.01536 | DC31: =$CU31*CO31*(1+$CV$3)*(1+$CV$4) -> 838.01536 | ... DG31: =$CU31*CS31*(1+$CV$3)*(1+$CV$4) -> 838.01536 | DH31: =SUM(CV31:DG31) -> 10056.184 | DI31: 1 | DJ31: =$DI31*CV31*(1+$DJ$3)*(1+$DJ$4) -> 932.7111 | DK31: =$DI31*CW31*(1+$DJ$3)*(1+$DJ$4) -> 932.7111 | DL31: =$DI31*CX31*(1+$DJ$3)*(1+$DJ$4) -> 932.7111 | DM31: =$DI31*CY31*(1+$DJ$3)*(1+$DJ$4) -> 932.7111 | DN31: =$DI31*CZ31*(1+$DJ$3)*(1+$DJ$4) -> 932.7111 | DO31: =$DI31*DA31*(1+$DJ$3)*(1+$DJ$4) -> 932.7111 | DP31: =$DI31*DB31*(1+$DJ$3)*(1+$DJ$4) -> 932.7111 | DQ31: =$DI31*DC31*(1+$DJ$3)*(1+$DJ$4) -> 932.7111 | ... DU31: =$DI31*DG31*(1+$DJ$3)*(1+$DJ$4) -> 932.7111 | DV31: =SUM(DJ31:DU31) -> 11192.533 | DW31: 1 | DX31: =$DW31*DJ31*(1+$DX$3)*(1+$DX$4) -> 1038.1075 | DY31: =$DW31*DK31*(1+$DX$3)*(1+$DX$4) -> 1038.1075 | DZ31: =$DW31*DL31*(1+$DX$3)*(1+$DX$4) -> 1038.1075 | EA31: =$DW31*DM31*(1+$DX$3)*(1+$DX$4) -> 1038.1075 | EB31: =$DW31*DN31*(1+$DX$3)*(1+$DX$4) -> 1038.1075 | EC31: =$DW31*DO31*(1+$DX$3)*(1+$DX$4) -> 1038.1075 | ED31: =$DW31*DP31*(1+$DX$3)*(1+$DX$4) -> 1038.1075 | EE31: =$DW31*DQ31*(1+$DX$3)*(1+$DX$4) -> 1038.1075 | ... EI31: =$DW31*DU31*(1+$DX$3)*(1+$DX$4) -> 1038.1075 | EJ31: =SUM(DX31:EI31) -> 12457.289
A32: Cartón para embalaje | B32: =12*B7 -> 17760 | C32: =B32*(1+C$3) -> 17760 | D32: =C32*(1+D$3) -> 17760 | E32: =D32*(1+E$3) -> 17760 | F32: =E32*(1+F$3) -> 17760 | G32: =F32*(1+G$3) -> 17760 | H32: =G32*(1+H$3) -> 17760 | I32: =H32*(1+I$3) -> 17760 | J32: =I32*(1+J$3) -> 17760 | ... M32: =L32*(1+M$3) -> 17760 | N32: =SUM(B32:M32) -> 213120 | O32: 1 | P32: =$O32*B32*(1+$P$3)*(1+$P$4) -> 19573.296 | Q32: =$O32*C32*(1+$P$3)*(1+$P$4) -> 19573.296 | R32: =$O32*D32*(1+$P$3)*(1+$P$4) -> 19573.296 | S32: =$O32*E32*(1+$P$3)*(1+$P$4) -> 19573.296 | T32: =$O32*F32*(1+$P$3)*(1+$P$4) -> 19573.296 | U32: =$O32*G32*(1+$P$3)*(1+$P$4) -> 19573.296 | V32: =$O32*H32*(1+$P$3)*(1+$P$4) -> 19573.296 | W32: =$O32*I32*(1+$P$3)*(1+$P$4) -> 19573.296 | ... AA32: =$O32*M32*(1+$P$3)*(1+$P$4) -> 19573.296 | AB32: =SUM(P32:AA32) -> 234879.55 | AC32: 1 | AD32: =$AC32*P32*(1+$AD$3)*(1+$AD$4) -> 21785.078 | AE32: =$AC32*Q32*(1+$AD$3)*(1+$AD$4) -> 21785.078 | AF32: =$AC32*R32*(1+$AD$3)*(1+$AD$4) -> 21785.078 | AG32: =$AC32*S32*(1+$AD$3)*(1+$AD$4) -> 21785.078 | AH32: =$AC32*T32*(1+$AD$3)*(1+$AD$4) -> 21785.078 | AI32: =$AC32*U32*(1+$AD$3)*(1+$AD$4) -> 21785.078 | AJ32: =$AC32*V32*(1+$AD$3)*(1+$AD$4) -> 21785.078 | AK32: =$AC32*W32*(1+$AD$3)*(1+$AD$4) -> 21785.078 | ... AO32: =$AC32*AA32*(1+$AD$3)*(1+$AD$4) -> 21785.078 | AP32: =SUM(AD32:AO32) -> 261420.94 | AQ32: 1 | AR32: =$AQ32*AD32*(1+$AR$3)*(1+$AR$4) -> 24246.792 | AS32: =$AQ32*AE32*(1+$AR$3)*(1+$AR$4) -> 24246.792 | AT32: =$AQ32*AF32*(1+$AR$3)*(1+$AR$4) -> 24246.792 | AU32: =$AQ32*AG32*(1+$AR$3)*(1+$AR$4) -> 24246.792 | AV32: =$AQ32*AH32*(1+$AR$3)*(1+$AR$4) -> 24246.792 | AW32: =$AQ32*AI32*(1+$AR$3)*(1+$AR$4) -> 24246.792 | AX32: =$AQ32*AJ32*(1+$AR$3)*(1+$AR$4) -> 24246.792 | AY32: =$AQ32*AK32*(1+$AR$3)*(1+$AR$4) -> 24246.792 | ... BC32: =$AQ32*AO32*(1+$AR$3)*(1+$AR$4) -> 24246.792 | BD32: =SUM(AR32:BC32) -> 290961.51 | BE32: 1 | BF32: =$BE32*AR32*(1+$BF$3)*(1+$BF$4) -> 26986.68 | BG32: =$BE32*AS32*(1+$BF$3)*(1+$BF$4) -> 26986.68 | BH32: =$BE32*AT32*(1+$BF$3)*(1+$BF$4) -> 26986.68 | BI32: =$BE32*AU32*(1+$BF$3)*(1+$BF$4) -> 26986.68 | BJ32: =$BE32*AV32*(1+$BF$3)*(1+$BF$4) -> 26986.68 | BK32: =$BE32*AW32*(1+$BF$3)*(1+$BF$4) -> 26986.68 | BL32: =$BE32*AX32*(1+$BF$3)*(1+$BF$4) -> 26986.68 | BM32: =$BE32*AY32*(1+$BF$3)*(1+$BF$4) -> 26986.68 | ... BQ32: =$BE32*BC32*(1+$BF$3)*(1+$BF$4) -> 26986.68 | BR32: =SUM(BF32:BQ32) -> 323840.16 | BS32: 1 | BT32: =$BS32*BF32*(1+$BT$3)*(1+$BT$4) -> 30036.175 | BU32: =$BS32*BG32*(1+$BT$3)*(1+$BT$4) -> 30036.175 | BV32: =$BS32*BH32*(1+$BT$3)*(1+$BT$4) -> 30036.175 | BW32: =$BS32*BI32*(1+$BT$3)*(1+$BT$4) -> 30036.175 | BX32: =$BS32*BJ32*(1+$BT$3)*(1+$BT$4) -> 30036.175 | BY32: =$BS32*BK32*(1+$BT$3)*(1+$BT$4) -> 30036.175 | BZ32: =$BS32*BL32*(1+$BT$3)*(1+$BT$4) -> 30036.175 | CA32: =$BS32*BM32*(1+$BT$3)*(1+$BT$4) -> 30036.175 | ... CE32: =$BS32*BQ32*(1+$BT$3)*(1+$BT$4) -> 30036.175 | CF32: =SUM(BT32:CE32) -> 360434.1 | CG32: 1 | CH32: =$CG32*BT32*(1+$CH$3)*(1+$CH$4) -> 33430.262 | CI32: =$CG32*BU32*(1+$CH$3)*(1+$CH$4) -> 33430.262 | CJ32: =$CG32*BV32*(1+$CH$3)*(1+$CH$4) -> 33430.262 | CK32: =$CG32*BW32*(1+$CH$3)*(1+$CH$4) -> 33430.262 | CL32: =$CG32*BX32*(1+$CH$3)*(1+$CH$4) -> 33430.262 | CM32: =$CG32*BY32*(1+$CH$3)*(1+$CH$4) -> 33430.262 | CN32: =$CG32*BZ32*(1+$CH$3)*(1+$CH$4) -> 33430.262 | CO32: =$CG32*CA32*(1+$CH$3)*(1+$CH$4) -> 33430.262 | ... CS32: =$CG32*CE32*(1+$CH$3)*(1+$CH$4) -> 33430.262 | CT32: =SUM(CH32:CS32) -> 401163.15 | CU32: 1 | CV32: =$CU32*CH32*(1+$CV$3)*(1+$CV$4) -> 37207.882 | CW32: =$CU32*CI32*(1+$CV$3)*(1+$CV$4) -> 37207.882 | CX32: =$CU32*CJ32*(1+$CV$3)*(1+$CV$4) -> 37207.882 | CY32: =$CU32*CK32*(1+$CV$3)*(1+$CV$4) -> 37207.882 | CZ32: =$CU32*CL32*(1+$CV$3)*(1+$CV$4) -> 37207.882 | DA32: =$CU32*CM32*(1+$CV$3)*(1+$CV$4) -> 37207.882 | DB32: =$CU32*CN32*(1+$CV$3)*(1+$CV$4) -> 37207.882 | DC32: =$CU32*CO32*(1+$CV$3)*(1+$CV$4) -> 37207.882 | ... DG32: =$CU32*CS32*(1+$CV$3)*(1+$CV$4) -> 37207.882 | DH32: =SUM(CV32:DG32) -> 446494.58 | DI32: 1 | DJ32: =$DI32*CV32*(1+$DJ$3)*(1+$DJ$4) -> 41412.373 | DK32: =$DI32*CW32*(1+$DJ$3)*(1+$DJ$4) -> 41412.373 | DL32: =$DI32*CX32*(1+$DJ$3)*(1+$DJ$4) -> 41412.373 | DM32: =$DI32*CY32*(1+$DJ$3)*(1+$DJ$4) -> 41412.373 | DN32: =$DI32*CZ32*(1+$DJ$3)*(1+$DJ$4) -> 41412.373 | DO32: =$DI32*DA32*(1+$DJ$3)*(1+$DJ$4) -> 41412.373 | DP32: =$DI32*DB32*(1+$DJ$3)*(1+$DJ$4) -> 41412.373 | DQ32: =$DI32*DC32*(1+$DJ$3)*(1+$DJ$4) -> 41412.373 | ... DU32: =$DI32*DG32*(1+$DJ$3)*(1+$DJ$4) -> 41412.373 | DV32: =SUM(DJ32:DU32) -> 496948.47 | DW32: 1 | DX32: =$DW32*DJ32*(1+$DX$3)*(1+$DX$4) -> 46091.971 | DY32: =$DW32*DK32*(1+$DX$3)*(1+$DX$4) -> 46091.971 | DZ32: =$DW32*DL32*(1+$DX$3)*(1+$DX$4) -> 46091.971 | EA32: =$DW32*DM32*(1+$DX$3)*(1+$DX$4) -> 46091.971 | EB32: =$DW32*DN32*(1+$DX$3)*(1+$DX$4) -> 46091.971 | EC32: =$DW32*DO32*(1+$DX$3)*(1+$DX$4) -> 46091.971 | ED32: =$DW32*DP32*(1+$DX$3)*(1+$DX$4) -> 46091.971 | EE32: =$DW32*DQ32*(1+$DX$3)*(1+$DX$4) -> 46091.971 | ... EI32: =$DW32*DU32*(1+$DX$3)*(1+$DX$4) -> 46091.971 | EJ32: =SUM(DX32:EI32) -> 553103.65
A33: Material de limpieza | B33: 9000 | C33: =B33 -> 9000 | D33: =C33*(1+D$3) -> 9000 | E33: =D33*(1+E$3) -> 9000 | F33: =E33*(1+F$3) -> 9000 | G33: =F33*(1+G$3) -> 9000 | H33: =G33*(1+H$3) -> 9000 | I33: =H33*(1+I$3) -> 9000 | J33: =I33*(1+J$3) -> 9000 | K33: =J33*(1+K$3) -> 9000 | ... M33: =L33*(1+M$3) -> 9000 | N33: =SUM(B33:M33) -> 108000 | O33: 1 | P33: =$O33*B33*(1+$P$4) -> 9630 | Q33: =$O33*C33*(1+$P$4) -> 9630 | R33: =$O33*D33*(1+$P$4) -> 9630 | S33: =$O33*E33*(1+$P$4) -> 9630 | T33: =$O33*F33*(1+$P$4) -> 9630 | U33: =$O33*G33*(1+$P$4) -> 9630 | V33: =$O33*H33*(1+$P$4) -> 9630 | W33: =$O33*I33*(1+$P$4) -> 9630 | ... AA33: =$O33*M33*(1+$P$4) -> 9630 | AB33: =SUM(P33:AA33) -> 115560 | AC33: 1 | AD33: =$AC33*P33*(1+$AD$4) -> 10207.8 | AE33: =$AC33*Q33*(1+$AD$4) -> 10207.8 | AF33: =$AC33*R33*(1+$AD$4) -> 10207.8 | AG33: =$AC33*S33*(1+$AD$4) -> 10207.8 | AH33: =$AC33*T33*(1+$AD$4) -> 10207.8 | AI33: =$AC33*U33*(1+$AD$4) -> 10207.8 | AJ33: =$AC33*V33*(1+$AD$4) -> 10207.8 | AK33: =$AC33*W33*(1+$AD$4) -> 10207.8 | ... AO33: =$AC33*AA33*(1+$AD$4) -> 10207.8 | AP33: =SUM(AD33:AO33) -> 122493.6 | AQ33: 1 | AR33: =$AQ33*AD33*(1+$AR$4) -> 10820.268 | AS33: =$AQ33*AE33*(1+$AR$4) -> 10820.268 | AT33: =$AQ33*AF33*(1+$AR$4) -> 10820.268 | AU33: =$AQ33*AG33*(1+$AR$4) -> 10820.268 | AV33: =$AQ33*AH33*(1+$AR$4) -> 10820.268 | AW33: =$AQ33*AI33*(1+$AR$4) -> 10820.268 | AX33: =$AQ33*AJ33*(1+$AR$4) -> 10820.268 | AY33: =$AQ33*AK33*(1+$AR$4) -> 10820.268 | ... BC33: =$AQ33*AO33*(1+$AR$4) -> 10820.268 | BD33: =SUM(AR33:BC33) -> 129843.22 | BE33: 1 | BF33: =$BE33*AR33*(1+$BF$4) -> 11469.484 | BG33: =$BE33*AS33*(1+$BF$4) -> 11469.484 | BH33: =$BE33*AT33*(1+$BF$4) -> 11469.484 | BI33: =$BE33*AU33*(1+$BF$4) -> 11469.484 | BJ33: =$BE33*AV33*(1+$BF$4) -> 11469.484 | BK33: =$BE33*AW33*(1+$BF$4) -> 11469.484 | BL33: =$BE33*AX33*(1+$BF$4) -> 11469.484 | BM33: =$BE33*AY33*(1+$BF$4) -> 11469.484 | ... BQ33: =$BE33*BC33*(1+$BF$4) -> 11469.484 | BR33: =SUM(BF33:BQ33) -> 137633.81 | BS33: 1 | BT33: =$BS33*BF33*(1+$BT$4) -> 12157.653 | BU33: =$BS33*BG33*(1+$BT$4) -> 12157.653 | BV33: =$BS33*BH33*(1+$BT$4) -> 12157.653 | BW33: =$BS33*BI33*(1+$BT$4) -> 12157.653 | BX33: =$BS33*BJ33*(1+$BT$4) -> 12157.653 | BY33: =$BS33*BK33*(1+$BT$4) -> 12157.653 | BZ33: =$BS33*BL33*(1+$BT$4) -> 12157.653 | CA33: =$BS33*BM33*(1+$BT$4) -> 12157.653 | ... CE33: =$BS33*BQ33*(1+$BT$4) -> 12157.653 | CF33: =SUM(BT33:CE33) -> 145891.84 | CG33: 1 | CH33: =$CG33*BT33*(1+$CH$4) -> 12887.112 | CI33: =$CG33*BU33*(1+$CH$4) -> 12887.112 | CJ33: =$CG33*BV33*(1+$CH$4) -> 12887.112 | CK33: =$CG33*BW33*(1+$CH$4) -> 12887.112 | CL33: =$CG33*BX33*(1+$CH$4) -> 12887.112 | CM33: =$CG33*BY33*(1+$CH$4) -> 12887.112 | CN33: =$CG33*BZ33*(1+$CH$4) -> 12887.112 | CO33: =$CG33*CA33*(1+$CH$4) -> 12887.112 | ... CS33: =$CG33*CE33*(1+$CH$4) -> 12887.112 | CT33: =SUM(CH33:CS33) -> 154645.35 | CU33: 1 | CV33: =$CU33*CH33*(1+$CV$4) -> 13660.339 | CW33: =$CU33*CI33*(1+$CV$4) -> 13660.339 | CX33: =$CU33*CJ33*(1+$CV$4) -> 13660.339 | CY33: =$CU33*CK33*(1+$CV$4) -> 13660.339 | CZ33: =$CU33*CL33*(1+$CV$4) -> 13660.339 | DA33: =$CU33*CM33*(1+$CV$4) -> 13660.339 | DB33: =$CU33*CN33*(1+$CV$4) -> 13660.339 | DC33: =$CU33*CO33*(1+$CV$4) -> 13660.339 | ... DG33: =$CU33*CS33*(1+$CV$4) -> 13660.339 | DH33: =SUM(CV33:DG33) -> 163924.07 | DI33: 1 | DJ33: =$DI33*CV33*(1+$DJ$4) -> 14479.959 | DK33: =$DI33*CW33*(1+$DJ$4) -> 14479.959 | DL33: =$DI33*CX33*(1+$DJ$4) -> 14479.959 | DM33: =$DI33*CY33*(1+$DJ$4) -> 14479.959 | DN33: =$DI33*CZ33*(1+$DJ$4) -> 14479.959 | DO33: =$DI33*DA33*(1+$DJ$4) -> 14479.959 | DP33: =$DI33*DB33*(1+$DJ$4) -> 14479.959 | DQ33: =$DI33*DC33*(1+$DJ$4) -> 14479.959 | ... DU33: =$DI33*DG33*(1+$DJ$4) -> 14479.959 | DV33: =SUM(DJ33:DU33) -> 173759.51 | DW33: 1 | DX33: =$DW33*DJ33*(1+$DX$4) -> 15348.757 | DY33: =$DW33*DK33*(1+$DX$4) -> 15348.757 | DZ33: =$DW33*DL33*(1+$DX$4) -> 15348.757 | EA33: =$DW33*DM33*(1+$DX$4) -> 15348.757 | EB33: =$DW33*DN33*(1+$DX$4) -> 15348.757 | EC33: =$DW33*DO33*(1+$DX$4) -> 15348.757 | ED33: =$DW33*DP33*(1+$DX$4) -> 15348.757 | EE33: =$DW33*DQ33*(1+$DX$4) -> 15348.757 | ... EI33: =$DW33*DU33*(1+$DX$4) -> 15348.757 | EJ33: =SUM(DX33:EI33) -> 184185.08
A34: Luz | B34: 8000 | C34: =B34*(1+C$3) -> 8000 | D34: =C34*(1+D$3) -> 8000 | E34: =D34*(1+E$3) -> 8000 | F34: =E34*(1+F$3) -> 8000 | G34: =F34*(1+G$3) -> 8000 | H34: =G34*(1+H$3) -> 8000 | I34: =H34*(1+I$3) -> 8000 | J34: =I34*(1+J$3) -> 8000 | ... M34: =L34*(1+M$3) -> 8000 | N34: =SUM(B34:M34) -> 96000 | O34: 1 | P34: =$O34*B34*(1+$P$3)*(1+$P$4) -> 8816.8 | Q34: =$O34*C34*(1+$P$3)*(1+$P$4) -> 8816.8 | R34: =$O34*D34*(1+$P$3)*(1+$P$4) -> 8816.8 | S34: =$O34*E34*(1+$P$3)*(1+$P$4) -> 8816.8 | T34: =$O34*F34*(1+$P$3)*(1+$P$4) -> 8816.8 | U34: =$O34*G34*(1+$P$3)*(1+$P$4) -> 8816.8 | V34: =$O34*H34*(1+$P$3)*(1+$P$4) -> 8816.8 | W34: =$O34*I34*(1+$P$3)*(1+$P$4) -> 8816.8 | ... AA34: =$O34*M34*(1+$P$3)*(1+$P$4) -> 8816.8 | AB34: =SUM(P34:AA34) -> 105801.6 | AC34: 1 | AD34: =$AC34*P34*(1+$AD$3)*(1+$AD$4) -> 9813.0984 | AE34: =$AC34*Q34*(1+$AD$3)*(1+$AD$4) -> 9813.0984 | AF34: =$AC34*R34*(1+$AD$3)*(1+$AD$4) -> 9813.0984 | AG34: =$AC34*S34*(1+$AD$3)*(1+$AD$4) -> 9813.0984 | AH34: =$AC34*T34*(1+$AD$3)*(1+$AD$4) -> 9813.0984 | AI34: =$AC34*U34*(1+$AD$3)*(1+$AD$4) -> 9813.0984 | AJ34: =$AC34*V34*(1+$AD$3)*(1+$AD$4) -> 9813.0984 | AK34: =$AC34*W34*(1+$AD$3)*(1+$AD$4) -> 9813.0984 | ... AO34: =$AC34*AA34*(1+$AD$3)*(1+$AD$4) -> 9813.0984 | AP34: =SUM(AD34:AO34) -> 117757.18 | AQ34: 1 | AR34: =$AQ34*AD34*(1+$AR$3)*(1+$AR$4) -> 10921.979 | AS34: =$AQ34*AE34*(1+$AR$3)*(1+$AR$4) -> 10921.979 | AT34: =$AQ34*AF34*(1+$AR$3)*(1+$AR$4) -> 10921.979 | AU34: =$AQ34*AG34*(1+$AR$3)*(1+$AR$4) -> 10921.979 | AV34: =$AQ34*AH34*(1+$AR$3)*(1+$AR$4) -> 10921.979 | AW34: =$AQ34*AI34*(1+$AR$3)*(1+$AR$4) -> 10921.979 | AX34: =$AQ34*AJ34*(1+$AR$3)*(1+$AR$4) -> 10921.979 | AY34: =$AQ34*AK34*(1+$AR$3)*(1+$AR$4) -> 10921.979 | ... BC34: =$AQ34*AO34*(1+$AR$3)*(1+$AR$4) -> 10921.979 | BD34: =SUM(AR34:BC34) -> 131063.74 | BE34: 1 | BF34: =$BE34*AR34*(1+$BF$3)*(1+$BF$4) -> 12156.162 | BG34: =$BE34*AS34*(1+$BF$3)*(1+$BF$4) -> 12156.162 | BH34: =$BE34*AT34*(1+$BF$3)*(1+$BF$4) -> 12156.162 | BI34: =$BE34*AU34*(1+$BF$3)*(1+$BF$4) -> 12156.162 | BJ34: =$BE34*AV34*(1+$BF$3)*(1+$BF$4) -> 12156.162 | BK34: =$BE34*AW34*(1+$BF$3)*(1+$BF$4) -> 12156.162 | BL34: =$BE34*AX34*(1+$BF$3)*(1+$BF$4) -> 12156.162 | BM34: =$BE34*AY34*(1+$BF$3)*(1+$BF$4) -> 12156.162 | ... BQ34: =$BE34*BC34*(1+$BF$3)*(1+$BF$4) -> 12156.162 | BR34: =SUM(BF34:BQ34) -> 145873.95 | BS34: 1 | BT34: =$BS34*BF34*(1+$BT$3)*(1+$BT$4) -> 13529.808 | BU34: =$BS34*BG34*(1+$BT$3)*(1+$BT$4) -> 13529.808 | BV34: =$BS34*BH34*(1+$BT$3)*(1+$BT$4) -> 13529.808 | BW34: =$BS34*BI34*(1+$BT$3)*(1+$BT$4) -> 13529.808 | BX34: =$BS34*BJ34*(1+$BT$3)*(1+$BT$4) -> 13529.808 | BY34: =$BS34*BK34*(1+$BT$3)*(1+$BT$4) -> 13529.808 | BZ34: =$BS34*BL34*(1+$BT$3)*(1+$BT$4) -> 13529.808 | CA34: =$BS34*BM34*(1+$BT$3)*(1+$BT$4) -> 13529.808 | ... CE34: =$BS34*BQ34*(1+$BT$3)*(1+$BT$4) -> 13529.808 | CF34: =SUM(BT34:CE34) -> 162357.7 | CG34: 1 | CH34: =$CG34*BT34*(1+$CH$3)*(1+$CH$4) -> 15058.677 | CI34: =$CG34*BU34*(1+$CH$3)*(1+$CH$4) -> 15058.677 | CJ34: =$CG34*BV34*(1+$CH$3)*(1+$CH$4) -> 15058.677 | CK34: =$CG34*BW34*(1+$CH$3)*(1+$CH$4) -> 15058.677 | CL34: =$CG34*BX34*(1+$CH$3)*(1+$CH$4) -> 15058.677 | CM34: =$CG34*BY34*(1+$CH$3)*(1+$CH$4) -> 15058.677 | CN34: =$CG34*BZ34*(1+$CH$3)*(1+$CH$4) -> 15058.677 | CO34: =$CG34*CA34*(1+$CH$3)*(1+$CH$4) -> 15058.677 | ... CS34: =$CG34*CE34*(1+$CH$3)*(1+$CH$4) -> 15058.677 | CT34: =SUM(CH34:CS34) -> 180704.12 | CU34: 1 | CV34: =$CU34*CH34*(1+$CV$3)*(1+$CV$4) -> 16760.307 | CW34: =$CU34*CI34*(1+$CV$3)*(1+$CV$4) -> 16760.307 | CX34: =$CU34*CJ34*(1+$CV$3)*(1+$CV$4) -> 16760.307 | CY34: =$CU34*CK34*(1+$CV$3)*(1+$CV$4) -> 16760.307 | CZ34: =$CU34*CL34*(1+$CV$3)*(1+$CV$4) -> 16760.307 | DA34: =$CU34*CM34*(1+$CV$3)*(1+$CV$4) -> 16760.307 | DB34: =$CU34*CN34*(1+$CV$3)*(1+$CV$4) -> 16760.307 | DC34: =$CU34*CO34*(1+$CV$3)*(1+$CV$4) -> 16760.307 | ... DG34: =$CU34*CS34*(1+$CV$3)*(1+$CV$4) -> 16760.307 | DH34: =SUM(CV34:DG34) -> 201123.69 | DI34: 1 | DJ34: =$DI34*CV34*(1+$DJ$3)*(1+$DJ$4) -> 18654.222 | DK34: =$DI34*CW34*(1+$DJ$3)*(1+$DJ$4) -> 18654.222 | DL34: =$DI34*CX34*(1+$DJ$3)*(1+$DJ$4) -> 18654.222 | DM34: =$DI34*CY34*(1+$DJ$3)*(1+$DJ$4) -> 18654.222 | DN34: =$DI34*CZ34*(1+$DJ$3)*(1+$DJ$4) -> 18654.222 | DO34: =$DI34*DA34*(1+$DJ$3)*(1+$DJ$4) -> 18654.222 | DP34: =$DI34*DB34*(1+$DJ$3)*(1+$DJ$4) -> 18654.222 | DQ34: =$DI34*DC34*(1+$DJ$3)*(1+$DJ$4) -> 18654.222 | ... DU34: =$DI34*DG34*(1+$DJ$3)*(1+$DJ$4) -> 18654.222 | DV34: =SUM(DJ34:DU34) -> 223850.66 | DW34: 1 | DX34: =$DW34*DJ34*(1+$DX$3)*(1+$DX$4) -> 20762.149 | DY34: =$DW34*DK34*(1+$DX$3)*(1+$DX$4) -> 20762.149 | DZ34: =$DW34*DL34*(1+$DX$3)*(1+$DX$4) -> 20762.149 | EA34: =$DW34*DM34*(1+$DX$3)*(1+$DX$4) -> 20762.149 | EB34: =$DW34*DN34*(1+$DX$3)*(1+$DX$4) -> 20762.149 | EC34: =$DW34*DO34*(1+$DX$3)*(1+$DX$4) -> 20762.149 | ED34: =$DW34*DP34*(1+$DX$3)*(1+$DX$4) -> 20762.149 | EE34: =$DW34*DQ34*(1+$DX$3)*(1+$DX$4) -> 20762.149 | ... EI34: =$DW34*DU34*(1+$DX$3)*(1+$DX$4) -> 20762.149 | EJ34: =SUM(DX34:EI34) -> 249145.79
A35: 1.4. Personal indirecto | B35: =SUM(B36:B40) -> 46000 | C35: =SUM(C36:C40) -> 46000 | D35: =SUM(D36:D40) -> 46000 | E35: =SUM(E36:E40) -> 46000 | F35: =SUM(F36:F40) -> 46000 | G35: =SUM(G36:G40) -> 46000 | H35: =SUM(H36:H40) -> 46000 | I35: =SUM(I36:I40) -> 46000 | ... M35: =SUM(M36:M40) -> 46000 | N35: =SUM(B35:M35) -> 552000 | P35: =SUM(P36:P40) -> 49220 | Q35: =SUM(Q36:Q40) -> 49220 | R35: =SUM(R36:R40) -> 49220 | S35: =SUM(S36:S40) -> 49220 | T35: =SUM(T36:T40) -> 49220 | U35: =SUM(U36:U40) -> 49220 | V35: =SUM(V36:V40) -> 49220 | W35: =SUM(W36:W40) -> 49220 | ... AA35: =SUM(AA36:AA40) -> 49220 | AB35: =SUM(P35:AA35) -> 590640 | AD35: =SUM(AD36:AD40) -> 52173.2 | AE35: =SUM(AE36:AE40) -> 52173.2 | AF35: =SUM(AF36:AF40) -> 52173.2 | AG35: =SUM(AG36:AG40) -> 52173.2 | AH35: =SUM(AH36:AH40) -> 52173.2 | AI35: =SUM(AI36:AI40) -> 52173.2 | AJ35: =SUM(AJ36:AJ40) -> 52173.2 | AK35: =SUM(AK36:AK40) -> 52173.2 | ... AO35: =SUM(AO36:AO40) -> 52173.2 | AP35: =SUM(AD35:AO35) -> 626078.4 | AR35: =SUM(AR36:AR40) -> 55303.592 | AS35: =SUM(AS36:AS40) -> 55303.592 | AT35: =SUM(AT36:AT40) -> 55303.592 | AU35: =SUM(AU36:AU40) -> 55303.592 | AV35: =SUM(AV36:AV40) -> 55303.592 | AW35: =SUM(AW36:AW40) -> 55303.592 | AX35: =SUM(AX36:AX40) -> 55303.592 | AY35: =SUM(AY36:AY40) -> 55303.592 | ... BC35: =SUM(BC36:BC40) -> 55303.592 | BD35: =SUM(AR35:BC35) -> 663643.1 | BF35: =SUM(BF36:BF40) -> 58621.808 | BG35: =SUM(BG36:BG40) -> 58621.808 | BH35: =SUM(BH36:BH40) -> 58621.808 | BI35: =SUM(BI36:BI40) -> 58621.808 | BJ35: =SUM(BJ36:BJ40) -> 58621.808 | BK35: =SUM(BK36:BK40) -> 58621.808 | BL35: =SUM(BL36:BL40) -> 58621.808 | BM35: =SUM(BM36:BM40) -> 58621.808 | ... BQ35: =SUM(BQ36:BQ40) -> 58621.808 | BR35: =SUM(BF35:BQ35) -> 703461.69 | BT35: =SUM(BT36:BT40) -> 62139.116 | BU35: =SUM(BU36:BU40) -> 62139.116 | BV35: =SUM(BV36:BV40) -> 62139.116 | BW35: =SUM(BW36:BW40) -> 62139.116 | BX35: =SUM(BX36:BX40) -> 62139.116 | BY35: =SUM(BY36:BY40) -> 62139.116 | BZ35: =SUM(BZ36:BZ40) -> 62139.116 | CA35: =SUM(CA36:CA40) -> 62139.116 | ... CE35: =SUM(CE36:CE40) -> 62139.116 | CF35: =SUM(BT35:CE35) -> 745669.39 | CH35: =SUM(CH36:CH40) -> 65867.463 | CI35: =SUM(CI36:CI40) -> 65867.463 | CJ35: =SUM(CJ36:CJ40) -> 65867.463 | CK35: =SUM(CK36:CK40) -> 65867.463 | CL35: =SUM(CL36:CL40) -> 65867.463 | CM35: =SUM(CM36:CM40) -> 65867.463 | CN35: =SUM(CN36:CN40) -> 65867.463 | CO35: =SUM(CO36:CO40) -> 65867.463 | ... CS35: =SUM(CS36:CS40) -> 65867.463 | CT35: =SUM(CH35:CS35) -> 790409.56 | CV35: =SUM(CV36:CV40) -> 69819.511 | CW35: =SUM(CW36:CW40) -> 69819.511 | CX35: =SUM(CX36:CX40) -> 69819.511 | CY35: =SUM(CY36:CY40) -> 69819.511 | CZ35: =SUM(CZ36:CZ40) -> 69819.511 | DA35: =SUM(DA36:DA40) -> 69819.511 | DB35: =SUM(DB36:DB40) -> 69819.511 | DC35: =SUM(DC36:DC40) -> 69819.511 | ... DG35: =SUM(DG36:DG40) -> 69819.511 | DH35: =SUM(CV35:DG35) -> 837834.13 | DJ35: =SUM(DJ36:DJ40) -> 74008.681 | DK35: =SUM(DK36:DK40) -> 74008.681 | DL35: =SUM(DL36:DL40) -> 74008.681 | DM35: =SUM(DM36:DM40) -> 74008.681 | DN35: =SUM(DN36:DN40) -> 74008.681 | DO35: =SUM(DO36:DO40) -> 74008.681 | DP35: =SUM(DP36:DP40) -> 74008.681 | DQ35: =SUM(DQ36:DQ40) -> 74008.681 | ... DU35: =SUM(DU36:DU40) -> 74008.681 | DV35: =SUM(DJ35:DU35) -> 888104.18 | DX35: =SUM(DX36:DX40) -> 78449.202 | DY35: =SUM(DY36:DY40) -> 78449.202 | DZ35: =SUM(DZ36:DZ40) -> 78449.202 | EA35: =SUM(EA36:EA40) -> 78449.202 | EB35: =SUM(EB36:EB40) -> 78449.202 | EC35: =SUM(EC36:EC40) -> 78449.202 | ED35: =SUM(ED36:ED40) -> 78449.202 | EE35: =SUM(EE36:EE40) -> 78449.202 | ... EI35: =SUM(EI36:EI40) -> 78449.202 | EJ35: =SUM(DX35:EI35) -> 941390.43
A36: Técnico de mantenimiento | B36: 10000 | C36: =B36 -> 10000 | D36: =C36 -> 10000 | E36: =D36 -> 10000 | F36: =E36 -> 10000 | G36: =F36 -> 10000 | H36: =G36 -> 10000 | I36: =H36 -> 10000 | J36: =I36 -> 10000 | ... M36: =L36 -> 10000 | N36: =SUM(B36:M36) -> 120000 | O36: 1 | P36: =$O36*B36*(1+$P$4) -> 10700 | Q36: =$O36*C36*(1+$P$4) -> 10700 | R36: =$O36*D36*(1+$P$4) -> 10700 | S36: =$O36*E36*(1+$P$4) -> 10700 | T36: =$O36*F36*(1+$P$4) -> 10700 | U36: =$O36*G36*(1+$P$4) -> 10700 | V36: =$O36*H36*(1+$P$4) -> 10700 | W36: =$O36*I36*(1+$P$4) -> 10700 | ... AA36: =$O36*M36*(1+$P$4) -> 10700 | AB36: =SUM(P36:AA36) -> 128400 | AC36: 1 | AD36: =$AC36*P36*(1+$AD$4) -> 11342 | AE36: =$AC36*Q36*(1+$AD$4) -> 11342 | AF36: =$AC36*R36*(1+$AD$4) -> 11342 | AG36: =$AC36*S36*(1+$AD$4) -> 11342 | AH36: =$AC36*T36*(1+$AD$4) -> 11342 | AI36: =$AC36*U36*(1+$AD$4) -> 11342 | AJ36: =$AC36*V36*(1+$AD$4) -> 11342 | AK36: =$AC36*W36*(1+$AD$4) -> 11342 | ... AO36: =$AC36*AA36*(1+$AD$4) -> 11342 | AP36: =SUM(AD36:AO36) -> 136104 | AQ36: 1 | AR36: =$AQ36*AD36*(1+$AR$4) -> 12022.52 | AS36: =$AQ36*AE36*(1+$AR$4) -> 12022.52 | AT36: =$AQ36*AF36*(1+$AR$4) -> 12022.52 | AU36: =$AQ36*AG36*(1+$AR$4) -> 12022.52 | AV36: =$AQ36*AH36*(1+$AR$4) -> 12022.52 | AW36: =$AQ36*AI36*(1+$AR$4) -> 12022.52 | AX36: =$AQ36*AJ36*(1+$AR$4) -> 12022.52 | AY36: =$AQ36*AK36*(1+$AR$4) -> 12022.52 | ... BC36: =$AQ36*AO36*(1+$AR$4) -> 12022.52 | BD36: =SUM(AR36:BC36) -> 144270.24 | BE36: 1 | BF36: =$BE36*AR36*(1+$BF$4) -> 12743.871 | BG36: =$BE36*AS36*(1+$BF$4) -> 12743.871 | BH36: =$BE36*AT36*(1+$BF$4) -> 12743.871 | BI36: =$BE36*AU36*(1+$BF$4) -> 12743.871 | BJ36: =$BE36*AV36*(1+$BF$4) -> 12743.871 | BK36: =$BE36*AW36*(1+$BF$4) -> 12743.871 | BL36: =$BE36*AX36*(1+$BF$4) -> 12743.871 | BM36: =$BE36*AY36*(1+$BF$4) -> 12743.871 | ... BQ36: =$BE36*BC36*(1+$BF$4) -> 12743.871 | BR36: =SUM(BF36:BQ36) -> 152926.45 | BS36: 1 | BT36: =$BS36*BF36*(1+$BT$4) -> 13508.503 | BU36: =$BS36*BG36*(1+$BT$4) -> 13508.503 | BV36: =$BS36*BH36*(1+$BT$4) -> 13508.503 | BW36: =$BS36*BI36*(1+$BT$4) -> 13508.503 | BX36: =$BS36*BJ36*(1+$BT$4) -> 13508.503 | BY36: =$BS36*BK36*(1+$BT$4) -> 13508.503 | BZ36: =$BS36*BL36*(1+$BT$4) -> 13508.503 | CA36: =$BS36*BM36*(1+$BT$4) -> 13508.503 | ... CE36: =$BS36*BQ36*(1+$BT$4) -> 13508.503 | CF36: =SUM(BT36:CE36) -> 162102.04 | CG36: 1 | CH36: =$CG36*BT36*(1+$CH$4) -> 14319.014 | CI36: =$CG36*BU36*(1+$CH$4) -> 14319.014 | CJ36: =$CG36*BV36*(1+$CH$4) -> 14319.014 | CK36: =$CG36*BW36*(1+$CH$4) -> 14319.014 | CL36: =$CG36*BX36*(1+$CH$4) -> 14319.014 | CM36: =$CG36*BY36*(1+$CH$4) -> 14319.014 | CN36: =$CG36*BZ36*(1+$CH$4) -> 14319.014 | CO36: =$CG36*CA36*(1+$CH$4) -> 14319.014 | ... CS36: =$CG36*CE36*(1+$CH$4) -> 14319.014 | CT36: =SUM(CH36:CS36) -> 171828.16 | CU36: 1 | CV36: =$CU36*CH36*(1+$CV$4) -> 15178.155 | CW36: =$CU36*CI36*(1+$CV$4) -> 15178.155 | CX36: =$CU36*CJ36*(1+$CV$4) -> 15178.155 | CY36: =$CU36*CK36*(1+$CV$4) -> 15178.155 | CZ36: =$CU36*CL36*(1+$CV$4) -> 15178.155 | DA36: =$CU36*CM36*(1+$CV$4) -> 15178.155 | DB36: =$CU36*CN36*(1+$CV$4) -> 15178.155 | DC36: =$CU36*CO36*(1+$CV$4) -> 15178.155 | ... DG36: =$CU36*CS36*(1+$CV$4) -> 15178.155 | DH36: =SUM(CV36:DG36) -> 182137.85 | DI36: 1 | DJ36: =$DI36*CV36*(1+$DJ$4) -> 16088.844 | DK36: =$DI36*CW36*(1+$DJ$4) -> 16088.844 | DL36: =$DI36*CX36*(1+$DJ$4) -> 16088.844 | DM36: =$DI36*CY36*(1+$DJ$4) -> 16088.844 | DN36: =$DI36*CZ36*(1+$DJ$4) -> 16088.844 | DO36: =$DI36*DA36*(1+$DJ$4) -> 16088.844 | DP36: =$DI36*DB36*(1+$DJ$4) -> 16088.844 | DQ36: =$DI36*DC36*(1+$DJ$4) -> 16088.844 | ... DU36: =$DI36*DG36*(1+$DJ$4) -> 16088.844 | DV36: =SUM(DJ36:DU36) -> 193066.13 | DW36: 1 | DX36: =$DW36*DJ36*(1+$DX$4) -> 17054.174 | DY36: =$DW36*DK36*(1+$DX$4) -> 17054.174 | DZ36: =$DW36*DL36*(1+$DX$4) -> 17054.174 | EA36: =$DW36*DM36*(1+$DX$4) -> 17054.174 | EB36: =$DW36*DN36*(1+$DX$4) -> 17054.174 | EC36: =$DW36*DO36*(1+$DX$4) -> 17054.174 | ED36: =$DW36*DP36*(1+$DX$4) -> 17054.174 | EE36: =$DW36*DQ36*(1+$DX$4) -> 17054.174 | ... EI36: =$DW36*DU36*(1+$DX$4) -> 17054.174 | EJ36: =SUM(DX36:EI36) -> 204650.09
A37: Supervisor de producción | B37: 10000 | C37: =B37 -> 10000 | D37: =C37 -> 10000 | E37: =D37 -> 10000 | F37: =E37 -> 10000 | G37: =F37 -> 10000 | H37: =G37 -> 10000 | I37: =H37 -> 10000 | J37: =I37 -> 10000 | ... M37: =L37 -> 10000 | N37: =SUM(B37:M37) -> 120000 | O37: 1 | P37: =$O37*B37*(1+$P$4) -> 10700 | Q37: =$O37*C37*(1+$P$4) -> 10700 | R37: =$O37*D37*(1+$P$4) -> 10700 | S37: =$O37*E37*(1+$P$4) -> 10700 | T37: =$O37*F37*(1+$P$4) -> 10700 | U37: =$O37*G37*(1+$P$4) -> 10700 | V37: =$O37*H37*(1+$P$4) -> 10700 | W37: =$O37*I37*(1+$P$4) -> 10700 | ... AA37: =$O37*M37*(1+$P$4) -> 10700 | AB37: =SUM(P37:AA37) -> 128400 | AC37: 1 | AD37: =$AC37*P37*(1+$AD$4) -> 11342 | AE37: =$AC37*Q37*(1+$AD$4) -> 11342 | AF37: =$AC37*R37*(1+$AD$4) -> 11342 | AG37: =$AC37*S37*(1+$AD$4) -> 11342 | AH37: =$AC37*T37*(1+$AD$4) -> 11342 | AI37: =$AC37*U37*(1+$AD$4) -> 11342 | AJ37: =$AC37*V37*(1+$AD$4) -> 11342 | AK37: =$AC37*W37*(1+$AD$4) -> 11342 | ... AO37: =$AC37*AA37*(1+$AD$4) -> 11342 | AP37: =SUM(AD37:AO37) -> 136104 | AQ37: 1 | AR37: =$AQ37*AD37*(1+$AR$4) -> 12022.52 | AS37: =$AQ37*AE37*(1+$AR$4) -> 12022.52 | AT37: =$AQ37*AF37*(1+$AR$4) -> 12022.52 | AU37: =$AQ37*AG37*(1+$AR$4) -> 12022.52 | AV37: =$AQ37*AH37*(1+$AR$4) -> 12022.52 | AW37: =$AQ37*AI37*(1+$AR$4) -> 12022.52 | AX37: =$AQ37*AJ37*(1+$AR$4) -> 12022.52 | AY37: =$AQ37*AK37*(1+$AR$4) -> 12022.52 | ... BC37: =$AQ37*AO37*(1+$AR$4) -> 12022.52 | BD37: =SUM(AR37:BC37) -> 144270.24 | BE37: 1 | BF37: =$BE37*AR37*(1+$BF$4) -> 12743.871 | BG37: =$BE37*AS37*(1+$BF$4) -> 12743.871 | BH37: =$BE37*AT37*(1+$BF$4) -> 12743.871 | BI37: =$BE37*AU37*(1+$BF$4) -> 12743.871 | BJ37: =$BE37*AV37*(1+$BF$4) -> 12743.871 | BK37: =$BE37*AW37*(1+$BF$4) -> 12743.871 | BL37: =$BE37*AX37*(1+$BF$4) -> 12743.871 | BM37: =$BE37*AY37*(1+$BF$4) -> 12743.871 | ... BQ37: =$BE37*BC37*(1+$BF$4) -> 12743.871 | BR37: =SUM(BF37:BQ37) -> 152926.45 | BS37: 1 | BT37: =$BS37*BF37*(1+$BT$4) -> 13508.503 | BU37: =$BS37*BG37*(1+$BT$4) -> 13508.503 | BV37: =$BS37*BH37*(1+$BT$4) -> 13508.503 | BW37: =$BS37*BI37*(1+$BT$4) -> 13508.503 | BX37: =$BS37*BJ37*(1+$BT$4) -> 13508.503 | BY37: =$BS37*BK37*(1+$BT$4) -> 13508.503 | BZ37: =$BS37*BL37*(1+$BT$4) -> 13508.503 | CA37: =$BS37*BM37*(1+$BT$4) -> 13508.503 | ... CE37: =$BS37*BQ37*(1+$BT$4) -> 13508.503 | CF37: =SUM(BT37:CE37) -> 162102.04 | CG37: 1 | CH37: =$CG37*BT37*(1+$CH$4) -> 14319.014 | CI37: =$CG37*BU37*(1+$CH$4) -> 14319.014 | CJ37: =$CG37*BV37*(1+$CH$4) -> 14319.014 | CK37: =$CG37*BW37*(1+$CH$4) -> 14319.014 | CL37: =$CG37*BX37*(1+$CH$4) -> 14319.014 | CM37: =$CG37*BY37*(1+$CH$4) -> 14319.014 | CN37: =$CG37*BZ37*(1+$CH$4) -> 14319.014 | CO37: =$CG37*CA37*(1+$CH$4) -> 14319.014 | ... CS37: =$CG37*CE37*(1+$CH$4) -> 14319.014 | CT37: =SUM(CH37:CS37) -> 171828.16 | CU37: 1 | CV37: =$CU37*CH37*(1+$CV$4) -> 15178.155 | CW37: =$CU37*CI37*(1+$CV$4) -> 15178.155 | CX37: =$CU37*CJ37*(1+$CV$4) -> 15178.155 | CY37: =$CU37*CK37*(1+$CV$4) -> 15178.155 | CZ37: =$CU37*CL37*(1+$CV$4) -> 15178.155 | DA37: =$CU37*CM37*(1+$CV$4) -> 15178.155 | DB37: =$CU37*CN37*(1+$CV$4) -> 15178.155 | DC37: =$CU37*CO37*(1+$CV$4) -> 15178.155 | ... DG37: =$CU37*CS37*(1+$CV$4) -> 15178.155 | DH37: =SUM(CV37:DG37) -> 182137.85 | DI37: 1 | DJ37: =$DI37*CV37*(1+$DJ$4) -> 16088.844 | DK37: =$DI37*CW37*(1+$DJ$4) -> 16088.844 | DL37: =$DI37*CX37*(1+$DJ$4) -> 16088.844 | DM37: =$DI37*CY37*(1+$DJ$4) -> 16088.844 | DN37: =$DI37*CZ37*(1+$DJ$4) -> 16088.844 | DO37: =$DI37*DA37*(1+$DJ$4) -> 16088.844 | DP37: =$DI37*DB37*(1+$DJ$4) -> 16088.844 | DQ37: =$DI37*DC37*(1+$DJ$4) -> 16088.844 | ... DU37: =$DI37*DG37*(1+$DJ$4) -> 16088.844 | DV37: =SUM(DJ37:DU37) -> 193066.13 | DW37: 1 | DX37: =$DW37*DJ37*(1+$DX$4) -> 17054.174 | DY37: =$DW37*DK37*(1+$DX$4) -> 17054.174 | DZ37: =$DW37*DL37*(1+$DX$4) -> 17054.174 | EA37: =$DW37*DM37*(1+$DX$4) -> 17054.174 | EB37: =$DW37*DN37*(1+$DX$4) -> 17054.174 | EC37: =$DW37*DO37*(1+$DX$4) -> 17054.174 | ED37: =$DW37*DP37*(1+$DX$4) -> 17054.174 | EE37: =$DW37*DQ37*(1+$DX$4) -> 17054.174 | ... EI37: =$DW37*DU37*(1+$DX$4) -> 17054.174 | EJ37: =SUM(DX37:EI37) -> 204650.09
A38: Diseñador gráfico | B38: 12000 | C38: =B38 -> 12000 | D38: =C38 -> 12000 | E38: =D38 -> 12000 | F38: =E38 -> 12000 | G38: =F38 -> 12000 | H38: =G38 -> 12000 | I38: =H38 -> 12000 | J38: =I38 -> 12000 | ... M38: =L38 -> 12000 | N38: =SUM(B38:M38) -> 144000 | O38: 1 | P38: =$O38*B38*(1+$P$4) -> 12840 | Q38: =$O38*C38*(1+$P$4) -> 12840 | R38: =$O38*D38*(1+$P$4) -> 12840 | S38: =$O38*E38*(1+$P$4) -> 12840 | T38: =$O38*F38*(1+$P$4) -> 12840 | U38: =$O38*G38*(1+$P$4) -> 12840 | V38: =$O38*H38*(1+$P$4) -> 12840 | W38: =$O38*I38*(1+$P$4) -> 12840 | ... AA38: =$O38*M38*(1+$P$4) -> 12840 | AB38: =SUM(P38:AA38) -> 154080 | AC38: 1 | AD38: =$AC38*P38*(1+$AD$4) -> 13610.4 | AE38: =$AC38*Q38*(1+$AD$4) -> 13610.4 | AF38: =$AC38*R38*(1+$AD$4) -> 13610.4 | AG38: =$AC38*S38*(1+$AD$4) -> 13610.4 | AH38: =$AC38*T38*(1+$AD$4) -> 13610.4 | AI38: =$AC38*U38*(1+$AD$4) -> 13610.4 | AJ38: =$AC38*V38*(1+$AD$4) -> 13610.4 | AK38: =$AC38*W38*(1+$AD$4) -> 13610.4 | ... AO38: =$AC38*AA38*(1+$AD$4) -> 13610.4 | AP38: =SUM(AD38:AO38) -> 163324.8 | AQ38: 1 | AR38: =$AQ38*AD38*(1+$AR$4) -> 14427.024 | AS38: =$AQ38*AE38*(1+$AR$4) -> 14427.024 | AT38: =$AQ38*AF38*(1+$AR$4) -> 14427.024 | AU38: =$AQ38*AG38*(1+$AR$4) -> 14427.024 | AV38: =$AQ38*AH38*(1+$AR$4) -> 14427.024 | AW38: =$AQ38*AI38*(1+$AR$4) -> 14427.024 | AX38: =$AQ38*AJ38*(1+$AR$4) -> 14427.024 | AY38: =$AQ38*AK38*(1+$AR$4) -> 14427.024 | ... BC38: =$AQ38*AO38*(1+$AR$4) -> 14427.024 | BD38: =SUM(AR38:BC38) -> 173124.29 | BE38: 1 | BF38: =$BE38*AR38*(1+$BF$4) -> 15292.645 | BG38: =$BE38*AS38*(1+$BF$4) -> 15292.645 | BH38: =$BE38*AT38*(1+$BF$4) -> 15292.645 | BI38: =$BE38*AU38*(1+$BF$4) -> 15292.645 | BJ38: =$BE38*AV38*(1+$BF$4) -> 15292.645 | BK38: =$BE38*AW38*(1+$BF$4) -> 15292.645 | BL38: =$BE38*AX38*(1+$BF$4) -> 15292.645 | BM38: =$BE38*AY38*(1+$BF$4) -> 15292.645 | ... BQ38: =$BE38*BC38*(1+$BF$4) -> 15292.645 | BR38: =SUM(BF38:BQ38) -> 183511.75 | BS38: 1 | BT38: =$BS38*BF38*(1+$BT$4) -> 16210.204 | BU38: =$BS38*BG38*(1+$BT$4) -> 16210.204 | BV38: =$BS38*BH38*(1+$BT$4) -> 16210.204 | BW38: =$BS38*BI38*(1+$BT$4) -> 16210.204 | BX38: =$BS38*BJ38*(1+$BT$4) -> 16210.204 | BY38: =$BS38*BK38*(1+$BT$4) -> 16210.204 | BZ38: =$BS38*BL38*(1+$BT$4) -> 16210.204 | CA38: =$BS38*BM38*(1+$BT$4) -> 16210.204 | ... CE38: =$BS38*BQ38*(1+$BT$4) -> 16210.204 | CF38: =SUM(BT38:CE38) -> 194522.45 | CG38: 1 | CH38: =$CG38*BT38*(1+$CH$4) -> 17182.816 | CI38: =$CG38*BU38*(1+$CH$4) -> 17182.816 | CJ38: =$CG38*BV38*(1+$CH$4) -> 17182.816 | CK38: =$CG38*BW38*(1+$CH$4) -> 17182.816 | CL38: =$CG38*BX38*(1+$CH$4) -> 17182.816 | CM38: =$CG38*BY38*(1+$CH$4) -> 17182.816 | CN38: =$CG38*BZ38*(1+$CH$4) -> 17182.816 | CO38: =$CG38*CA38*(1+$CH$4) -> 17182.816 | ... CS38: =$CG38*CE38*(1+$CH$4) -> 17182.816 | CT38: =SUM(CH38:CS38) -> 206193.8 | CU38: 1 | CV38: =$CU38*CH38*(1+$CV$4) -> 18213.785 | CW38: =$CU38*CI38*(1+$CV$4) -> 18213.785 | CX38: =$CU38*CJ38*(1+$CV$4) -> 18213.785 | CY38: =$CU38*CK38*(1+$CV$4) -> 18213.785 | CZ38: =$CU38*CL38*(1+$CV$4) -> 18213.785 | DA38: =$CU38*CM38*(1+$CV$4) -> 18213.785 | DB38: =$CU38*CN38*(1+$CV$4) -> 18213.785 | DC38: =$CU38*CO38*(1+$CV$4) -> 18213.785 | ... DG38: =$CU38*CS38*(1+$CV$4) -> 18213.785 | DH38: =SUM(CV38:DG38) -> 218565.42 | DI38: 1 | DJ38: =$DI38*CV38*(1+$DJ$4) -> 19306.613 | DK38: =$DI38*CW38*(1+$DJ$4) -> 19306.613 | DL38: =$DI38*CX38*(1+$DJ$4) -> 19306.613 | DM38: =$DI38*CY38*(1+$DJ$4) -> 19306.613 | DN38: =$DI38*CZ38*(1+$DJ$4) -> 19306.613 | DO38: =$DI38*DA38*(1+$DJ$4) -> 19306.613 | DP38: =$DI38*DB38*(1+$DJ$4) -> 19306.613 | DQ38: =$DI38*DC38*(1+$DJ$4) -> 19306.613 | ... DU38: =$DI38*DG38*(1+$DJ$4) -> 19306.613 | DV38: =SUM(DJ38:DU38) -> 231679.35 | DW38: 1 | DX38: =$DW38*DJ38*(1+$DX$4) -> 20465.009 | DY38: =$DW38*DK38*(1+$DX$4) -> 20465.009 | DZ38: =$DW38*DL38*(1+$DX$4) -> 20465.009 | EA38: =$DW38*DM38*(1+$DX$4) -> 20465.009 | EB38: =$DW38*DN38*(1+$DX$4) -> 20465.009 | EC38: =$DW38*DO38*(1+$DX$4) -> 20465.009 | ED38: =$DW38*DP38*(1+$DX$4) -> 20465.009 | EE38: =$DW38*DQ38*(1+$DX$4) -> 20465.009 | ... EI38: =$DW38*DU38*(1+$DX$4) -> 20465.009 | EJ38: =SUM(DX38:EI38) -> 245580.11
A39: Inspector de calidad | B39: 8000 | C39: =B39 -> 8000 | D39: =C39 -> 8000 | E39: =D39 -> 8000 | F39: =E39 -> 8000 | G39: =F39 -> 8000 | H39: =G39 -> 8000 | I39: =H39 -> 8000 | J39: =I39 -> 8000 | ... M39: =L39 -> 8000 | N39: =SUM(B39:M39) -> 96000 | O39: 1 | P39: =$O39*B39*(1+$P$4) -> 8560 | Q39: =$O39*C39*(1+$P$4) -> 8560 | R39: =$O39*D39*(1+$P$4) -> 8560 | S39: =$O39*E39*(1+$P$4) -> 8560 | T39: =$O39*F39*(1+$P$4) -> 8560 | U39: =$O39*G39*(1+$P$4) -> 8560 | V39: =$O39*H39*(1+$P$4) -> 8560 | W39: =$O39*I39*(1+$P$4) -> 8560 | ... AA39: =$O39*M39*(1+$P$4) -> 8560 | AB39: =SUM(P39:AA39) -> 102720 | AC39: 1 | AD39: =$AC39*P39*(1+$AD$4) -> 9073.6 | AE39: =$AC39*Q39*(1+$AD$4) -> 9073.6 | AF39: =$AC39*R39*(1+$AD$4) -> 9073.6 | AG39: =$AC39*S39*(1+$AD$4) -> 9073.6 | AH39: =$AC39*T39*(1+$AD$4) -> 9073.6 | AI39: =$AC39*U39*(1+$AD$4) -> 9073.6 | AJ39: =$AC39*V39*(1+$AD$4) -> 9073.6 | AK39: =$AC39*W39*(1+$AD$4) -> 9073.6 | ... AO39: =$AC39*AA39*(1+$AD$4) -> 9073.6 | AP39: =SUM(AD39:AO39) -> 108883.2 | AQ39: 1 | AR39: =$AQ39*AD39*(1+$AR$4) -> 9618.016 | AS39: =$AQ39*AE39*(1+$AR$4) -> 9618.016 | AT39: =$AQ39*AF39*(1+$AR$4) -> 9618.016 | AU39: =$AQ39*AG39*(1+$AR$4) -> 9618.016 | AV39: =$AQ39*AH39*(1+$AR$4) -> 9618.016 | AW39: =$AQ39*AI39*(1+$AR$4) -> 9618.016 | AX39: =$AQ39*AJ39*(1+$AR$4) -> 9618.016 | AY39: =$AQ39*AK39*(1+$AR$4) -> 9618.016 | ... BC39: =$AQ39*AO39*(1+$AR$4) -> 9618.016 | BD39: =SUM(AR39:BC39) -> 115416.19 | BE39: 1 | BF39: =$BE39*AR39*(1+$BF$4) -> 10195.097 | BG39: =$BE39*AS39*(1+$BF$4) -> 10195.097 | BH39: =$BE39*AT39*(1+$BF$4) -> 10195.097 | BI39: =$BE39*AU39*(1+$BF$4) -> 10195.097 | BJ39: =$BE39*AV39*(1+$BF$4) -> 10195.097 | BK39: =$BE39*AW39*(1+$BF$4) -> 10195.097 | BL39: =$BE39*AX39*(1+$BF$4) -> 10195.097 | BM39: =$BE39*AY39*(1+$BF$4) -> 10195.097 | ... BQ39: =$BE39*BC39*(1+$BF$4) -> 10195.097 | BR39: =SUM(BF39:BQ39) -> 122341.16 | BS39: 1 | BT39: =$BS39*BF39*(1+$BT$4) -> 10806.803 | BU39: =$BS39*BG39*(1+$BT$4) -> 10806.803 | BV39: =$BS39*BH39*(1+$BT$4) -> 10806.803 | BW39: =$BS39*BI39*(1+$BT$4) -> 10806.803 | BX39: =$BS39*BJ39*(1+$BT$4) -> 10806.803 | BY39: =$BS39*BK39*(1+$BT$4) -> 10806.803 | BZ39: =$BS39*BL39*(1+$BT$4) -> 10806.803 | CA39: =$BS39*BM39*(1+$BT$4) -> 10806.803 | ... CE39: =$BS39*BQ39*(1+$BT$4) -> 10806.803 | CF39: =SUM(BT39:CE39) -> 129681.63 | CG39: 1 | CH39: =$CG39*BT39*(1+$CH$4) -> 11455.211 | CI39: =$CG39*BU39*(1+$CH$4) -> 11455.211 | CJ39: =$CG39*BV39*(1+$CH$4) -> 11455.211 | CK39: =$CG39*BW39*(1+$CH$4) -> 11455.211 | CL39: =$CG39*BX39*(1+$CH$4) -> 11455.211 | CM39: =$CG39*BY39*(1+$CH$4) -> 11455.211 | CN39: =$CG39*BZ39*(1+$CH$4) -> 11455.211 | CO39: =$CG39*CA39*(1+$CH$4) -> 11455.211 | ... CS39: =$CG39*CE39*(1+$CH$4) -> 11455.211 | CT39: =SUM(CH39:CS39) -> 137462.53 | CU39: 1 | CV39: =$CU39*CH39*(1+$CV$4) -> 12142.524 | CW39: =$CU39*CI39*(1+$CV$4) -> 12142.524 | CX39: =$CU39*CJ39*(1+$CV$4) -> 12142.524 | CY39: =$CU39*CK39*(1+$CV$4) -> 12142.524 | CZ39: =$CU39*CL39*(1+$CV$4) -> 12142.524 | DA39: =$CU39*CM39*(1+$CV$4) -> 12142.524 | DB39: =$CU39*CN39*(1+$CV$4) -> 12142.524 | DC39: =$CU39*CO39*(1+$CV$4) -> 12142.524 | ... DG39: =$CU39*CS39*(1+$CV$4) -> 12142.524 | DH39: =SUM(CV39:DG39) -> 145710.28 | DI39: 1 | DJ39: =$DI39*CV39*(1+$DJ$4) -> 12871.075 | DK39: =$DI39*CW39*(1+$DJ$4) -> 12871.075 | DL39: =$DI39*CX39*(1+$DJ$4) -> 12871.075 | DM39: =$DI39*CY39*(1+$DJ$4) -> 12871.075 | DN39: =$DI39*CZ39*(1+$DJ$4) -> 12871.075 | DO39: =$DI39*DA39*(1+$DJ$4) -> 12871.075 | DP39: =$DI39*DB39*(1+$DJ$4) -> 12871.075 | DQ39: =$DI39*DC39*(1+$DJ$4) -> 12871.075 | ... DU39: =$DI39*DG39*(1+$DJ$4) -> 12871.075 | DV39: =SUM(DJ39:DU39) -> 154452.9 | DW39: 1 | DX39: =$DW39*DJ39*(1+$DX$4) -> 13643.34 | DY39: =$DW39*DK39*(1+$DX$4) -> 13643.34 | DZ39: =$DW39*DL39*(1+$DX$4) -> 13643.34 | EA39: =$DW39*DM39*(1+$DX$4) -> 13643.34 | EB39: =$DW39*DN39*(1+$DX$4) -> 13643.34 | EC39: =$DW39*DO39*(1+$DX$4) -> 13643.34 | ED39: =$DW39*DP39*(1+$DX$4) -> 13643.34 | EE39: =$DW39*DQ39*(1+$DX$4) -> 13643.34 | ... EI39: =$DW39*DU39*(1+$DX$4) -> 13643.34 | EJ39: =SUM(DX39:EI39) -> 163720.07
A40: Personal de limpieza | B40: 6000 | C40: =B40 -> 6000 | D40: =C40 -> 6000 | E40: =D40 -> 6000 | F40: =E40 -> 6000 | G40: =F40 -> 6000 | H40: =G40 -> 6000 | I40: =H40 -> 6000 | J40: =I40 -> 6000 | ... M40: =L40 -> 6000 | N40: =SUM(B40:M40) -> 72000 | O40: 1 | P40: =$O40*B40*(1+$P$4) -> 6420 | Q40: =$O40*C40*(1+$P$4) -> 6420 | R40: =$O40*D40*(1+$P$4) -> 6420 | S40: =$O40*E40*(1+$P$4) -> 6420 | T40: =$O40*F40*(1+$P$4) -> 6420 | U40: =$O40*G40*(1+$P$4) -> 6420 | V40: =$O40*H40*(1+$P$4) -> 6420 | W40: =$O40*I40*(1+$P$4) -> 6420 | ... AA40: =$O40*M40*(1+$P$4) -> 6420 | AB40: =SUM(P40:AA40) -> 77040 | AC40: 1 | AD40: =$AC40*P40*(1+$AD$4) -> 6805.2 | AE40: =$AC40*Q40*(1+$AD$4) -> 6805.2 | AF40: =$AC40*R40*(1+$AD$4) -> 6805.2 | AG40: =$AC40*S40*(1+$AD$4) -> 6805.2 | AH40: =$AC40*T40*(1+$AD$4) -> 6805.2 | AI40: =$AC40*U40*(1+$AD$4) -> 6805.2 | AJ40: =$AC40*V40*(1+$AD$4) -> 6805.2 | AK40: =$AC40*W40*(1+$AD$4) -> 6805.2 | ... AO40: =$AC40*AA40*(1+$AD$4) -> 6805.2 | AP40: =SUM(AD40:AO40) -> 81662.4 | AQ40: 1 | AR40: =$AQ40*AD40*(1+$AR$4) -> 7213.512 | AS40: =$AQ40*AE40*(1+$AR$4) -> 7213.512 | AT40: =$AQ40*AF40*(1+$AR$4) -> 7213.512 | AU40: =$AQ40*AG40*(1+$AR$4) -> 7213.512 | AV40: =$AQ40*AH40*(1+$AR$4) -> 7213.512 | AW40: =$AQ40*AI40*(1+$AR$4) -> 7213.512 | AX40: =$AQ40*AJ40*(1+$AR$4) -> 7213.512 | AY40: =$AQ40*AK40*(1+$AR$4) -> 7213.512 | ... BC40: =$AQ40*AO40*(1+$AR$4) -> 7213.512 | BD40: =SUM(AR40:BC40) -> 86562.144 | BE40: 1 | BF40: =$BE40*AR40*(1+$BF$4) -> 7646.3227 | BG40: =$BE40*AS40*(1+$BF$4) -> 7646.3227 | BH40: =$BE40*AT40*(1+$BF$4) -> 7646.3227 | BI40: =$BE40*AU40*(1+$BF$4) -> 7646.3227 | BJ40: =$BE40*AV40*(1+$BF$4) -> 7646.3227 | BK40: =$BE40*AW40*(1+$BF$4) -> 7646.3227 | BL40: =$BE40*AX40*(1+$BF$4) -> 7646.3227 | BM40: =$BE40*AY40*(1+$BF$4) -> 7646.3227 | ... BQ40: =$BE40*BC40*(1+$BF$4) -> 7646.3227 | BR40: =SUM(BF40:BQ40) -> 91755.873 | BS40: 1 | BT40: =$BS40*BF40*(1+$BT$4) -> 8105.1021 | BU40: =$BS40*BG40*(1+$BT$4) -> 8105.1021 | BV40: =$BS40*BH40*(1+$BT$4) -> 8105.1021 | BW40: =$BS40*BI40*(1+$BT$4) -> 8105.1021 | BX40: =$BS40*BJ40*(1+$BT$4) -> 8105.1021 | BY40: =$BS40*BK40*(1+$BT$4) -> 8105.1021 | BZ40: =$BS40*BL40*(1+$BT$4) -> 8105.1021 | CA40: =$BS40*BM40*(1+$BT$4) -> 8105.1021 | ... CE40: =$BS40*BQ40*(1+$BT$4) -> 8105.1021 | CF40: =SUM(BT40:CE40) -> 97261.225 | CG40: 1 | CH40: =$CG40*BT40*(1+$CH$4) -> 8591.4082 | CI40: =$CG40*BU40*(1+$CH$4) -> 8591.4082 | CJ40: =$CG40*BV40*(1+$CH$4) -> 8591.4082 | CK40: =$CG40*BW40*(1+$CH$4) -> 8591.4082 | CL40: =$CG40*BX40*(1+$CH$4) -> 8591.4082 | CM40: =$CG40*BY40*(1+$CH$4) -> 8591.4082 | CN40: =$CG40*BZ40*(1+$CH$4) -> 8591.4082 | CO40: =$CG40*CA40*(1+$CH$4) -> 8591.4082 | ... CS40: =$CG40*CE40*(1+$CH$4) -> 8591.4082 | CT40: =SUM(CH40:CS40) -> 103096.9 | CU40: 1 | CV40: =$CU40*CH40*(1+$CV$4) -> 9106.8927 | CW40: =$CU40*CI40*(1+$CV$4) -> 9106.8927 | CX40: =$CU40*CJ40*(1+$CV$4) -> 9106.8927 | CY40: =$CU40*CK40*(1+$CV$4) -> 9106.8927 | CZ40: =$CU40*CL40*(1+$CV$4) -> 9106.8927 | DA40: =$CU40*CM40*(1+$CV$4) -> 9106.8927 | DB40: =$CU40*CN40*(1+$CV$4) -> 9106.8927 | DC40: =$CU40*CO40*(1+$CV$4) -> 9106.8927 | ... DG40: =$CU40*CS40*(1+$CV$4) -> 9106.8927 | DH40: =SUM(CV40:DG40) -> 109282.71 | DI40: 1 | DJ40: =$DI40*CV40*(1+$DJ$4) -> 9653.3063 | DK40: =$DI40*CW40*(1+$DJ$4) -> 9653.3063 | DL40: =$DI40*CX40*(1+$DJ$4) -> 9653.3063 | DM40: =$DI40*CY40*(1+$DJ$4) -> 9653.3063 | DN40: =$DI40*CZ40*(1+$DJ$4) -> 9653.3063 | DO40: =$DI40*DA40*(1+$DJ$4) -> 9653.3063 | DP40: =$DI40*DB40*(1+$DJ$4) -> 9653.3063 | DQ40: =$DI40*DC40*(1+$DJ$4) -> 9653.3063 | ... DU40: =$DI40*DG40*(1+$DJ$4) -> 9653.3063 | DV40: =SUM(DJ40:DU40) -> 115839.68 | DW40: 1 | DX40: =$DW40*DJ40*(1+$DX$4) -> 10232.505 | DY40: =$DW40*DK40*(1+$DX$4) -> 10232.505 | DZ40: =$DW40*DL40*(1+$DX$4) -> 10232.505 | EA40: =$DW40*DM40*(1+$DX$4) -> 10232.505 | EB40: =$DW40*DN40*(1+$DX$4) -> 10232.505 | EC40: =$DW40*DO40*(1+$DX$4) -> 10232.505 | ED40: =$DW40*DP40*(1+$DX$4) -> 10232.505 | EE40: =$DW40*DQ40*(1+$DX$4) -> 10232.505 | ... EI40: =$DW40*DU40*(1+$DX$4) -> 10232.505 | EJ40: =SUM(DX40:EI40) -> 122790.06
A41: 2. Gastos de operación | B41: =B42+B49+B52 -> 63900 | C41: =C42+C49+C52 -> 63900 | D41: =D42+D49+D52 -> 63900 | E41: =E42+E49+E52 -> 63900 | F41: =F42+F49+F52 -> 63900 | G41: =G42+G49+G52 -> 63900 | H41: =H42+H49+H52 -> 63900 | I41: =I42+I49+I52 -> 63900 | ... M41: =M42+M49+M52 -> 63900 | N41: =SUM(B41:M41) -> 766800 | P41: =P42+P49+P52 -> 68694 | Q41: =Q42+Q49+Q52 -> 68694 | R41: =R42+R49+R52 -> 68694 | S41: =S42+S49+S52 -> 68694 | T41: =T42+T49+T52 -> 68694 | U41: =U42+U49+U52 -> 68694 | V41: =V42+V49+V52 -> 68694 | W41: =W42+W49+W52 -> 68694 | ... AA41: =AA42+AA49+AA52 -> 68694 | AB41: =SUM(P41:AA41) -> 824328 | AD41: =AD42+AD49+AD52 -> 73399.753 | AE41: =AE42+AE49+AE52 -> 73399.753 | AF41: =AF42+AF49+AF52 -> 73399.753 | AG41: =AG42+AG49+AG52 -> 73399.753 | AH41: =AH42+AH49+AH52 -> 73399.753 | AI41: =AI42+AI49+AI52 -> 73399.753 | AJ41: =AJ42+AJ49+AJ52 -> 73399.753 | AK41: =AK42+AK49+AK52 -> 73399.753 | ... AO41: =AO42+AO49+AO52 -> 73399.753 | AP41: =SUM(AD41:AO41) -> 880797.04 | AR41: =AR42+AR49+AR52 -> 78453.856 | AS41: =AS42+AS49+AS52 -> 78453.856 | AT41: =AT42+AT49+AT52 -> 78453.856 | AU41: =AU42+AU49+AU52 -> 78453.856 | AV41: =AV42+AV49+AV52 -> 78453.856 | AW41: =AW42+AW49+AW52 -> 78453.856 | AX41: =AX42+AX49+AX52 -> 78453.856 | AY41: =AY42+AY49+AY52 -> 78453.856 | ... BC41: =BC42+BC49+BC52 -> 78453.856 | BD41: =SUM(AR41:BC41) -> 941446.27 | BF41: =BF42+BF49+BF52 -> 83884.668 | BG41: =BG42+BG49+BG52 -> 83884.668 | BH41: =BH42+BH49+BH52 -> 83884.668 | BI41: =BI42+BI49+BI52 -> 83884.668 | BJ41: =BJ42+BJ49+BJ52 -> 83884.668 | BK41: =BK42+BK49+BK52 -> 83884.668 | BL41: =BL42+BL49+BL52 -> 83884.668 | BM41: =BM42+BM49+BM52 -> 83884.668 | ... BQ41: =BQ42+BQ49+BQ52 -> 83884.668 | BR41: =SUM(BF41:BQ41) -> 1006616 | BT41: =BT42+BT49+BT52 -> 89723.094 | BU41: =BU42+BU49+BU52 -> 89723.094 | BV41: =BV42+BV49+BV52 -> 89723.094 | BW41: =BW42+BW49+BW52 -> 89723.094 | BX41: =BX42+BX49+BX52 -> 89723.094 | BY41: =BY42+BY49+BY52 -> 89723.094 | BZ41: =BZ42+BZ49+BZ52 -> 89723.094 | CA41: =CA42+CA49+CA52 -> 89723.094 | ... CE41: =CE42+CE49+CE52 -> 89723.094 | CF41: =SUM(BT41:CE41) -> 1076677.1 | CH41: =CH42+CH49+CH52 -> 96002.83 | CI41: =CI42+CI49+CI52 -> 96002.83 | CJ41: =CJ42+CJ49+CJ52 -> 96002.83 | CK41: =CK42+CK49+CK52 -> 96002.83 | CL41: =CL42+CL49+CL52 -> 96002.83 | CM41: =CM42+CM49+CM52 -> 96002.83 | CN41: =CN42+CN49+CN52 -> 96002.83 | CO41: =CO42+CO49+CO52 -> 96002.83 | ... CS41: =CS42+CS49+CS52 -> 96002.83 | CT41: =SUM(CH41:CS41) -> 1152034 | CV41: =CV42+CV49+CV52 -> 102760.64 | CW41: =CW42+CW49+CW52 -> 102760.64 | CX41: =CX42+CX49+CX52 -> 102760.64 | CY41: =CY42+CY49+CY52 -> 102760.64 | CZ41: =CZ42+CZ49+CZ52 -> 102760.64 | DA41: =DA42+DA49+DA52 -> 102760.64 | DB41: =DB42+DB49+DB52 -> 102760.64 | DC41: =DC42+DC49+DC52 -> 102760.64 | ... DG41: =DG42+DG49+DG52 -> 102760.64 | DH41: =SUM(CV41:DG41) -> 1233127.6 | DJ41: =DJ42+DJ49+DJ52 -> 110036.65 | DK41: =DK42+DK49+DK52 -> 110036.65 | DL41: =DL42+DL49+DL52 -> 110036.65 | DM41: =DM42+DM49+DM52 -> 110036.65 | DN41: =DN42+DN49+DN52 -> 110036.65 | DO41: =DO42+DO49+DO52 -> 110036.65 | DP41: =DP42+DP49+DP52 -> 110036.65 | DQ41: =DQ42+DQ49+DQ52 -> 110036.65 | ... DU41: =DU42+DU49+DU52 -> 110036.65 | DV41: =SUM(DJ41:DU41) -> 1320439.7 | DX41: =DX42+DX49+DX52 -> 117874.69 | DY41: =DY42+DY49+DY52 -> 117874.69 | DZ41: =DZ42+DZ49+DZ52 -> 117874.69 | EA41: =EA42+EA49+EA52 -> 117874.69 | EB41: =EB42+EB49+EB52 -> 117874.69 | EC41: =EC42+EC49+EC52 -> 117874.69 | ED41: =ED42+ED49+ED52 -> 117874.69 | EE41: =EE42+EE49+EE52 -> 117874.69 | ... EI41: =EI42+EI49+EI52 -> 117874.69 | EJ41: =SUM(DX41:EI41) -> 1414496.2
A42: 2.1. Gastos administrativos | B42: =SUM(B43:B48) -> 38900 | C42: =SUM(C43:C48) -> 38900 | D42: =SUM(D43:D48) -> 38900 | E42: =SUM(E43:E48) -> 38900 | F42: =SUM(F43:F48) -> 38900 | G42: =SUM(G43:G48) -> 38900 | H42: =SUM(H43:H48) -> 38900 | I42: =SUM(I43:I48) -> 38900 | ... M42: =SUM(M43:M48) -> 38900 | N42: =SUM(B42:M42) -> 466800 | P42: =SUM(P43:P48) -> 41623 | Q42: =SUM(Q43:Q48) -> 41623 | R42: =SUM(R43:R48) -> 41623 | S42: =SUM(S43:S48) -> 41623 | T42: =SUM(T43:T48) -> 41623 | U42: =SUM(U43:U48) -> 41623 | V42: =SUM(V43:V48) -> 41623 | W42: =SUM(W43:W48) -> 41623 | ... AA42: =SUM(AA43:AA48) -> 41623 | AB42: =SUM(P42:AA42) -> 499476 | AD42: =SUM(AD43:AD48) -> 44120.38 | AE42: =SUM(AE43:AE48) -> 44120.38 | AF42: =SUM(AF43:AF48) -> 44120.38 | AG42: =SUM(AG43:AG48) -> 44120.38 | AH42: =SUM(AH43:AH48) -> 44120.38 | AI42: =SUM(AI43:AI48) -> 44120.38 | AJ42: =SUM(AJ43:AJ48) -> 44120.38 | AK42: =SUM(AK43:AK48) -> 44120.38 | ... AO42: =SUM(AO43:AO48) -> 44120.38 | AP42: =SUM(AD42:AO42) -> 529444.56 | AR42: =SUM(AR43:AR48) -> 46767.603 | AS42: =SUM(AS43:AS48) -> 46767.603 | AT42: =SUM(AT43:AT48) -> 46767.603 | AU42: =SUM(AU43:AU48) -> 46767.603 | AV42: =SUM(AV43:AV48) -> 46767.603 | AW42: =SUM(AW43:AW48) -> 46767.603 | AX42: =SUM(AX43:AX48) -> 46767.603 | AY42: =SUM(AY43:AY48) -> 46767.603 | ... BC42: =SUM(BC43:BC48) -> 46767.603 | BD42: =SUM(AR42:BC42) -> 561211.23 | BF42: =SUM(BF43:BF48) -> 49573.659 | BG42: =SUM(BG43:BG48) -> 49573.659 | BH42: =SUM(BH43:BH48) -> 49573.659 | BI42: =SUM(BI43:BI48) -> 49573.659 | BJ42: =SUM(BJ43:BJ48) -> 49573.659 | BK42: =SUM(BK43:BK48) -> 49573.659 | BL42: =SUM(BL43:BL48) -> 49573.659 | BM42: =SUM(BM43:BM48) -> 49573.659 | ... BQ42: =SUM(BQ43:BQ48) -> 49573.659 | BR42: =SUM(BF42:BQ42) -> 594883.91 | BT42: =SUM(BT43:BT48) -> 52548.079 | BU42: =SUM(BU43:BU48) -> 52548.079 | BV42: =SUM(BV43:BV48) -> 52548.079 | BW42: =SUM(BW43:BW48) -> 52548.079 | BX42: =SUM(BX43:BX48) -> 52548.079 | BY42: =SUM(BY43:BY48) -> 52548.079 | BZ42: =SUM(BZ43:BZ48) -> 52548.079 | CA42: =SUM(CA43:CA48) -> 52548.079 | ... CE42: =SUM(CE43:CE48) -> 52548.079 | CF42: =SUM(BT42:CE42) -> 630576.94 | CH42: =SUM(CH43:CH48) -> 55700.963 | CI42: =SUM(CI43:CI48) -> 55700.963 | CJ42: =SUM(CJ43:CJ48) -> 55700.963 | CK42: =SUM(CK43:CK48) -> 55700.963 | CL42: =SUM(CL43:CL48) -> 55700.963 | CM42: =SUM(CM43:CM48) -> 55700.963 | CN42: =SUM(CN43:CN48) -> 55700.963 | CO42: =SUM(CO43:CO48) -> 55700.963 | ... CS42: =SUM(CS43:CS48) -> 55700.963 | CT42: =SUM(CH42:CS42) -> 668411.56 | CV42: =SUM(CV43:CV48) -> 59043.021 | CW42: =SUM(CW43:CW48) -> 59043.021 | CX42: =SUM(CX43:CX48) -> 59043.021 | CY42: =SUM(CY43:CY48) -> 59043.021 | CZ42: =SUM(CZ43:CZ48) -> 59043.021 | DA42: =SUM(DA43:DA48) -> 59043.021 | DB42: =SUM(DB43:DB48) -> 59043.021 | DC42: =SUM(DC43:DC48) -> 59043.021 | ... DG42: =SUM(DG43:DG48) -> 59043.021 | DH42: =SUM(CV42:DG42) -> 708516.25 | DJ42: =SUM(DJ43:DJ48) -> 62585.602 | DK42: =SUM(DK43:DK48) -> 62585.602 | DL42: =SUM(DL43:DL48) -> 62585.602 | DM42: =SUM(DM43:DM48) -> 62585.602 | DN42: =SUM(DN43:DN48) -> 62585.602 | DO42: =SUM(DO43:DO48) -> 62585.602 | DP42: =SUM(DP43:DP48) -> 62585.602 | DQ42: =SUM(DQ43:DQ48) -> 62585.602 | ... DU42: =SUM(DU43:DU48) -> 62585.602 | DV42: =SUM(DJ42:DU42) -> 751027.23 | DX42: =SUM(DX43:DX48) -> 66340.738 | DY42: =SUM(DY43:DY48) -> 66340.738 | DZ42: =SUM(DZ43:DZ48) -> 66340.738 | EA42: =SUM(EA43:EA48) -> 66340.738 | EB42: =SUM(EB43:EB48) -> 66340.738 | EC42: =SUM(EC43:EC48) -> 66340.738 | ED42: =SUM(ED43:ED48) -> 66340.738 | EE42: =SUM(EE43:EE48) -> 66340.738 | ... EI42: =SUM(EI43:EI48) -> 66340.738 | EJ42: =SUM(DX42:EI42) -> 796088.86
A43: Administrador | B43: 16000 | C43: =B43 -> 16000 | D43: =C43 -> 16000 | E43: =D43 -> 16000 | F43: =E43 -> 16000 | G43: =F43 -> 16000 | H43: =G43 -> 16000 | I43: =H43 -> 16000 | J43: =I43 -> 16000 | ... M43: =L43 -> 16000 | N43: =SUM(B43:M43) -> 192000 | O43: 1 | P43: =$O43*B43*(1+$P$4) -> 17120 | Q43: =$O43*C43*(1+$P$4) -> 17120 | R43: =$O43*D43*(1+$P$4) -> 17120 | S43: =$O43*E43*(1+$P$4) -> 17120 | T43: =$O43*F43*(1+$P$4) -> 17120 | U43: =$O43*G43*(1+$P$4) -> 17120 | V43: =$O43*H43*(1+$P$4) -> 17120 | W43: =$O43*I43*(1+$P$4) -> 17120 | ... AA43: =$O43*M43*(1+$P$4) -> 17120 | AB43: =SUM(P43:AA43) -> 205440 | AC43: 1 | AD43: =$AC43*P43*(1+$AD$4) -> 18147.2 | AE43: =$AC43*Q43*(1+$AD$4) -> 18147.2 | AF43: =$AC43*R43*(1+$AD$4) -> 18147.2 | AG43: =$AC43*S43*(1+$AD$4) -> 18147.2 | AH43: =$AC43*T43*(1+$AD$4) -> 18147.2 | AI43: =$AC43*U43*(1+$AD$4) -> 18147.2 | AJ43: =$AC43*V43*(1+$AD$4) -> 18147.2 | AK43: =$AC43*W43*(1+$AD$4) -> 18147.2 | ... AO43: =$AC43*AA43*(1+$AD$4) -> 18147.2 | AP43: =SUM(AD43:AO43) -> 217766.4 | AQ43: 1 | AR43: =$AQ43*AD43*(1+$AR$4) -> 19236.032 | AS43: =$AQ43*AE43*(1+$AR$4) -> 19236.032 | AT43: =$AQ43*AF43*(1+$AR$4) -> 19236.032 | AU43: =$AQ43*AG43*(1+$AR$4) -> 19236.032 | AV43: =$AQ43*AH43*(1+$AR$4) -> 19236.032 | AW43: =$AQ43*AI43*(1+$AR$4) -> 19236.032 | AX43: =$AQ43*AJ43*(1+$AR$4) -> 19236.032 | AY43: =$AQ43*AK43*(1+$AR$4) -> 19236.032 | ... BC43: =$AQ43*AO43*(1+$AR$4) -> 19236.032 | BD43: =SUM(AR43:BC43) -> 230832.38 | BE43: 1 | BF43: =$BE43*AR43*(1+$BF$4) -> 20390.194 | BG43: =$BE43*AS43*(1+$BF$4) -> 20390.194 | BH43: =$BE43*AT43*(1+$BF$4) -> 20390.194 | BI43: =$BE43*AU43*(1+$BF$4) -> 20390.194 | BJ43: =$BE43*AV43*(1+$BF$4) -> 20390.194 | BK43: =$BE43*AW43*(1+$BF$4) -> 20390.194 | BL43: =$BE43*AX43*(1+$BF$4) -> 20390.194 | BM43: =$BE43*AY43*(1+$BF$4) -> 20390.194 | ... BQ43: =$BE43*BC43*(1+$BF$4) -> 20390.194 | BR43: =SUM(BF43:BQ43) -> 244682.33 | BS43: 1 | BT43: =$BS43*BF43*(1+$BT$4) -> 21613.606 | BU43: =$BS43*BG43*(1+$BT$4) -> 21613.606 | BV43: =$BS43*BH43*(1+$BT$4) -> 21613.606 | BW43: =$BS43*BI43*(1+$BT$4) -> 21613.606 | BX43: =$BS43*BJ43*(1+$BT$4) -> 21613.606 | BY43: =$BS43*BK43*(1+$BT$4) -> 21613.606 | BZ43: =$BS43*BL43*(1+$BT$4) -> 21613.606 | CA43: =$BS43*BM43*(1+$BT$4) -> 21613.606 | ... CE43: =$BS43*BQ43*(1+$BT$4) -> 21613.606 | CF43: =SUM(BT43:CE43) -> 259363.27 | CG43: 1 | CH43: =$CG43*BT43*(1+$CH$4) -> 22910.422 | CI43: =$CG43*BU43*(1+$CH$4) -> 22910.422 | CJ43: =$CG43*BV43*(1+$CH$4) -> 22910.422 | CK43: =$CG43*BW43*(1+$CH$4) -> 22910.422 | CL43: =$CG43*BX43*(1+$CH$4) -> 22910.422 | CM43: =$CG43*BY43*(1+$CH$4) -> 22910.422 | CN43: =$CG43*BZ43*(1+$CH$4) -> 22910.422 | CO43: =$CG43*CA43*(1+$CH$4) -> 22910.422 | ... CS43: =$CG43*CE43*(1+$CH$4) -> 22910.422 | CT43: =SUM(CH43:CS43) -> 274925.06 | CU43: 1 | CV43: =$CU43*CH43*(1+$CV$4) -> 24285.047 | CW43: =$CU43*CI43*(1+$CV$4) -> 24285.047 | CX43: =$CU43*CJ43*(1+$CV$4) -> 24285.047 | CY43: =$CU43*CK43*(1+$CV$4) -> 24285.047 | CZ43: =$CU43*CL43*(1+$CV$4) -> 24285.047 | DA43: =$CU43*CM43*(1+$CV$4) -> 24285.047 | DB43: =$CU43*CN43*(1+$CV$4) -> 24285.047 | DC43: =$CU43*CO43*(1+$CV$4) -> 24285.047 | ... DG43: =$CU43*CS43*(1+$CV$4) -> 24285.047 | DH43: =SUM(CV43:DG43) -> 291420.57 | DI43: 1 | DJ43: =$DI43*CV43*(1+$DJ$4) -> 25742.15 | DK43: =$DI43*CW43*(1+$DJ$4) -> 25742.15 | DL43: =$DI43*CX43*(1+$DJ$4) -> 25742.15 | DM43: =$DI43*CY43*(1+$DJ$4) -> 25742.15 | DN43: =$DI43*CZ43*(1+$DJ$4) -> 25742.15 | DO43: =$DI43*DA43*(1+$DJ$4) -> 25742.15 | DP43: =$DI43*DB43*(1+$DJ$4) -> 25742.15 | DQ43: =$DI43*DC43*(1+$DJ$4) -> 25742.15 | ... DU43: =$DI43*DG43*(1+$DJ$4) -> 25742.15 | DV43: =SUM(DJ43:DU43) -> 308905.8 | DW43: 1 | DX43: =$DW43*DJ43*(1+$DX$4) -> 27286.679 | DY43: =$DW43*DK43*(1+$DX$4) -> 27286.679 | DZ43: =$DW43*DL43*(1+$DX$4) -> 27286.679 | EA43: =$DW43*DM43*(1+$DX$4) -> 27286.679 | EB43: =$DW43*DN43*(1+$DX$4) -> 27286.679 | EC43: =$DW43*DO43*(1+$DX$4) -> 27286.679 | ED43: =$DW43*DP43*(1+$DX$4) -> 27286.679 | EE43: =$DW43*DQ43*(1+$DX$4) -> 27286.679 | ... EI43: =$DW43*DU43*(1+$DX$4) -> 27286.679 | EJ43: =SUM(DX43:EI43) -> 327440.15
A44: Contador | B44: 12000 | C44: =B44 -> 12000 | D44: =C44 -> 12000 | E44: =D44 -> 12000 | F44: =E44 -> 12000 | G44: =F44 -> 12000 | H44: =G44 -> 12000 | I44: =H44 -> 12000 | J44: =I44 -> 12000 | ... M44: =L44 -> 12000 | N44: =SUM(B44:M44) -> 144000 | O44: 1 | P44: =$O44*B44*(1+$P$4) -> 12840 | Q44: =$O44*C44*(1+$P$4) -> 12840 | R44: =$O44*D44*(1+$P$4) -> 12840 | S44: =$O44*E44*(1+$P$4) -> 12840 | T44: =$O44*F44*(1+$P$4) -> 12840 | U44: =$O44*G44*(1+$P$4) -> 12840 | V44: =$O44*H44*(1+$P$4) -> 12840 | W44: =$O44*I44*(1+$P$4) -> 12840 | ... AA44: =$O44*M44*(1+$P$4) -> 12840 | AB44: =SUM(P44:AA44) -> 154080 | AC44: 1 | AD44: =$AC44*P44*(1+$AD$4) -> 13610.4 | AE44: =$AC44*Q44*(1+$AD$4) -> 13610.4 | AF44: =$AC44*R44*(1+$AD$4) -> 13610.4 | AG44: =$AC44*S44*(1+$AD$4) -> 13610.4 | AH44: =$AC44*T44*(1+$AD$4) -> 13610.4 | AI44: =$AC44*U44*(1+$AD$4) -> 13610.4 | AJ44: =$AC44*V44*(1+$AD$4) -> 13610.4 | AK44: =$AC44*W44*(1+$AD$4) -> 13610.4 | ... AO44: =$AC44*AA44*(1+$AD$4) -> 13610.4 | AP44: =SUM(AD44:AO44) -> 163324.8 | AQ44: 1 | AR44: =$AQ44*AD44*(1+$AR$4) -> 14427.024 | AS44: =$AQ44*AE44*(1+$AR$4) -> 14427.024 | AT44: =$AQ44*AF44*(1+$AR$4) -> 14427.024 | AU44: =$AQ44*AG44*(1+$AR$4) -> 14427.024 | AV44: =$AQ44*AH44*(1+$AR$4) -> 14427.024 | AW44: =$AQ44*AI44*(1+$AR$4) -> 14427.024 | AX44: =$AQ44*AJ44*(1+$AR$4) -> 14427.024 | AY44: =$AQ44*AK44*(1+$AR$4) -> 14427.024 | ... BC44: =$AQ44*AO44*(1+$AR$4) -> 14427.024 | BD44: =SUM(AR44:BC44) -> 173124.29 | BE44: 1 | BF44: =$BE44*AR44*(1+$BF$4) -> 15292.645 | BG44: =$BE44*AS44*(1+$BF$4) -> 15292.645 | BH44: =$BE44*AT44*(1+$BF$4) -> 15292.645 | BI44: =$BE44*AU44*(1+$BF$4) -> 15292.645 | BJ44: =$BE44*AV44*(1+$BF$4) -> 15292.645 | BK44: =$BE44*AW44*(1+$BF$4) -> 15292.645 | BL44: =$BE44*AX44*(1+$BF$4) -> 15292.645 | BM44: =$BE44*AY44*(1+$BF$4) -> 15292.645 | ... BQ44: =$BE44*BC44*(1+$BF$4) -> 15292.645 | BR44: =SUM(BF44:BQ44) -> 183511.75 | BS44: 1 | BT44: =$BS44*BF44*(1+$BT$4) -> 16210.204 | BU44: =$BS44*BG44*(1+$BT$4) -> 16210.204 | BV44: =$BS44*BH44*(1+$BT$4) -> 16210.204 | BW44: =$BS44*BI44*(1+$BT$4) -> 16210.204 | BX44: =$BS44*BJ44*(1+$BT$4) -> 16210.204 | BY44: =$BS44*BK44*(1+$BT$4) -> 16210.204 | BZ44: =$BS44*BL44*(1+$BT$4) -> 16210.204 | CA44: =$BS44*BM44*(1+$BT$4) -> 16210.204 | ... CE44: =$BS44*BQ44*(1+$BT$4) -> 16210.204 | CF44: =SUM(BT44:CE44) -> 194522.45 | CG44: 1 | CH44: =$CG44*BT44*(1+$CH$4) -> 17182.816 | CI44: =$CG44*BU44*(1+$CH$4) -> 17182.816 | CJ44: =$CG44*BV44*(1+$CH$4) -> 17182.816 | CK44: =$CG44*BW44*(1+$CH$4) -> 17182.816 | CL44: =$CG44*BX44*(1+$CH$4) -> 17182.816 | CM44: =$CG44*BY44*(1+$CH$4) -> 17182.816 | CN44: =$CG44*BZ44*(1+$CH$4) -> 17182.816 | CO44: =$CG44*CA44*(1+$CH$4) -> 17182.816 | ... CS44: =$CG44*CE44*(1+$CH$4) -> 17182.816 | CT44: =SUM(CH44:CS44) -> 206193.8 | CU44: 1 | CV44: =$CU44*CH44*(1+$CV$4) -> 18213.785 | CW44: =$CU44*CI44*(1+$CV$4) -> 18213.785 | CX44: =$CU44*CJ44*(1+$CV$4) -> 18213.785 | CY44: =$CU44*CK44*(1+$CV$4) -> 18213.785 | CZ44: =$CU44*CL44*(1+$CV$4) -> 18213.785 | DA44: =$CU44*CM44*(1+$CV$4) -> 18213.785 | DB44: =$CU44*CN44*(1+$CV$4) -> 18213.785 | DC44: =$CU44*CO44*(1+$CV$4) -> 18213.785 | ... DG44: =$CU44*CS44*(1+$CV$4) -> 18213.785 | DH44: =SUM(CV44:DG44) -> 218565.42 | DI44: 1 | DJ44: =$DI44*CV44*(1+$DJ$4) -> 19306.613 | DK44: =$DI44*CW44*(1+$DJ$4) -> 19306.613 | DL44: =$DI44*CX44*(1+$DJ$4) -> 19306.613 | DM44: =$DI44*CY44*(1+$DJ$4) -> 19306.613 | DN44: =$DI44*CZ44*(1+$DJ$4) -> 19306.613 | DO44: =$DI44*DA44*(1+$DJ$4) -> 19306.613 | DP44: =$DI44*DB44*(1+$DJ$4) -> 19306.613 | DQ44: =$DI44*DC44*(1+$DJ$4) -> 19306.613 | ... DU44: =$DI44*DG44*(1+$DJ$4) -> 19306.613 | DV44: =SUM(DJ44:DU44) -> 231679.35 | DW44: 1 | DX44: =$DW44*DJ44*(1+$DX$4) -> 20465.009 | DY44: =$DW44*DK44*(1+$DX$4) -> 20465.009 | DZ44: =$DW44*DL44*(1+$DX$4) -> 20465.009 | EA44: =$DW44*DM44*(1+$DX$4) -> 20465.009 | EB44: =$DW44*DN44*(1+$DX$4) -> 20465.009 | EC44: =$DW44*DO44*(1+$DX$4) -> 20465.009 | ED44: =$DW44*DP44*(1+$DX$4) -> 20465.009 | EE44: =$DW44*DQ44*(1+$DX$4) -> 20465.009 | ... EI44: =$DW44*DU44*(1+$DX$4) -> 20465.009 | EJ44: =SUM(DX44:EI44) -> 245580.11
A45: Asistente administrativo | B45: 8500 | C45: =B45 -> 8500 | D45: =C45 -> 8500 | E45: =D45 -> 8500 | F45: =E45 -> 8500 | G45: =F45 -> 8500 | H45: =G45 -> 8500 | I45: =H45 -> 8500 | J45: =I45 -> 8500 | ... M45: =L45 -> 8500 | N45: =SUM(B45:M45) -> 102000 | O45: 1 | P45: =$O45*B45*(1+$P$4) -> 9095 | Q45: =$O45*C45*(1+$P$4) -> 9095 | R45: =$O45*D45*(1+$P$4) -> 9095 | S45: =$O45*E45*(1+$P$4) -> 9095 | T45: =$O45*F45*(1+$P$4) -> 9095 | U45: =$O45*G45*(1+$P$4) -> 9095 | V45: =$O45*H45*(1+$P$4) -> 9095 | W45: =$O45*I45*(1+$P$4) -> 9095 | ... AA45: =$O45*M45*(1+$P$4) -> 9095 | AB45: =SUM(P45:AA45) -> 109140 | AC45: 1 | AD45: =$AC45*P45*(1+$AD$4) -> 9640.7 | AE45: =$AC45*Q45*(1+$AD$4) -> 9640.7 | AF45: =$AC45*R45*(1+$AD$4) -> 9640.7 | AG45: =$AC45*S45*(1+$AD$4) -> 9640.7 | AH45: =$AC45*T45*(1+$AD$4) -> 9640.7 | AI45: =$AC45*U45*(1+$AD$4) -> 9640.7 | AJ45: =$AC45*V45*(1+$AD$4) -> 9640.7 | AK45: =$AC45*W45*(1+$AD$4) -> 9640.7 | ... AO45: =$AC45*AA45*(1+$AD$4) -> 9640.7 | AP45: =SUM(AD45:AO45) -> 115688.4 | AQ45: 1 | AR45: =$AQ45*AD45*(1+$AR$4) -> 10219.142 | AS45: =$AQ45*AE45*(1+$AR$4) -> 10219.142 | AT45: =$AQ45*AF45*(1+$AR$4) -> 10219.142 | AU45: =$AQ45*AG45*(1+$AR$4) -> 10219.142 | AV45: =$AQ45*AH45*(1+$AR$4) -> 10219.142 | AW45: =$AQ45*AI45*(1+$AR$4) -> 10219.142 | AX45: =$AQ45*AJ45*(1+$AR$4) -> 10219.142 | AY45: =$AQ45*AK45*(1+$AR$4) -> 10219.142 | ... BC45: =$AQ45*AO45*(1+$AR$4) -> 10219.142 | BD45: =SUM(AR45:BC45) -> 122629.7 | BE45: 1 | BF45: =$BE45*AR45*(1+$BF$4) -> 10832.291 | BG45: =$BE45*AS45*(1+$BF$4) -> 10832.291 | BH45: =$BE45*AT45*(1+$BF$4) -> 10832.291 | BI45: =$BE45*AU45*(1+$BF$4) -> 10832.291 | BJ45: =$BE45*AV45*(1+$BF$4) -> 10832.291 | BK45: =$BE45*AW45*(1+$BF$4) -> 10832.291 | BL45: =$BE45*AX45*(1+$BF$4) -> 10832.291 | BM45: =$BE45*AY45*(1+$BF$4) -> 10832.291 | ... BQ45: =$BE45*BC45*(1+$BF$4) -> 10832.291 | BR45: =SUM(BF45:BQ45) -> 129987.49 | BS45: 1 | BT45: =$BS45*BF45*(1+$BT$4) -> 11482.228 | BU45: =$BS45*BG45*(1+$BT$4) -> 11482.228 | BV45: =$BS45*BH45*(1+$BT$4) -> 11482.228 | BW45: =$BS45*BI45*(1+$BT$4) -> 11482.228 | BX45: =$BS45*BJ45*(1+$BT$4) -> 11482.228 | BY45: =$BS45*BK45*(1+$BT$4) -> 11482.228 | BZ45: =$BS45*BL45*(1+$BT$4) -> 11482.228 | CA45: =$BS45*BM45*(1+$BT$4) -> 11482.228 | ... CE45: =$BS45*BQ45*(1+$BT$4) -> 11482.228 | CF45: =SUM(BT45:CE45) -> 137786.74 | CG45: 1 | CH45: =$CG45*BT45*(1+$CH$4) -> 12171.162 | CI45: =$CG45*BU45*(1+$CH$4) -> 12171.162 | CJ45: =$CG45*BV45*(1+$CH$4) -> 12171.162 | CK45: =$CG45*BW45*(1+$CH$4) -> 12171.162 | CL45: =$CG45*BX45*(1+$CH$4) -> 12171.162 | CM45: =$CG45*BY45*(1+$CH$4) -> 12171.162 | CN45: =$CG45*BZ45*(1+$CH$4) -> 12171.162 | CO45: =$CG45*CA45*(1+$CH$4) -> 12171.162 | ... CS45: =$CG45*CE45*(1+$CH$4) -> 12171.162 | CT45: =SUM(CH45:CS45) -> 146053.94 | CU45: 1 | CV45: =$CU45*CH45*(1+$CV$4) -> 12901.431 | CW45: =$CU45*CI45*(1+$CV$4) -> 12901.431 | CX45: =$CU45*CJ45*(1+$CV$4) -> 12901.431 | CY45: =$CU45*CK45*(1+$CV$4) -> 12901.431 | CZ45: =$CU45*CL45*(1+$CV$4) -> 12901.431 | DA45: =$CU45*CM45*(1+$CV$4) -> 12901.431 | DB45: =$CU45*CN45*(1+$CV$4) -> 12901.431 | DC45: =$CU45*CO45*(1+$CV$4) -> 12901.431 | ... DG45: =$CU45*CS45*(1+$CV$4) -> 12901.431 | DH45: =SUM(CV45:DG45) -> 154817.18 | DI45: 1 | DJ45: =$DI45*CV45*(1+$DJ$4) -> 13675.517 | DK45: =$DI45*CW45*(1+$DJ$4) -> 13675.517 | DL45: =$DI45*CX45*(1+$DJ$4) -> 13675.517 | DM45: =$DI45*CY45*(1+$DJ$4) -> 13675.517 | DN45: =$DI45*CZ45*(1+$DJ$4) -> 13675.517 | DO45: =$DI45*DA45*(1+$DJ$4) -> 13675.517 | DP45: =$DI45*DB45*(1+$DJ$4) -> 13675.517 | DQ45: =$DI45*DC45*(1+$DJ$4) -> 13675.517 | ... DU45: =$DI45*DG45*(1+$DJ$4) -> 13675.517 | DV45: =SUM(DJ45:DU45) -> 164106.21 | DW45: 1 | DX45: =$DW45*DJ45*(1+$DX$4) -> 14496.048 | DY45: =$DW45*DK45*(1+$DX$4) -> 14496.048 | DZ45: =$DW45*DL45*(1+$DX$4) -> 14496.048 | EA45: =$DW45*DM45*(1+$DX$4) -> 14496.048 | EB45: =$DW45*DN45*(1+$DX$4) -> 14496.048 | EC45: =$DW45*DO45*(1+$DX$4) -> 14496.048 | ED45: =$DW45*DP45*(1+$DX$4) -> 14496.048 | EE45: =$DW45*DQ45*(1+$DX$4) -> 14496.048 | ... EI45: =$DW45*DU45*(1+$DX$4) -> 14496.048 | EJ45: =SUM(DX45:EI45) -> 173952.58
A46: Internet/telefonía (cuota mensual) | B46: 600 | C46: =B46 -> 600 | D46: =C46 -> 600 | E46: =D46 -> 600 | F46: =E46 -> 600 | G46: =F46 -> 600 | H46: =G46 -> 600 | I46: =H46 -> 600 | J46: =I46 -> 600 | ... M46: =L46 -> 600 | N46: =SUM(B46:M46) -> 7200 | O46: 1 | P46: =$O46*B46*(1+$P$4) -> 642 | Q46: =$O46*C46*(1+$P$4) -> 642 | R46: =$O46*D46*(1+$P$4) -> 642 | S46: =$O46*E46*(1+$P$4) -> 642 | T46: =$O46*F46*(1+$P$4) -> 642 | U46: =$O46*G46*(1+$P$4) -> 642 | V46: =$O46*H46*(1+$P$4) -> 642 | W46: =$O46*I46*(1+$P$4) -> 642 | ... AA46: =$O46*M46*(1+$P$4) -> 642 | AB46: =SUM(P46:AA46) -> 7704 | AC46: 1 | AD46: =$AC46*P46*(1+$AD$4) -> 680.52 | AE46: =$AC46*Q46*(1+$AD$4) -> 680.52 | AF46: =$AC46*R46*(1+$AD$4) -> 680.52 | AG46: =$AC46*S46*(1+$AD$4) -> 680.52 | AH46: =$AC46*T46*(1+$AD$4) -> 680.52 | AI46: =$AC46*U46*(1+$AD$4) -> 680.52 | AJ46: =$AC46*V46*(1+$AD$4) -> 680.52 | AK46: =$AC46*W46*(1+$AD$4) -> 680.52 | ... AO46: =$AC46*AA46*(1+$AD$4) -> 680.52 | AP46: =SUM(AD46:AO46) -> 8166.24 | AQ46: 1 | AR46: =$AQ46*AD46*(1+$AR$4) -> 721.3512 | AS46: =$AQ46*AE46*(1+$AR$4) -> 721.3512 | AT46: =$AQ46*AF46*(1+$AR$4) -> 721.3512 | AU46: =$AQ46*AG46*(1+$AR$4) -> 721.3512 | AV46: =$AQ46*AH46*(1+$AR$4) -> 721.3512 | AW46: =$AQ46*AI46*(1+$AR$4) -> 721.3512 | AX46: =$AQ46*AJ46*(1+$AR$4) -> 721.3512 | AY46: =$AQ46*AK46*(1+$AR$4) -> 721.3512 | ... BC46: =$AQ46*AO46*(1+$AR$4) -> 721.3512 | BD46: =SUM(AR46:BC46) -> 8656.2144 | BE46: 1 | BF46: =$BE46*AR46*(1+$BF$4) -> 764.63227 | BG46: =$BE46*AS46*(1+$BF$4) -> 764.63227 | BH46: =$BE46*AT46*(1+$BF$4) -> 764.63227 | BI46: =$BE46*AU46*(1+$BF$4) -> 764.63227 | BJ46: =$BE46*AV46*(1+$BF$4) -> 764.63227 | BK46: =$BE46*AW46*(1+$BF$4) -> 764.63227 | BL46: =$BE46*AX46*(1+$BF$4) -> 764.63227 | BM46: =$BE46*AY46*(1+$BF$4) -> 764.63227 | ... BQ46: =$BE46*BC46*(1+$BF$4) -> 764.63227 | BR46: =SUM(BF46:BQ46) -> 9175.5873 | BS46: 1 | BT46: =$BS46*BF46*(1+$BT$4) -> 810.51021 | BU46: =$BS46*BG46*(1+$BT$4) -> 810.51021 | BV46: =$BS46*BH46*(1+$BT$4) -> 810.51021 | BW46: =$BS46*BI46*(1+$BT$4) -> 810.51021 | BX46: =$BS46*BJ46*(1+$BT$4) -> 810.51021 | BY46: =$BS46*BK46*(1+$BT$4) -> 810.51021 | BZ46: =$BS46*BL46*(1+$BT$4) -> 810.51021 | CA46: =$BS46*BM46*(1+$BT$4) -> 810.51021 | ... CE46: =$BS46*BQ46*(1+$BT$4) -> 810.51021 | CF46: =SUM(BT46:CE46) -> 9726.1225 | CG46: 1 | CH46: =$CG46*BT46*(1+$CH$4) -> 859.14082 | CI46: =$CG46*BU46*(1+$CH$4) -> 859.14082 | CJ46: =$CG46*BV46*(1+$CH$4) -> 859.14082 | CK46: =$CG46*BW46*(1+$CH$4) -> 859.14082 | CL46: =$CG46*BX46*(1+$CH$4) -> 859.14082 | CM46: =$CG46*BY46*(1+$CH$4) -> 859.14082 | CN46: =$CG46*BZ46*(1+$CH$4) -> 859.14082 | CO46: =$CG46*CA46*(1+$CH$4) -> 859.14082 | ... CS46: =$CG46*CE46*(1+$CH$4) -> 859.14082 | CT46: =SUM(CH46:CS46) -> 10309.69 | CU46: 1 | CV46: =$CU46*CH46*(1+$CV$4) -> 910.68927 | CW46: =$CU46*CI46*(1+$CV$4) -> 910.68927 | CX46: =$CU46*CJ46*(1+$CV$4) -> 910.68927 | CY46: =$CU46*CK46*(1+$CV$4) -> 910.68927 | CZ46: =$CU46*CL46*(1+$CV$4) -> 910.68927 | DA46: =$CU46*CM46*(1+$CV$4) -> 910.68927 | DB46: =$CU46*CN46*(1+$CV$4) -> 910.68927 | DC46: =$CU46*CO46*(1+$CV$4) -> 910.68927 | ... DG46: =$CU46*CS46*(1+$CV$4) -> 910.68927 | DH46: =SUM(CV46:DG46) -> 10928.271 | DI46: 1 | DJ46: =$DI46*CV46*(1+$DJ$4) -> 965.33063 | DK46: =$DI46*CW46*(1+$DJ$4) -> 965.33063 | DL46: =$DI46*CX46*(1+$DJ$4) -> 965.33063 | DM46: =$DI46*CY46*(1+$DJ$4) -> 965.33063 | DN46: =$DI46*CZ46*(1+$DJ$4) -> 965.33063 | DO46: =$DI46*DA46*(1+$DJ$4) -> 965.33063 | DP46: =$DI46*DB46*(1+$DJ$4) -> 965.33063 | DQ46: =$DI46*DC46*(1+$DJ$4) -> 965.33063 | ... DU46: =$DI46*DG46*(1+$DJ$4) -> 965.33063 | DV46: =SUM(DJ46:DU46) -> 11583.968 | DW46: 1 | DX46: =$DW46*DJ46*(1+$DX$4) -> 1023.2505 | DY46: =$DW46*DK46*(1+$DX$4) -> 1023.2505 | DZ46: =$DW46*DL46*(1+$DX$4) -> 1023.2505 | EA46: =$DW46*DM46*(1+$DX$4) -> 1023.2505 | EB46: =$DW46*DN46*(1+$DX$4) -> 1023.2505 | EC46: =$DW46*DO46*(1+$DX$4) -> 1023.2505 | ED46: =$DW46*DP46*(1+$DX$4) -> 1023.2505 | EE46: =$DW46*DQ46*(1+$DX$4) -> 1023.2505 | ... EI46: =$DW46*DU46*(1+$DX$4) -> 1023.2505 | EJ46: =SUM(DX46:EI46) -> 12279.006
A47: Papelería (material predeterminado) | B47: 800 | C47: =B47 -> 800 | D47: =C47 -> 800 | E47: =D47 -> 800 | F47: =E47 -> 800 | G47: =F47 -> 800 | H47: =G47 -> 800 | I47: =H47 -> 800 | J47: =I47 -> 800 | ... M47: =L47 -> 800 | N47: =SUM(B47:M47) -> 9600 | O47: 1 | P47: =$O47*B47*(1+$P$4) -> 856 | Q47: =$O47*C47*(1+$P$4) -> 856 | R47: =$O47*D47*(1+$P$4) -> 856 | S47: =$O47*E47*(1+$P$4) -> 856 | T47: =$O47*F47*(1+$P$4) -> 856 | U47: =$O47*G47*(1+$P$4) -> 856 | V47: =$O47*H47*(1+$P$4) -> 856 | W47: =$O47*I47*(1+$P$4) -> 856 | ... AA47: =$O47*M47*(1+$P$4) -> 856 | AB47: =SUM(P47:AA47) -> 10272 | AC47: 1 | AD47: =$AC47*P47*(1+$AD$4) -> 907.36 | AE47: =$AC47*Q47*(1+$AD$4) -> 907.36 | AF47: =$AC47*R47*(1+$AD$4) -> 907.36 | AG47: =$AC47*S47*(1+$AD$4) -> 907.36 | AH47: =$AC47*T47*(1+$AD$4) -> 907.36 | AI47: =$AC47*U47*(1+$AD$4) -> 907.36 | AJ47: =$AC47*V47*(1+$AD$4) -> 907.36 | AK47: =$AC47*W47*(1+$AD$4) -> 907.36 | ... AO47: =$AC47*AA47*(1+$AD$4) -> 907.36 | AP47: =SUM(AD47:AO47) -> 10888.32 | AQ47: 1 | AR47: =$AQ47*AD47*(1+$AR$4) -> 961.8016 | AS47: =$AQ47*AE47*(1+$AR$4) -> 961.8016 | AT47: =$AQ47*AF47*(1+$AR$4) -> 961.8016 | AU47: =$AQ47*AG47*(1+$AR$4) -> 961.8016 | AV47: =$AQ47*AH47*(1+$AR$4) -> 961.8016 | AW47: =$AQ47*AI47*(1+$AR$4) -> 961.8016 | AX47: =$AQ47*AJ47*(1+$AR$4) -> 961.8016 | AY47: =$AQ47*AK47*(1+$AR$4) -> 961.8016 | ... BC47: =$AQ47*AO47*(1+$AR$4) -> 961.8016 | BD47: =SUM(AR47:BC47) -> 11541.619 | BE47: 1 | BF47: =$BE47*AR47*(1+$BF$4) -> 1019.5097 | BG47: =$BE47*AS47*(1+$BF$4) -> 1019.5097 | BH47: =$BE47*AT47*(1+$BF$4) -> 1019.5097 | BI47: =$BE47*AU47*(1+$BF$4) -> 1019.5097 | BJ47: =$BE47*AV47*(1+$BF$4) -> 1019.5097 | BK47: =$BE47*AW47*(1+$BF$4) -> 1019.5097 | BL47: =$BE47*AX47*(1+$BF$4) -> 1019.5097 | BM47: =$BE47*AY47*(1+$BF$4) -> 1019.5097 | ... BQ47: =$BE47*BC47*(1+$BF$4) -> 1019.5097 | BR47: =SUM(BF47:BQ47) -> 12234.116 | BS47: 1 | BT47: =$BS47*BF47*(1+$BT$4) -> 1080.6803 | BU47: =$BS47*BG47*(1+$BT$4) -> 1080.6803 | BV47: =$BS47*BH47*(1+$BT$4) -> 1080.6803 | BW47: =$BS47*BI47*(1+$BT$4) -> 1080.6803 | BX47: =$BS47*BJ47*(1+$BT$4) -> 1080.6803 | BY47: =$BS47*BK47*(1+$BT$4) -> 1080.6803 | BZ47: =$BS47*BL47*(1+$BT$4) -> 1080.6803 | CA47: =$BS47*BM47*(1+$BT$4) -> 1080.6803 | ... CE47: =$BS47*BQ47*(1+$BT$4) -> 1080.6803 | CF47: =SUM(BT47:CE47) -> 12968.163 | CG47: 1 | CH47: =$CG47*BT47*(1+$CH$4) -> 1145.5211 | CI47: =$CG47*BU47*(1+$CH$4) -> 1145.5211 | CJ47: =$CG47*BV47*(1+$CH$4) -> 1145.5211 | CK47: =$CG47*BW47*(1+$CH$4) -> 1145.5211 | CL47: =$CG47*BX47*(1+$CH$4) -> 1145.5211 | CM47: =$CG47*BY47*(1+$CH$4) -> 1145.5211 | CN47: =$CG47*BZ47*(1+$CH$4) -> 1145.5211 | CO47: =$CG47*CA47*(1+$CH$4) -> 1145.5211 | ... CS47: =$CG47*CE47*(1+$CH$4) -> 1145.5211 | CT47: =SUM(CH47:CS47) -> 13746.253 | CU47: 1 | CV47: =$CU47*CH47*(1+$CV$4) -> 1214.2524 | CW47: =$CU47*CI47*(1+$CV$4) -> 1214.2524 | CX47: =$CU47*CJ47*(1+$CV$4) -> 1214.2524 | CY47: =$CU47*CK47*(1+$CV$4) -> 1214.2524 | CZ47: =$CU47*CL47*(1+$CV$4) -> 1214.2524 | DA47: =$CU47*CM47*(1+$CV$4) -> 1214.2524 | DB47: =$CU47*CN47*(1+$CV$4) -> 1214.2524 | DC47: =$CU47*CO47*(1+$CV$4) -> 1214.2524 | ... DG47: =$CU47*CS47*(1+$CV$4) -> 1214.2524 | DH47: =SUM(CV47:DG47) -> 14571.028 | DI47: 1 | DJ47: =$DI47*CV47*(1+$DJ$4) -> 1287.1075 | DK47: =$DI47*CW47*(1+$DJ$4) -> 1287.1075 | DL47: =$DI47*CX47*(1+$DJ$4) -> 1287.1075 | DM47: =$DI47*CY47*(1+$DJ$4) -> 1287.1075 | DN47: =$DI47*CZ47*(1+$DJ$4) -> 1287.1075 | DO47: =$DI47*DA47*(1+$DJ$4) -> 1287.1075 | DP47: =$DI47*DB47*(1+$DJ$4) -> 1287.1075 | DQ47: =$DI47*DC47*(1+$DJ$4) -> 1287.1075 | ... DU47: =$DI47*DG47*(1+$DJ$4) -> 1287.1075 | DV47: =SUM(DJ47:DU47) -> 15445.29 | DW47: 1 | DX47: =$DW47*DJ47*(1+$DX$4) -> 1364.334 | DY47: =$DW47*DK47*(1+$DX$4) -> 1364.334 | DZ47: =$DW47*DL47*(1+$DX$4) -> 1364.334 | EA47: =$DW47*DM47*(1+$DX$4) -> 1364.334 | EB47: =$DW47*DN47*(1+$DX$4) -> 1364.334 | EC47: =$DW47*DO47*(1+$DX$4) -> 1364.334 | ED47: =$DW47*DP47*(1+$DX$4) -> 1364.334 | EE47: =$DW47*DQ47*(1+$DX$4) -> 1364.334 | ... EI47: =$DW47*DU47*(1+$DX$4) -> 1364.334 | EJ47: =SUM(DX47:EI47) -> 16372.007
A48: Caja chica | B48: 1000 | C48: =B48 -> 1000 | D48: =C48 -> 1000 | E48: =D48 -> 1000 | F48: =E48 -> 1000 | G48: =F48 -> 1000 | H48: =G48 -> 1000 | I48: =H48 -> 1000 | J48: =I48 -> 1000 | ... M48: =L48 -> 1000 | N48: =SUM(B48:M48) -> 12000 | O48: 1 | P48: =$O48*B48*(1+$P$4) -> 1070 | Q48: =$O48*C48*(1+$P$4) -> 1070 | R48: =$O48*D48*(1+$P$4) -> 1070 | S48: =$O48*E48*(1+$P$4) -> 1070 | T48: =$O48*F48*(1+$P$4) -> 1070 | U48: =$O48*G48*(1+$P$4) -> 1070 | V48: =$O48*H48*(1+$P$4) -> 1070 | W48: =$O48*I48*(1+$P$4) -> 1070 | ... AA48: =$O48*M48*(1+$P$4) -> 1070 | AB48: =SUM(P48:AA48) -> 12840 | AC48: 1 | AD48: =$AC48*P48*(1+$AD$4) -> 1134.2 | AE48: =$AC48*Q48*(1+$AD$4) -> 1134.2 | AF48: =$AC48*R48*(1+$AD$4) -> 1134.2 | AG48: =$AC48*S48*(1+$AD$4) -> 1134.2 | AH48: =$AC48*T48*(1+$AD$4) -> 1134.2 | AI48: =$AC48*U48*(1+$AD$4) -> 1134.2 | AJ48: =$AC48*V48*(1+$AD$4) -> 1134.2 | AK48: =$AC48*W48*(1+$AD$4) -> 1134.2 | ... AO48: =$AC48*AA48*(1+$AD$4) -> 1134.2 | AP48: =SUM(AD48:AO48) -> 13610.4 | AQ48: 1 | AR48: =$AQ48*AD48*(1+$AR$4) -> 1202.252 | AS48: =$AQ48*AE48*(1+$AR$4) -> 1202.252 | AT48: =$AQ48*AF48*(1+$AR$4) -> 1202.252 | AU48: =$AQ48*AG48*(1+$AR$4) -> 1202.252 | AV48: =$AQ48*AH48*(1+$AR$4) -> 1202.252 | AW48: =$AQ48*AI48*(1+$AR$4) -> 1202.252 | AX48: =$AQ48*AJ48*(1+$AR$4) -> 1202.252 | AY48: =$AQ48*AK48*(1+$AR$4) -> 1202.252 | ... BC48: =$AQ48*AO48*(1+$AR$4) -> 1202.252 | BD48: =SUM(AR48:BC48) -> 14427.024 | BE48: 1 | BF48: =$BE48*AR48*(1+$BF$4) -> 1274.3871 | BG48: =$BE48*AS48*(1+$BF$4) -> 1274.3871 | BH48: =$BE48*AT48*(1+$BF$4) -> 1274.3871 | BI48: =$BE48*AU48*(1+$BF$4) -> 1274.3871 | BJ48: =$BE48*AV48*(1+$BF$4) -> 1274.3871 | BK48: =$BE48*AW48*(1+$BF$4) -> 1274.3871 | BL48: =$BE48*AX48*(1+$BF$4) -> 1274.3871 | BM48: =$BE48*AY48*(1+$BF$4) -> 1274.3871 | ... BQ48: =$BE48*BC48*(1+$BF$4) -> 1274.3871 | BR48: =SUM(BF48:BQ48) -> 15292.645 | BS48: 1 | BT48: =$BS48*BF48*(1+$BT$4) -> 1350.8503 | BU48: =$BS48*BG48*(1+$BT$4) -> 1350.8503 | BV48: =$BS48*BH48*(1+$BT$4) -> 1350.8503 | BW48: =$BS48*BI48*(1+$BT$4) -> 1350.8503 | BX48: =$BS48*BJ48*(1+$BT$4) -> 1350.8503 | BY48: =$BS48*BK48*(1+$BT$4) -> 1350.8503 | BZ48: =$BS48*BL48*(1+$BT$4) -> 1350.8503 | CA48: =$BS48*BM48*(1+$BT$4) -> 1350.8503 | ... CE48: =$BS48*BQ48*(1+$BT$4) -> 1350.8503 | CF48: =SUM(BT48:CE48) -> 16210.204 | CG48: 1 | CH48: =$CG48*BT48*(1+$CH$4) -> 1431.9014 | CI48: =$CG48*BU48*(1+$CH$4) -> 1431.9014 | CJ48: =$CG48*BV48*(1+$CH$4) -> 1431.9014 | CK48: =$CG48*BW48*(1+$CH$4) -> 1431.9014 | CL48: =$CG48*BX48*(1+$CH$4) -> 1431.9014 | CM48: =$CG48*BY48*(1+$CH$4) -> 1431.9014 | CN48: =$CG48*BZ48*(1+$CH$4) -> 1431.9014 | CO48: =$CG48*CA48*(1+$CH$4) -> 1431.9014 | ... CS48: =$CG48*CE48*(1+$CH$4) -> 1431.9014 | CT48: =SUM(CH48:CS48) -> 17182.816 | CU48: 1 | CV48: =$CU48*CH48*(1+$CV$4) -> 1517.8155 | CW48: =$CU48*CI48*(1+$CV$4) -> 1517.8155 | CX48: =$CU48*CJ48*(1+$CV$4) -> 1517.8155 | CY48: =$CU48*CK48*(1+$CV$4) -> 1517.8155 | CZ48: =$CU48*CL48*(1+$CV$4) -> 1517.8155 | DA48: =$CU48*CM48*(1+$CV$4) -> 1517.8155 | DB48: =$CU48*CN48*(1+$CV$4) -> 1517.8155 | DC48: =$CU48*CO48*(1+$CV$4) -> 1517.8155 | ... DG48: =$CU48*CS48*(1+$CV$4) -> 1517.8155 | DH48: =SUM(CV48:DG48) -> 18213.785 | DI48: 1 | DJ48: =$DI48*CV48*(1+$DJ$4) -> 1608.8844 | DK48: =$DI48*CW48*(1+$DJ$4) -> 1608.8844 | DL48: =$DI48*CX48*(1+$DJ$4) -> 1608.8844 | DM48: =$DI48*CY48*(1+$DJ$4) -> 1608.8844 | DN48: =$DI48*CZ48*(1+$DJ$4) -> 1608.8844 | DO48: =$DI48*DA48*(1+$DJ$4) -> 1608.8844 | DP48: =$DI48*DB48*(1+$DJ$4) -> 1608.8844 | DQ48: =$DI48*DC48*(1+$DJ$4) -> 1608.8844 | ... DU48: =$DI48*DG48*(1+$DJ$4) -> 1608.8844 | DV48: =SUM(DJ48:DU48) -> 19306.613 | DW48: 1 | DX48: =$DW48*DJ48*(1+$DX$4) -> 1705.4174 | DY48: =$DW48*DK48*(1+$DX$4) -> 1705.4174 | DZ48: =$DW48*DL48*(1+$DX$4) -> 1705.4174 | EA48: =$DW48*DM48*(1+$DX$4) -> 1705.4174 | EB48: =$DW48*DN48*(1+$DX$4) -> 1705.4174 | EC48: =$DW48*DO48*(1+$DX$4) -> 1705.4174 | ED48: =$DW48*DP48*(1+$DX$4) -> 1705.4174 | EE48: =$DW48*DQ48*(1+$DX$4) -> 1705.4174 | ... EI48: =$DW48*DU48*(1+$DX$4) -> 1705.4174 | EJ48: =SUM(DX48:EI48) -> 20465.009
A49: 2.2. Gastos de ventas | B49: =SUM(B50:B51) -> 25000 | C49: =SUM(C50:C51) -> 25000 | D49: =SUM(D50:D51) -> 25000 | E49: =SUM(E50:E51) -> 25000 | F49: =SUM(F50:F51) -> 25000 | G49: =SUM(G50:G51) -> 25000 | H49: =SUM(H50:H51) -> 25000 | I49: =SUM(I50:I51) -> 25000 | ... M49: =SUM(M50:M51) -> 25000 | N49: =SUM(B49:M49) -> 300000 | P49: =SUM(P50:P51) -> 27071 | Q49: =SUM(Q50:Q51) -> 27071 | R49: =SUM(R50:R51) -> 27071 | S49: =SUM(S50:S51) -> 27071 | T49: =SUM(T50:T51) -> 27071 | U49: =SUM(U50:U51) -> 27071 | V49: =SUM(V50:V51) -> 27071 | W49: =SUM(W50:W51) -> 27071 | ... AA49: =SUM(AA50:AA51) -> 27071 | AB49: =SUM(P49:AA49) -> 324852 | AD49: =SUM(AD50:AD51) -> 29279.373 | AE49: =SUM(AE50:AE51) -> 29279.373 | AF49: =SUM(AF50:AF51) -> 29279.373 | AG49: =SUM(AG50:AG51) -> 29279.373 | AH49: =SUM(AH50:AH51) -> 29279.373 | AI49: =SUM(AI50:AI51) -> 29279.373 | AJ49: =SUM(AJ50:AJ51) -> 29279.373 | AK49: =SUM(AK50:AK51) -> 29279.373 | ... AO49: =SUM(AO50:AO51) -> 29279.373 | AP49: =SUM(AD49:AO49) -> 351352.48 | AR49: =SUM(AR50:AR51) -> 31686.253 | AS49: =SUM(AS50:AS51) -> 31686.253 | AT49: =SUM(AT50:AT51) -> 31686.253 | AU49: =SUM(AU50:AU51) -> 31686.253 | AV49: =SUM(AV50:AV51) -> 31686.253 | AW49: =SUM(AW50:AW51) -> 31686.253 | AX49: =SUM(AX50:AX51) -> 31686.253 | AY49: =SUM(AY50:AY51) -> 31686.253 | ... BC49: =SUM(BC50:BC51) -> 31686.253 | BD49: =SUM(AR49:BC49) -> 380235.04 | BF49: =SUM(BF50:BF51) -> 34311.009 | BG49: =SUM(BG50:BG51) -> 34311.009 | BH49: =SUM(BH50:BH51) -> 34311.009 | BI49: =SUM(BI50:BI51) -> 34311.009 | BJ49: =SUM(BJ50:BJ51) -> 34311.009 | BK49: =SUM(BK50:BK51) -> 34311.009 | BL49: =SUM(BL50:BL51) -> 34311.009 | BM49: =SUM(BM50:BM51) -> 34311.009 | ... BQ49: =SUM(BQ50:BQ51) -> 34311.009 | BR49: =SUM(BF49:BQ49) -> 411732.11 | BT49: =SUM(BT50:BT51) -> 37175.016 | BU49: =SUM(BU50:BU51) -> 37175.016 | BV49: =SUM(BV50:BV51) -> 37175.016 | BW49: =SUM(BW50:BW51) -> 37175.016 | BX49: =SUM(BX50:BX51) -> 37175.016 | BY49: =SUM(BY50:BY51) -> 37175.016 | BZ49: =SUM(BZ50:BZ51) -> 37175.016 | CA49: =SUM(CA50:CA51) -> 37175.016 | ... CE49: =SUM(CE50:CE51) -> 37175.016 | CF49: =SUM(BT49:CE49) -> 446100.19 | CH49: =SUM(CH50:CH51) -> 40301.866 | CI49: =SUM(CI50:CI51) -> 40301.866 | CJ49: =SUM(CJ50:CJ51) -> 40301.866 | CK49: =SUM(CK50:CK51) -> 40301.866 | CL49: =SUM(CL50:CL51) -> 40301.866 | CM49: =SUM(CM50:CM51) -> 40301.866 | CN49: =SUM(CN50:CN51) -> 40301.866 | CO49: =SUM(CO50:CO51) -> 40301.866 | ... CS49: =SUM(CS50:CS51) -> 40301.866 | CT49: =SUM(CH49:CS49) -> 483622.4 | CV49: =SUM(CV50:CV51) -> 43717.616 | CW49: =SUM(CW50:CW51) -> 43717.616 | CX49: =SUM(CX50:CX51) -> 43717.616 | CY49: =SUM(CY50:CY51) -> 43717.616 | CZ49: =SUM(CZ50:CZ51) -> 43717.616 | DA49: =SUM(DA50:DA51) -> 43717.616 | DB49: =SUM(DB50:DB51) -> 43717.616 | DC49: =SUM(DC50:DC51) -> 43717.616 | ... DG49: =SUM(DG50:DG51) -> 43717.616 | DH49: =SUM(CV49:DG49) -> 524611.39 | DJ49: =SUM(DJ50:DJ51) -> 47451.043 | DK49: =SUM(DK50:DK51) -> 47451.043 | DL49: =SUM(DL50:DL51) -> 47451.043 | DM49: =SUM(DM50:DM51) -> 47451.043 | DN49: =SUM(DN50:DN51) -> 47451.043 | DO49: =SUM(DO50:DO51) -> 47451.043 | DP49: =SUM(DP50:DP51) -> 47451.043 | DQ49: =SUM(DQ50:DQ51) -> 47451.043 | ... DU49: =SUM(DU50:DU51) -> 47451.043 | DV49: =SUM(DJ49:DU49) -> 569412.52 | DX49: =SUM(DX50:DX51) -> 51533.948 | DY49: =SUM(DY50:DY51) -> 51533.948 | DZ49: =SUM(DZ50:DZ51) -> 51533.948 | EA49: =SUM(EA50:EA51) -> 51533.948 | EB49: =SUM(EB50:EB51) -> 51533.948 | EC49: =SUM(EC50:EC51) -> 51533.948 | ED49: =SUM(ED50:ED51) -> 51533.948 | EE49: =SUM(EE50:EE51) -> 51533.948 | ... EI49: =SUM(EI50:EI51) -> 51533.948 | EJ49: =SUM(DX49:EI49) -> 618407.37
A50: Combustible | B50: 15000 | C50: =B50 -> 15000 | D50: =C50 -> 15000 | E50: =D50 -> 15000 | F50: =E50 -> 15000 | G50: =F50 -> 15000 | H50: =G50 -> 15000 | I50: =H50 -> 15000 | J50: =I50 -> 15000 | ... M50: =L50 -> 15000 | N50: =SUM(B50:M50) -> 180000 | O50: 1 | P50: =$O50*B50*(1+$P$4) -> 16050 | Q50: =$O50*C50*(1+$P$4) -> 16050 | R50: =$O50*D50*(1+$P$4) -> 16050 | S50: =$O50*E50*(1+$P$4) -> 16050 | T50: =$O50*F50*(1+$P$4) -> 16050 | U50: =$O50*G50*(1+$P$4) -> 16050 | V50: =$O50*H50*(1+$P$4) -> 16050 | W50: =$O50*I50*(1+$P$4) -> 16050 | ... AA50: =$O50*M50*(1+$P$4) -> 16050 | AB50: =SUM(P50:AA50) -> 192600 | AC50: 1 | AD50: =$AC50*P50*(1+$AD$4) -> 17013 | AE50: =$AC50*Q50*(1+$AD$4) -> 17013 | AF50: =$AC50*R50*(1+$AD$4) -> 17013 | AG50: =$AC50*S50*(1+$AD$4) -> 17013 | AH50: =$AC50*T50*(1+$AD$4) -> 17013 | AI50: =$AC50*U50*(1+$AD$4) -> 17013 | AJ50: =$AC50*V50*(1+$AD$4) -> 17013 | AK50: =$AC50*W50*(1+$AD$4) -> 17013 | ... AO50: =$AC50*AA50*(1+$AD$4) -> 17013 | AP50: =SUM(AD50:AO50) -> 204156 | AQ50: 1 | AR50: =$AQ50*AD50*(1+$AR$4) -> 18033.78 | AS50: =$AQ50*AE50*(1+$AR$4) -> 18033.78 | AT50: =$AQ50*AF50*(1+$AR$4) -> 18033.78 | AU50: =$AQ50*AG50*(1+$AR$4) -> 18033.78 | AV50: =$AQ50*AH50*(1+$AR$4) -> 18033.78 | AW50: =$AQ50*AI50*(1+$AR$4) -> 18033.78 | AX50: =$AQ50*AJ50*(1+$AR$4) -> 18033.78 | AY50: =$AQ50*AK50*(1+$AR$4) -> 18033.78 | ... BC50: =$AQ50*AO50*(1+$AR$4) -> 18033.78 | BD50: =SUM(AR50:BC50) -> 216405.36 | BE50: 1 | BF50: =$BE50*AR50*(1+$BF$4) -> 19115.807 | BG50: =$BE50*AS50*(1+$BF$4) -> 19115.807 | BH50: =$BE50*AT50*(1+$BF$4) -> 19115.807 | BI50: =$BE50*AU50*(1+$BF$4) -> 19115.807 | BJ50: =$BE50*AV50*(1+$BF$4) -> 19115.807 | BK50: =$BE50*AW50*(1+$BF$4) -> 19115.807 | BL50: =$BE50*AX50*(1+$BF$4) -> 19115.807 | BM50: =$BE50*AY50*(1+$BF$4) -> 19115.807 | ... BQ50: =$BE50*BC50*(1+$BF$4) -> 19115.807 | BR50: =SUM(BF50:BQ50) -> 229389.68 | BS50: 1 | BT50: =$BS50*BF50*(1+$BT$4) -> 20262.755 | BU50: =$BS50*BG50*(1+$BT$4) -> 20262.755 | BV50: =$BS50*BH50*(1+$BT$4) -> 20262.755 | BW50: =$BS50*BI50*(1+$BT$4) -> 20262.755 | BX50: =$BS50*BJ50*(1+$BT$4) -> 20262.755 | BY50: =$BS50*BK50*(1+$BT$4) -> 20262.755 | BZ50: =$BS50*BL50*(1+$BT$4) -> 20262.755 | CA50: =$BS50*BM50*(1+$BT$4) -> 20262.755 | ... CE50: =$BS50*BQ50*(1+$BT$4) -> 20262.755 | CF50: =SUM(BT50:CE50) -> 243153.06 | CG50: 1 | CH50: =$CG50*BT50*(1+$CH$4) -> 21478.521 | CI50: =$CG50*BU50*(1+$CH$4) -> 21478.521 | CJ50: =$CG50*BV50*(1+$CH$4) -> 21478.521 | CK50: =$CG50*BW50*(1+$CH$4) -> 21478.521 | CL50: =$CG50*BX50*(1+$CH$4) -> 21478.521 | CM50: =$CG50*BY50*(1+$CH$4) -> 21478.521 | CN50: =$CG50*BZ50*(1+$CH$4) -> 21478.521 | CO50: =$CG50*CA50*(1+$CH$4) -> 21478.521 | ... CS50: =$CG50*CE50*(1+$CH$4) -> 21478.521 | CT50: =SUM(CH50:CS50) -> 257742.25 | CU50: 1 | CV50: =$CU50*CH50*(1+$CV$4) -> 22767.232 | CW50: =$CU50*CI50*(1+$CV$4) -> 22767.232 | CX50: =$CU50*CJ50*(1+$CV$4) -> 22767.232 | CY50: =$CU50*CK50*(1+$CV$4) -> 22767.232 | CZ50: =$CU50*CL50*(1+$CV$4) -> 22767.232 | DA50: =$CU50*CM50*(1+$CV$4) -> 22767.232 | DB50: =$CU50*CN50*(1+$CV$4) -> 22767.232 | DC50: =$CU50*CO50*(1+$CV$4) -> 22767.232 | ... DG50: =$CU50*CS50*(1+$CV$4) -> 22767.232 | DH50: =SUM(CV50:DG50) -> 273206.78 | DI50: 1 | DJ50: =$DI50*CV50*(1+$DJ$4) -> 24133.266 | DK50: =$DI50*CW50*(1+$DJ$4) -> 24133.266 | DL50: =$DI50*CX50*(1+$DJ$4) -> 24133.266 | DM50: =$DI50*CY50*(1+$DJ$4) -> 24133.266 | DN50: =$DI50*CZ50*(1+$DJ$4) -> 24133.266 | DO50: =$DI50*DA50*(1+$DJ$4) -> 24133.266 | DP50: =$DI50*DB50*(1+$DJ$4) -> 24133.266 | DQ50: =$DI50*DC50*(1+$DJ$4) -> 24133.266 | ... DU50: =$DI50*DG50*(1+$DJ$4) -> 24133.266 | DV50: =SUM(DJ50:DU50) -> 289599.19 | DW50: 1 | DX50: =$DW50*DJ50*(1+$DX$4) -> 25581.262 | DY50: =$DW50*DK50*(1+$DX$4) -> 25581.262 | DZ50: =$DW50*DL50*(1+$DX$4) -> 25581.262 | EA50: =$DW50*DM50*(1+$DX$4) -> 25581.262 | EB50: =$DW50*DN50*(1+$DX$4) -> 25581.262 | EC50: =$DW50*DO50*(1+$DX$4) -> 25581.262 | ED50: =$DW50*DP50*(1+$DX$4) -> 25581.262 | EE50: =$DW50*DQ50*(1+$DX$4) -> 25581.262 | ... EI50: =$DW50*DU50*(1+$DX$4) -> 25581.262 | EJ50: =SUM(DX50:EI50) -> 306975.14
A51: Encargado de ventas y distribución | B51: 10000 | C51: =B51*(1+C$3) -> 10000 | D51: =C51*(1+D$3) -> 10000 | E51: =D51*(1+E$3) -> 10000 | F51: =E51*(1+F$3) -> 10000 | G51: =F51*(1+G$3) -> 10000 | H51: =G51*(1+H$3) -> 10000 | I51: =H51*(1+I$3) -> 10000 | J51: =I51*(1+J$3) -> 10000 | ... M51: =L51*(1+M$3) -> 10000 | N51: =SUM(B51:M51) -> 120000 | O51: 1 | P51: =$O51*B51*(1+$P$3)*(1+$P$4) -> 11021 | Q51: =$O51*C51*(1+$P$3)*(1+$P$4) -> 11021 | R51: =$O51*D51*(1+$P$3)*(1+$P$4) -> 11021 | S51: =$O51*E51*(1+$P$3)*(1+$P$4) -> 11021 | T51: =$O51*F51*(1+$P$3)*(1+$P$4) -> 11021 | U51: =$O51*G51*(1+$P$3)*(1+$P$4) -> 11021 | V51: =$O51*H51*(1+$P$3)*(1+$P$4) -> 11021 | W51: =$O51*I51*(1+$P$3)*(1+$P$4) -> 11021 | ... AA51: =$O51*M51*(1+$P$3)*(1+$P$4) -> 11021 | AB51: =SUM(P51:AA51) -> 132252 | AC51: 1 | AD51: =$AC51*P51*(1+$AD$3)*(1+$AD$4) -> 12266.373 | AE51: =$AC51*Q51*(1+$AD$3)*(1+$AD$4) -> 12266.373 | AF51: =$AC51*R51*(1+$AD$3)*(1+$AD$4) -> 12266.373 | AG51: =$AC51*S51*(1+$AD$3)*(1+$AD$4) -> 12266.373 | AH51: =$AC51*T51*(1+$AD$3)*(1+$AD$4) -> 12266.373 | AI51: =$AC51*U51*(1+$AD$3)*(1+$AD$4) -> 12266.373 | AJ51: =$AC51*V51*(1+$AD$3)*(1+$AD$4) -> 12266.373 | AK51: =$AC51*W51*(1+$AD$3)*(1+$AD$4) -> 12266.373 | ... AO51: =$AC51*AA51*(1+$AD$3)*(1+$AD$4) -> 12266.373 | AP51: =SUM(AD51:AO51) -> 147196.48 | AQ51: 1 | AR51: =$AQ51*AD51*(1+$AR$3)*(1+$AR$4) -> 13652.473 | AS51: =$AQ51*AE51*(1+$AR$3)*(1+$AR$4) -> 13652.473 | AT51: =$AQ51*AF51*(1+$AR$3)*(1+$AR$4) -> 13652.473 | AU51: =$AQ51*AG51*(1+$AR$3)*(1+$AR$4) -> 13652.473 | AV51: =$AQ51*AH51*(1+$AR$3)*(1+$AR$4) -> 13652.473 | AW51: =$AQ51*AI51*(1+$AR$3)*(1+$AR$4) -> 13652.473 | AX51: =$AQ51*AJ51*(1+$AR$3)*(1+$AR$4) -> 13652.473 | AY51: =$AQ51*AK51*(1+$AR$3)*(1+$AR$4) -> 13652.473 | ... BC51: =$AQ51*AO51*(1+$AR$3)*(1+$AR$4) -> 13652.473 | BD51: =SUM(AR51:BC51) -> 163829.68 | BE51: 1 | BF51: =$BE51*AR51*(1+$BF$3)*(1+$BF$4) -> 15195.203 | BG51: =$BE51*AS51*(1+$BF$3)*(1+$BF$4) -> 15195.203 | BH51: =$BE51*AT51*(1+$BF$3)*(1+$BF$4) -> 15195.203 | BI51: =$BE51*AU51*(1+$BF$3)*(1+$BF$4) -> 15195.203 | BJ51: =$BE51*AV51*(1+$BF$3)*(1+$BF$4) -> 15195.203 | BK51: =$BE51*AW51*(1+$BF$3)*(1+$BF$4) -> 15195.203 | BL51: =$BE51*AX51*(1+$BF$3)*(1+$BF$4) -> 15195.203 | BM51: =$BE51*AY51*(1+$BF$3)*(1+$BF$4) -> 15195.203 | ... BQ51: =$BE51*BC51*(1+$BF$3)*(1+$BF$4) -> 15195.203 | BR51: =SUM(BF51:BQ51) -> 182342.43 | BS51: 1 | BT51: =$BS51*BF51*(1+$BT$3)*(1+$BT$4) -> 16912.261 | BU51: =$BS51*BG51*(1+$BT$3)*(1+$BT$4) -> 16912.261 | BV51: =$BS51*BH51*(1+$BT$3)*(1+$BT$4) -> 16912.261 | BW51: =$BS51*BI51*(1+$BT$3)*(1+$BT$4) -> 16912.261 | BX51: =$BS51*BJ51*(1+$BT$3)*(1+$BT$4) -> 16912.261 | BY51: =$BS51*BK51*(1+$BT$3)*(1+$BT$4) -> 16912.261 | BZ51: =$BS51*BL51*(1+$BT$3)*(1+$BT$4) -> 16912.261 | CA51: =$BS51*BM51*(1+$BT$3)*(1+$BT$4) -> 16912.261 | ... CE51: =$BS51*BQ51*(1+$BT$3)*(1+$BT$4) -> 16912.261 | CF51: =SUM(BT51:CE51) -> 202947.13 | CG51: 1 | CH51: =$CG51*BT51*(1+$CH$3)*(1+$CH$4) -> 18823.346 | CI51: =$CG51*BU51*(1+$CH$3)*(1+$CH$4) -> 18823.346 | CJ51: =$CG51*BV51*(1+$CH$3)*(1+$CH$4) -> 18823.346 | CK51: =$CG51*BW51*(1+$CH$3)*(1+$CH$4) -> 18823.346 | CL51: =$CG51*BX51*(1+$CH$3)*(1+$CH$4) -> 18823.346 | CM51: =$CG51*BY51*(1+$CH$3)*(1+$CH$4) -> 18823.346 | CN51: =$CG51*BZ51*(1+$CH$3)*(1+$CH$4) -> 18823.346 | CO51: =$CG51*CA51*(1+$CH$3)*(1+$CH$4) -> 18823.346 | ... CS51: =$CG51*CE51*(1+$CH$3)*(1+$CH$4) -> 18823.346 | CT51: =SUM(CH51:CS51) -> 225880.15 | CU51: 1 | CV51: =$CU51*CH51*(1+$CV$3)*(1+$CV$4) -> 20950.384 | CW51: =$CU51*CI51*(1+$CV$3)*(1+$CV$4) -> 20950.384 | CX51: =$CU51*CJ51*(1+$CV$3)*(1+$CV$4) -> 20950.384 | CY51: =$CU51*CK51*(1+$CV$3)*(1+$CV$4) -> 20950.384 | CZ51: =$CU51*CL51*(1+$CV$3)*(1+$CV$4) -> 20950.384 | DA51: =$CU51*CM51*(1+$CV$3)*(1+$CV$4) -> 20950.384 | DB51: =$CU51*CN51*(1+$CV$3)*(1+$CV$4) -> 20950.384 | DC51: =$CU51*CO51*(1+$CV$3)*(1+$CV$4) -> 20950.384 | ... DG51: =$CU51*CS51*(1+$CV$3)*(1+$CV$4) -> 20950.384 | DH51: =SUM(CV51:DG51) -> 251404.61 | DI51: 1 | DJ51: =$DI51*CV51*(1+$DJ$3)*(1+$DJ$4) -> 23317.777 | DK51: =$DI51*CW51*(1+$DJ$3)*(1+$DJ$4) -> 23317.777 | DL51: =$DI51*CX51*(1+$DJ$3)*(1+$DJ$4) -> 23317.777 | DM51: =$DI51*CY51*(1+$DJ$3)*(1+$DJ$4) -> 23317.777 | DN51: =$DI51*CZ51*(1+$DJ$3)*(1+$DJ$4) -> 23317.777 | DO51: =$DI51*DA51*(1+$DJ$3)*(1+$DJ$4) -> 23317.777 | DP51: =$DI51*DB51*(1+$DJ$3)*(1+$DJ$4) -> 23317.777 | DQ51: =$DI51*DC51*(1+$DJ$3)*(1+$DJ$4) -> 23317.777 | ... DU51: =$DI51*DG51*(1+$DJ$3)*(1+$DJ$4) -> 23317.777 | DV51: =SUM(DJ51:DU51) -> 279813.33 | DW51: 1 | DX51: =$DW51*DJ51*(1+$DX$3)*(1+$DX$4) -> 25952.686 | DY51: =$DW51*DK51*(1+$DX$3)*(1+$DX$4) -> 25952.686 | DZ51: =$DW51*DL51*(1+$DX$3)*(1+$DX$4) -> 25952.686 | EA51: =$DW51*DM51*(1+$DX$3)*(1+$DX$4) -> 25952.686 | EB51: =$DW51*DN51*(1+$DX$3)*(1+$DX$4) -> 25952.686 | EC51: =$DW51*DO51*(1+$DX$3)*(1+$DX$4) -> 25952.686 | ED51: =$DW51*DP51*(1+$DX$3)*(1+$DX$4) -> 25952.686 | EE51: =$DW51*DQ51*(1+$DX$3)*(1+$DX$4) -> 25952.686 | ... EI51: =$DW51*DU51*(1+$DX$3)*(1+$DX$4) -> 25952.686 | EJ51: =SUM(DX51:EI51) -> 311432.24
A52: 2.3. Gastos financieros | B52: =SUM(B53:B53) -> 0 | C52: =SUM(C53:C53) -> 0 | D52: =SUM(D53:D53) -> 0 | E52: =SUM(E53:E53) -> 0 | F52: =SUM(F53:F53) -> 0 | G52: =SUM(G53:G53) -> 0 | H52: =SUM(H53:H53) -> 0 | I52: =SUM(I53:I53) -> 0 | ... M52: =SUM(M53:M53) -> 0 | N52: =SUM(B52:M52) -> 0 | P52: =SUM(P53:P53) -> 0 | Q52: =SUM(Q53:Q53) -> 0 | R52: =SUM(R53:R53) -> 0 | S52: =SUM(S53:S53) -> 0 | T52: =SUM(T53:T53) -> 0 | U52: =SUM(U53:U53) -> 0 | V52: =SUM(V53:V53) -> 0 | W52: =SUM(W53:W53) -> 0 | ... AA52: =SUM(AA53:AA53) -> 0 | AB52: =SUM(P52:AA52) -> 0 | AD52: =SUM(AD53:AD53) -> 0 | AE52: =SUM(AE53:AE53) -> 0 | AF52: =SUM(AF53:AF53) -> 0 | AG52: =SUM(AG53:AG53) -> 0 | AH52: =SUM(AH53:AH53) -> 0 | AI52: =SUM(AI53:AI53) -> 0 | AJ52: =SUM(AJ53:AJ53) -> 0 | AK52: =SUM(AK53:AK53) -> 0 | ... AO52: =SUM(AO53:AO53) -> 0 | AP52: =SUM(AD52:AO52) -> 0 | AR52: =SUM(AR53:AR53) -> 0 | AS52: =SUM(AS53:AS53) -> 0 | AT52: =SUM(AT53:AT53) -> 0 | AU52: =SUM(AU53:AU53) -> 0 | AV52: =SUM(AV53:AV53) -> 0 | AW52: =SUM(AW53:AW53) -> 0 | AX52: =SUM(AX53:AX53) -> 0 | AY52: =SUM(AY53:AY53) -> 0 | ... BC52: =SUM(BC53:BC53) -> 0 | BD52: =SUM(AR52:BC52) -> 0 | BF52: =SUM(BF53:BF53) -> 0 | BG52: =SUM(BG53:BG53) -> 0 | BH52: =SUM(BH53:BH53) -> 0 | BI52: =SUM(BI53:BI53) -> 0 | BJ52: =SUM(BJ53:BJ53) -> 0 | BK52: =SUM(BK53:BK53) -> 0 | BL52: =SUM(BL53:BL53) -> 0 | BM52: =SUM(BM53:BM53) -> 0 | ... BQ52: =SUM(BQ53:BQ53) -> 0 | BR52: =SUM(BF52:BQ52) -> 0 | BT52: =SUM(BT53:BT53) -> 0 | BU52: =SUM(BU53:BU53) -> 0 | BV52: =SUM(BV53:BV53) -> 0 | BW52: =SUM(BW53:BW53) -> 0 | BX52: =SUM(BX53:BX53) -> 0 | BY52: =SUM(BY53:BY53) -> 0 | BZ52: =SUM(BZ53:BZ53) -> 0 | CA52: =SUM(CA53:CA53) -> 0 | ... CE52: =SUM(CE53:CE53) -> 0 | CF52: =SUM(BT52:CE52) -> 0 | CH52: =SUM(CH53:CH53) -> 0 | CI52: =SUM(CI53:CI53) -> 0 | CJ52: =SUM(CJ53:CJ53) -> 0 | CK52: =SUM(CK53:CK53) -> 0 | CL52: =SUM(CL53:CL53) -> 0 | CM52: =SUM(CM53:CM53) -> 0 | CN52: =SUM(CN53:CN53) -> 0 | CO52: =SUM(CO53:CO53) -> 0 | ... CS52: =SUM(CS53:CS53) -> 0 | CT52: =SUM(CH52:CS52) -> 0 | CV52: =SUM(CV53:CV53) -> 0 | CW52: =SUM(CW53:CW53) -> 0 | CX52: =SUM(CX53:CX53) -> 0 | CY52: =SUM(CY53:CY53) -> 0 | CZ52: =SUM(CZ53:CZ53) -> 0 | DA52: =SUM(DA53:DA53) -> 0 | DB52: =SUM(DB53:DB53) -> 0 | DC52: =SUM(DC53:DC53) -> 0 | ... DG52: =SUM(DG53:DG53) -> 0 | DH52: =SUM(CV52:DG52) -> 0 | DJ52: =SUM(DJ53:DJ53) -> 0 | DK52: =SUM(DK53:DK53) -> 0 | DL52: =SUM(DL53:DL53) -> 0 | DM52: =SUM(DM53:DM53) -> 0 | DN52: =SUM(DN53:DN53) -> 0 | DO52: =SUM(DO53:DO53) -> 0 | DP52: =SUM(DP53:DP53) -> 0 | DQ52: =SUM(DQ53:DQ53) -> 0 | ... DU52: =SUM(DU53:DU53) -> 0 | DV52: =SUM(DJ52:DU52) -> 0 | DX52: =SUM(DX53:DX53) -> 0 | DY52: =SUM(DY53:DY53) -> 0 | DZ52: =SUM(DZ53:DZ53) -> 0 | EA52: =SUM(EA53:EA53) -> 0 | EB52: =SUM(EB53:EB53) -> 0 | EC52: =SUM(EC53:EC53) -> 0 | ED52: =SUM(ED53:ED53) -> 0 | EE52: =SUM(EE53:EE53) -> 0 | ... EI52: =SUM(EI53:EI53) -> 0 | EJ52: =SUM(DX52:EI52) -> 0
A53: Intereses pagados por financiamiento | C53: =B53 -> 0 | D53: =C53 -> 0 | E53: =D53 -> 0 | F53: =E53 -> 0 | G53: =F53 -> 0 | H53: =G53 -> 0 | I53: =H53 -> 0 | J53: =I53 -> 0 | ... M53: =L53 -> 0 | N53: =SUM(B53:M53) -> 0 | O53: 1 | P53: =$O53*B53*(1+$P$4) -> 0 | Q53: =$O53*C53*(1+Q$4) -> 0 | R53: =$O53*D53*(1+R$4) -> 0 | S53: =$O53*E53*(1+S$4) -> 0 | T53: =$O53*F53*(1+T$4) -> 0 | U53: =$O53*G53*(1+U$4) -> 0 | V53: =$O53*H53*(1+V$4) -> 0 | W53: =$O53*I53*(1+W$4) -> 0 | X53: =$O53*J53*(1+X$4) -> 0 | ... AA53: =$O53*M53*(1+AA$4) -> 0 | AB53: =SUM(P53:AA53) -> 0 | AC53: 1 | AD53: =$AC53*P53*(1+$AD$4) -> 0 | AE53: =$AC53*Q53*(1+$AD$4) -> 0 | AF53: =$AC53*R53*(1+$AD$4) -> 0 | AG53: =$AC53*S53*(1+$AD$4) -> 0 | AH53: =$AC53*T53*(1+$AD$4) -> 0 | AI53: =$AC53*U53*(1+$AD$4) -> 0 | AJ53: =$AC53*V53*(1+$AD$4) -> 0 | AK53: =$AC53*W53*(1+$AD$4) -> 0 | ... AO53: =$AC53*AA53*(1+$AD$4) -> 0 | AP53: =SUM(AD53:AO53) -> 0 | AQ53: 1 | AR53: =$AQ53*AD53*(1+$AR$4) -> 0 | AS53: =$AQ53*AE53*(1+$AR$4) -> 0 | AT53: =$AQ53*AF53*(1+$AR$4) -> 0 | AU53: =$AQ53*AG53*(1+$AR$4) -> 0 | AV53: =$AQ53*AH53*(1+$AR$4) -> 0 | AW53: =$AQ53*AI53*(1+$AR$4) -> 0 | AX53: =$AQ53*AJ53*(1+$AR$4) -> 0 | AY53: =$AQ53*AK53*(1+$AR$4) -> 0 | ... BC53: =$AQ53*AO53*(1+$AR$4) -> 0 | BD53: =SUM(AR53:BC53) -> 0 | BE53: 1 | BF53: =$BE53*AR53*(1+$BF$4) -> 0 | BG53: =$BE53*AS53*(1+$BF$4) -> 0 | BH53: =$BE53*AT53*(1+$BF$4) -> 0 | BI53: =$BE53*AU53*(1+$BF$4) -> 0 | BJ53: =$BE53*AV53*(1+$BF$4) -> 0 | BK53: =$BE53*AW53*(1+$BF$4) -> 0 | BL53: =$BE53*AX53*(1+$BF$4) -> 0 | BM53: =$BE53*AY53*(1+$BF$4) -> 0 | ... BQ53: =$BE53*BC53*(1+$BF$4) -> 0 | BR53: =SUM(BF53:BQ53) -> 0 | BS53: 1 | BT53: =$BS53*BF53*(1+$BT$4) -> 0 | BU53: =$BS53*BG53*(1+$BT$4) -> 0 | BV53: =$BS53*BH53*(1+$BT$4) -> 0 | BW53: =$BS53*BI53*(1+$BT$4) -> 0 | BX53: =$BS53*BJ53*(1+$BT$4) -> 0 | BY53: =$BS53*BK53*(1+$BT$4) -> 0 | BZ53: =$BS53*BL53*(1+$BT$4) -> 0 | CA53: =$BS53*BM53*(1+$BT$4) -> 0 | ... CE53: =$BS53*BQ53*(1+$BT$4) -> 0 | CF53: =SUM(BT53:CE53) -> 0 | CG53: 1 | CH53: =$CG53*BT53*(1+$CH$4) -> 0 | CI53: =$CG53*BU53*(1+$CH$4) -> 0 | CJ53: =$CG53*BV53*(1+$CH$4) -> 0 | CK53: =$CG53*BW53*(1+$CH$4) -> 0 | CL53: =$CG53*BX53*(1+$CH$4) -> 0 | CM53: =$CG53*BY53*(1+$CH$4) -> 0 | CN53: =$CG53*BZ53*(1+$CH$4) -> 0 | CO53: =$CG53*CA53*(1+$CH$4) -> 0 | ... CS53: =$CG53*CE53*(1+$CH$4) -> 0 | CT53: =SUM(CH53:CS53) -> 0 | CU53: 1 | CV53: =$CU53*CH53*(1+$CV$4) -> 0 | CW53: =$CU53*CI53*(1+$CV$4) -> 0 | CX53: =$CU53*CJ53*(1+$CV$4) -> 0 | CY53: =$CU53*CK53*(1+$CV$4) -> 0 | CZ53: =$CU53*CL53*(1+$CV$4) -> 0 | DA53: =$CU53*CM53*(1+$CV$4) -> 0 | DB53: =$CU53*CN53*(1+$CV$4) -> 0 | DC53: =$CU53*CO53*(1+$CV$4) -> 0 | ... DG53: =$CU53*CS53*(1+$CV$4) -> 0 | DH53: =SUM(CV53:DG53) -> 0 | DI53: 1 | DJ53: =$DI53*CV53*(1+$DJ$4) -> 0 | DK53: =$DI53*CW53*(1+$DJ$4) -> 0 | DL53: =$DI53*CX53*(1+$DJ$4) -> 0 | DM53: =$DI53*CY53*(1+$DJ$4) -> 0 | DN53: =$DI53*CZ53*(1+$DJ$4) -> 0 | DO53: =$DI53*DA53*(1+$DJ$4) -> 0 | DP53: =$DI53*DB53*(1+$DJ$4) -> 0 | DQ53: =$DI53*DC53*(1+$DJ$4) -> 0 | ... DU53: =$DI53*DG53*(1+$DJ$4) -> 0 | DV53: =SUM(DJ53:DU53) -> 0 | DW53: 1 | DX53: =$DW53*DJ53*(1+$DX$4) -> 0 | DY53: =$DW53*DK53*(1+$DX$4) -> 0 | DZ53: =$DW53*DL53*(1+$DX$4) -> 0 | EA53: =$DW53*DM53*(1+$DX$4) -> 0 | EB53: =$DW53*DN53*(1+$DX$4) -> 0 | EC53: =$DW53*DO53*(1+$DX$4) -> 0 | ED53: =$DW53*DP53*(1+$DX$4) -> 0 | EE53: =$DW53*DQ53*(1+$DX$4) -> 0 | ... EI53: =$DW53*DU53*(1+$DX$4) -> 0 | EJ53: =SUM(DX53:EI53) -> 0
A54: Costos totales (CT) | B54: =B14+B41 -> 426490 | C54: =C14+C41 -> 426490 | D54: =D14+D41 -> 426490 | E54: =E14+E41 -> 426490 | F54: =F14+F41 -> 426490 | G54: =G14+G41 -> 426490 | H54: =H14+H41 -> 426490 | I54: =I14+I41 -> 426490 | ... M54: =M14+M41 -> 426490 | N54: =SUM(B54:M54) -> 5117880 | P54: =P14+P41 -> 465723.6 | Q54: =Q14+Q41 -> 465723.6 | R54: =R14+R41 -> 465723.6 | S54: =S14+S41 -> 465723.6 | T54: =T14+T41 -> 465723.6 | U54: =U14+U41 -> 465723.6 | V54: =V14+V41 -> 465723.6 | W54: =W14+W41 -> 465723.6 | ... AA54: =AA14+AA41 -> 465723.6 | AB54: =SUM(P54:AA54) -> 5588683.2 | AD54: =AD14+AD41 -> 510734.21 | AE54: =AE14+AE41 -> 510734.21 | AF54: =AF14+AF41 -> 510734.21 | AG54: =AG14+AG41 -> 510734.21 | AH54: =AH14+AH41 -> 510734.21 | AI54: =AI14+AI41 -> 510734.21 | AJ54: =AJ14+AJ41 -> 510734.21 | AK54: =AK14+AK41 -> 510734.21 | ... AO54: =AO14+AO41 -> 510734.21 | AP54: =SUM(AD54:AO54) -> 6128810.6 | AR54: =AR14+AR41 -> 560374.06 | AS54: =AS14+AS41 -> 560374.06 | AT54: =AT14+AT41 -> 560374.06 | AU54: =AU14+AU41 -> 560374.06 | AV54: =AV14+AV41 -> 560374.06 | AW54: =AW14+AW41 -> 560374.06 | AX54: =AX14+AX41 -> 560374.06 | AY54: =AY14+AY41 -> 560374.06 | ... BC54: =BC14+BC41 -> 560374.06 | BD54: =SUM(AR54:BC54) -> 6724488.7 | BF54: =BF14+BF41 -> 615138.82 | BG54: =BG14+BG41 -> 615138.82 | BH54: =BH14+BH41 -> 615138.82 | BI54: =BI14+BI41 -> 615138.82 | BJ54: =BJ14+BJ41 -> 615138.82 | BK54: =BK14+BK41 -> 615138.82 | BL54: =BL14+BL41 -> 615138.82 | BM54: =BM14+BM41 -> 615138.82 | ... BQ54: =BQ14+BQ41 -> 615138.82 | BR54: =SUM(BF54:BQ54) -> 7381665.8 | BT54: =BT14+BT41 -> 675578.54 | BU54: =BU14+BU41 -> 675578.54 | BV54: =BV14+BV41 -> 675578.54 | BW54: =BW14+BW41 -> 675578.54 | BX54: =BX14+BX41 -> 675578.54 | BY54: =BY14+BY41 -> 675578.54 | BZ54: =BZ14+BZ41 -> 675578.54 | CA54: =CA14+CA41 -> 675578.54 | ... CE54: =CE14+CE41 -> 675578.54 | CF54: =SUM(BT54:CE54) -> 8106942.5 | CH54: =CH14+CH41 -> 742303.7 | CI54: =CI14+CI41 -> 742303.7 | CJ54: =CJ14+CJ41 -> 742303.7 | CK54: =CK14+CK41 -> 742303.7 | CL54: =CL14+CL41 -> 742303.7 | CM54: =CM14+CM41 -> 742303.7 | CN54: =CN14+CN41 -> 742303.7 | CO54: =CO14+CO41 -> 742303.7 | ... CS54: =CS14+CS41 -> 742303.7 | CT54: =SUM(CH54:CS54) -> 8907644.4 | CV54: =CV14+CV41 -> 815991.89 | CW54: =CW14+CW41 -> 815991.89 | CX54: =CX14+CX41 -> 815991.89 | CY54: =CY14+CY41 -> 815991.89 | CZ54: =CZ14+CZ41 -> 815991.89 | DA54: =DA14+DA41 -> 815991.89 | DB54: =DB14+DB41 -> 815991.89 | DC54: =DC14+DC41 -> 815991.89 | ... DG54: =DG14+DG41 -> 815991.89 | DH54: =SUM(CV54:DG54) -> 9791902.6 | DJ54: =DJ14+DJ41 -> 897395.31 | DK54: =DK14+DK41 -> 897395.31 | DL54: =DL14+DL41 -> 897395.31 | DM54: =DM14+DM41 -> 897395.31 | DN54: =DN14+DN41 -> 897395.31 | DO54: =DO14+DO41 -> 897395.31 | DP54: =DP14+DP41 -> 897395.31 | DQ54: =DQ14+DQ41 -> 897395.31 | ... DU54: =DU14+DU41 -> 897395.31 | DV54: =SUM(DJ54:DU54) -> 10768744 | DX54: =DX14+DX41 -> 987349.1 | DY54: =DY14+DY41 -> 987349.1 | DZ54: =DZ14+DZ41 -> 987349.1 | EA54: =EA14+EA41 -> 987349.1 | EB54: =EB14+EB41 -> 987349.1 | EC54: =EC14+EC41 -> 987349.1 | ED54: =ED14+ED41 -> 987349.1 | EE54: =EE14+EE41 -> 987349.1 | ... EI54: =EI14+EI41 -> 987349.1 | EJ54: =SUM(DX54:EI54) -> 11848189
A55: CAPITAL DE TRABAJO | B55: AÑO 1 | P55: AÑO 2 | AD55: Año 3 | AR55: AÑO 4 | BF55: AÑO 5 | BT55: AÑO 6 | CH55: AÑO 7 | CV55: AÑO 8 | DJ55: AÑO 9 | DX55: AÑO 10
